Workbook

Sheet README
A1: Instruction | B1: Detail
A2: 1. Defensible Deletion Proof | B2: Every target in this list has zero METADATA activity (writes/modifications) for at least 365 days.
A3: 2. How to Validate Storage | B3: Run the SQL in the [Validation SQL (Storage)] column to verify the size and absolute last modified date.
A4: 3. How to Validate Usage | B4: Run the SQL in the [Validation SQL (Read/Usage)] column. If it returns 0 rows, NO ONE has queried this dataset in 180 days.
A5: 4. Safe Deletion Process | B5: Instead of DROP, consider setting a 7-day expiration (the "Scream Test"). If no one complains, the data auto-deletes.
A6: 5. Access Issues | B6: Refer to the [AccessIssues] sheet for a list of projects where the audit service account lacks permissions.
A9: Category | B9: Definition | C9: Detail
A10: Tranche 1 | B10: Stale Test/Temp | C10: Datasets with "test/temp/tmp" in the name AND no access in 180 days. Immediate deletion candidates.
A11: Tranche 2 | B11: High Saving Stale | C11: Production datasets > 100GB with no access in 180 days. Primary target for cost reduction.
A12: Tranche 3 | B12: Stale Production | C12: Small production datasets with no access in 180 days.
A13: Tranche 4 | B13: Active Test/Temp | C13: Datasets with "test/temp/tmp" in name but HAVE access history. Review for housekeeping.
A14: Column: Description | B14: Dataset Metadata | C14: Pulled from BigQuery SCHEMATA_OPTIONS. Helps identify ownership/purpose.
A15: Column: Last 5 Access | B15: Audit Trail | C15: Shows the most recent 5 jobs (Read or Write) including the user email and time.
A16: Column: Monthly Cost | B16: Financial Impact | C16: Estimated based on $0.02 per GB per month (standard logical storage).
A17: thg-influencer | B17: Inividual Project | C17: Charlie Stringer to review
A18: thg-ingenuity | B18: Inividual Project | C18: Charlie Stringer to review
A19: thg-central-marketing | B19: Inividual Project | C19: Charlie Stringer to review
A20: thg-seoclarity | B20: Inividual Project | C20: Charlie Stringer to review

Sheet Dashboard
A1: BigQuery Data Estate Cleanup — Dashboard
A2: Source: BQ-added-Data sheet
A4: KEY METRICS | D4: BY TRANCHE | S4: Full Name | T4: Short Name
A5: Total Datasets | B5: =COUNTA('BQ-added-Data'!A2:A2098) -> 2097 | D5: Tranche | E5: # Datasets | F5: Size (GB) | G5: Monthly Cost ($) | H5: Annual ($) | S5: =D6 -> Tranche 1: Abandoned Test/Temp (>1yr) | T5: T1
A6: Total Size (GB) | B6: =SUM('BQ-added-Data'!E2:E2098) -> 2164100.2 | D6: Tranche 1: Abandoned Test/Temp (>1yr) | E6: =COUNTIF('BQ-added-Data'!G:G,D6) -> 30 | F6: =SUMIF('BQ-added-Data'!G:G,D6,'BQ-added-Data'!E:E) -> 27106.86 | G6: =SUMIF('BQ-added-Data'!G:G,D6,'BQ-added-Data'!F:F) -> 542.15 | H6: =G6*12 -> 6505.8 | S6: =D7 -> Tranche 1.1: Abandoned Test/Temp (>1yr) | T6: T1.1
A7: Total Size (TB) | B7: =B6/1024 -> 2113.3791 | D7: Tranche 1.1: Abandoned Test/Temp (>1yr) | E7: =COUNTIF('BQ-added-Data'!G:G,"Tranche 1.1: Abandoned Test/Temp (>1yr)") -> 7 | F7: =SUMIF('BQ-added-Data'!G:G,"Tranche 1.1: Abandoned Test/Temp (>1yr)",'BQ-added-Data'!E:E) -> 387.33 | G7: =SUMIF('BQ-added-Data'!G:G,"Tranche 1.1: Abandoned Test/Temp (>1yr)",'BQ-added-Data'!F:F) -> 7.75 | H7: =G7*12 -> 93 | S7: =D9 -> Tranche 2: Abandoned Large Prod (>1yr) | T7: T2
A8: Monthly Cost ($) | B8: =SUM('BQ-added-Data'!F2:F2098) -> 43281.69 | D8: Tranche 1 Subtotal | E8: =SUM(E6:E7) -> 37 | F8: =SUM(F6:F7) -> 27494.19 | G8: =SUM(G6:G7) -> 549.9 | H8: =G8*12 -> 6598.8 | S8: =D10 -> Tranche 2.1: Abandoned Large Prod (>1yr) | T8: T2.1
A9: Annualised Cost ($) | B9: =B8*12 -> 519380.28 | D9: Tranche 2: Abandoned Large Prod (>1yr) | E9: =COUNTIF('BQ-added-Data'!G:G,D9) -> 151 | F9: =SUMIF('BQ-added-Data'!G:G,D9,'BQ-added-Data'!E:E) -> 436588.6 | G9: =SUMIF('BQ-added-Data'!G:G,D9,'BQ-added-Data'!F:F) -> 8731.75 | H9: =G9*12 -> 104781 | S9: =D12 -> Tranche 3: Abandoned Small Prod (>1yr) | T9: T3
A10: Critical Priority Datasets | B10: =COUNTIF('BQ-added-Data'!H2:H2098,"Critical") -> 218 | D10: Tranche 2.1: Abandoned Large Prod (>1yr) | E10: =COUNTIF('BQ-added-Data'!G:G,"Tranche 2.1: Abandoned Large Prod (>1yr)") -> 23 | F10: =SUMIF('BQ-added-Data'!G:G,"Tranche 2.1: Abandoned Large Prod (>1yr)",'BQ-added-Data'!E:E) -> 9093.22 | G10: =SUMIF('BQ-added-Data'!G:G,"Tranche 2.1: Abandoned Large Prod (>1yr)",'BQ-added-Data'!F:F) -> 181.84 | H10: =G10*12 -> 2182.08 | S10: =D13 -> Tranche 3.1: Abandoned Small Prod (>1yr) | T10: T3.1
A11: Defensible Deletion Confirmed | B11: =COUNTIF('BQ-added-Data'!P2:P2098,"CONFIRMED: NO MODS > 1YR") -> 310 | D11: Tranche 2 Subtotal | E11: =SUM(E9:E10) -> 174 | F11: =SUM(F9:F10) -> 445681.82 | G11: =SUM(G9:G10) -> 8913.59 | H11: =G11*12 -> 106963.08 | S11: =D15 -> Tranche 4: Stale (No Access 180d, No Write >6mo) | T11: T4
A12: Distinct Projects | B12: {=SUMPRODUCT((('BQ-added-Data'!A2:A2098)<>"")/COUNTIF('BQ-added-Data'!A2:A2098,'BQ-added-Data'!A2:A2098&""))} -> 29 | D12: Tranche 3: Abandoned Small Prod (>1yr) | E12: =COUNTIF('BQ-added-Data'!G:G,D12) -> 643 | F12: =SUMIF('BQ-added-Data'!G:G,D12,'BQ-added-Data'!E:E) -> 7629.44 | G12: =SUMIF('BQ-added-Data'!G:G,D12,'BQ-added-Data'!F:F) -> 152.54 | H12: =G12*12 -> 1830.48 | S12: =D16 -> Tranche 4.1: Stale (No Access 180d, No Write >6mo) | T12: T4.1
D13: Tranche 3.1: Abandoned Small Prod (>1yr) | E13: =COUNTIF('BQ-added-Data'!G:G,"Tranche 3.1: Abandoned Small Prod (>1yr)") -> 367 | F13: =SUMIF('BQ-added-Data'!G:G,"Tranche 3.1: Abandoned Small Prod (>1yr)",'BQ-added-Data'!E:E) -> 3743.34 | G13: =SUMIF('BQ-added-Data'!G:G,"Tranche 3.1: Abandoned Small Prod (>1yr)",'BQ-added-Data'!F:F) -> 74.79 | H13: =G13*12 -> 897.48 | S13: =D18 -> Tranche 5: Active Test (Housekeeping) | T13: T5
D14: Tranche 3 Subtotal | E14: =SUM(E12:E13) -> 1010 | F14: =SUM(F12:F13) -> 11372.78 | G14: =SUM(G12:G13) -> 227.33 | H14: =G14*12 -> 2727.96 | S14: =D19 -> Tranche 5.1: Active Test (Housekeeping) | T14: T5.1
D15: Tranche 4: Stale (No Access 180d, No Write >6mo) | E15: =COUNTIF('BQ-added-Data'!G:G,D15) -> 20 | F15: =SUMIF('BQ-added-Data'!G:G,D15,'BQ-added-Data'!E:E) -> 4833.92 | G15: =SUMIF('BQ-added-Data'!G:G,D15,'BQ-added-Data'!F:F) -> 96.69 | H15: =G15*12 -> 1160.28 | S15: =D21 -> Active | T15: Active
D16: Tranche 4.1: Stale (No Access 180d, No Write >6mo) | E16: =COUNTIF('BQ-added-Data'!G:G,"Tranche 4.1: Stale (No Access 180d, No Write >6mo)") -> 19 | F16: =SUMIF('BQ-added-Data'!G:G,"Tranche 4.1: Stale (No Access 180d, No Write >6mo)",'BQ-added-Data'!E:E) -> 349.04 | G16: =SUMIF('BQ-added-Data'!G:G,"Tranche 4.1: Stale (No Access 180d, No Write >6mo)",'BQ-added-Data'!F:F) -> 6.99 | H16: =G16*12 -> 83.88 | S16: Low | T16: =G19 -> 35.82
D17: Tranche 4 Subtotal | E17: =SUM(E15:E16) -> 39 | F17: =SUM(F15:F16) -> 5182.96 | G17: =SUM(G15:G16) -> 103.68 | H17: =G17*12 -> 1244.16
D18: Tranche 5: Active Test (Housekeeping) | E18: =COUNTIF('BQ-added-Data'!G:G,D18) -> 44 | F18: =SUMIF('BQ-added-Data'!G:G,D18,'BQ-added-Data'!E:E) -> 27262.73 | G18: =SUMIF('BQ-added-Data'!G:G,D18,'BQ-added-Data'!F:F) -> 545.25 | H18: =G18*12 -> 6543 | S18: Project | T18: Monthly $
D19: Tranche 5.1: Active Test (Housekeeping) | E19: =COUNTIF('BQ-added-Data'!G:G,"Tranche 5.1: Active Test (Housekeeping)") -> 5 | F19: =SUMIF('BQ-added-Data'!G:G,"Tranche 5.1: Active Test (Housekeeping)",'BQ-added-Data'!E:E) -> 1791.03 | G19: =SUMIF('BQ-added-Data'!G:G,"Tranche 5.1: Active Test (Housekeeping)",'BQ-added-Data'!F:F) -> 35.82 | H19: =G19*12 -> 429.84 | S19: =D24 -> agile-bonbon-662 | T19: =G24 -> 14855.31
D20: Tranche 5 Subtotal | E20: =SUM(E18:E19) -> 49 | F20: =SUM(F18:F19) -> 29053.76 | G20: =SUM(G18:G19) -> 581.07 | H20: =G20*12 -> 6972.84 | S20: =D25 -> thg-ingenuity | T20: =G25 -> 890.72
D21: Active | E21: =COUNTIF('BQ-added-Data'!G:G,D21) -> 788 | F21: =SUMIF('BQ-added-Data'!G:G,D21,'BQ-added-Data'!E:E) -> 1645314.7 | G21: =SUMIF('BQ-added-Data'!G:G,D21,'BQ-added-Data'!F:F) -> 32906.12 | H21: =G21*12 -> 394873.44 | S21: =D26 -> the-hut-group | T21: =G26 -> 15712.67
D22: TOTAL | E22: =E8+E11+E14+E17+E20+E21 -> 2097 | F22: =F8+F11+F14+F17+F20+F21 -> 2164100.2 | G22: =G8+G11+G14+G17+G20+G21 -> 43281.69 | H22: =G22*12 -> 519380.28 | S22: =D27 -> vibrant-map-107910 | T22: =G27 -> 2953.03
D23: Project | E23: # Datasets | F23: Size (GB) | G23: Monthly Cost ($) | H23: Annual ($) | S23: =D28 -> thg-beauty | T23: =G28 -> 953.12
D24: agile-bonbon-662 | E24: =COUNTIF('BQ-added-Data'!A:A,D24) -> 915 | F24: =SUMIF('BQ-added-Data'!A:A,D24,'BQ-added-Data'!E:E) -> 742768.12 | G24: =SUMIF('BQ-added-Data'!A:A,D24,'BQ-added-Data'!F:F) -> 14855.31 | H24: =G24*12 -> 178263.72 | S24: =D29 -> thg-ml-dev | T24: =G29 -> 252.36
D25: thg-ingenuity | E25: =COUNTIF('BQ-added-Data'!A:A,D25) -> 534 | F25: =SUMIF('BQ-added-Data'!A:A,D25,'BQ-added-Data'!E:E) -> 44539.12 | G25: =SUMIF('BQ-added-Data'!A:A,D25,'BQ-added-Data'!F:F) -> 890.72 | H25: =G25*12 -> 10688.64 | S25: =D30 -> thg-central-marketing | T25: =G30 -> 3501.61
D26: the-hut-group | E26: =COUNTIF('BQ-added-Data'!A:A,D26) -> 114 | F26: =SUMIF('BQ-added-Data'!A:A,D26,'BQ-added-Data'!E:E) -> 785636.05 | G26: =SUMIF('BQ-added-Data'!A:A,D26,'BQ-added-Data'!F:F) -> 15712.67 | H26: =G26*12 -> 188552.04 | S26: =D31 -> thg-influencer | T26: =G31 -> 32.52
D27: vibrant-map-107910 | E27: =COUNTIF('BQ-added-Data'!A:A,D27) -> 79 | F27: =SUMIF('BQ-added-Data'!A:A,D27,'BQ-added-Data'!E:E) -> 147651.32 | G27: =SUMIF('BQ-added-Data'!A:A,D27,'BQ-added-Data'!F:F) -> 2953.03 | H27: =G27*12 -> 35436.36 | S27: =D32 -> thg-content | T27: =G32 -> 70.52
D28: thg-beauty | E28: =COUNTIF('BQ-added-Data'!A:A,D28) -> 145 | F28: =SUMIF('BQ-added-Data'!A:A,D28,'BQ-added-Data'!E:E) -> 47656.57 | G28: =SUMIF('BQ-added-Data'!A:A,D28,'BQ-added-Data'!F:F) -> 953.12 | H28: =G28*12 -> 11437.44 | S28: =D33 -> thg-seoclarity | T28: =G33 -> 45.7
D29: thg-ml-dev | E29: =COUNTIF('BQ-added-Data'!A:A,D29) -> 60 | F29: =SUMIF('BQ-added-Data'!A:A,D29,'BQ-added-Data'!E:E) -> 12618.19 | G29: =SUMIF('BQ-added-Data'!A:A,D29,'BQ-added-Data'!F:F) -> 252.36 | H29: =G29*12 -> 3028.32 | S29: All Others | T29: =G34 -> -39115.02
D30: thg-central-marketing | E30: =COUNTIF('BQ-added-Data'!A:A,D30) -> 66 | F30: =SUMIF('BQ-added-Data'!A:A,D30,'BQ-added-Data'!E:E) -> 175082.62 | G30: =SUMIF('BQ-added-Data'!A:A,D30,'BQ-added-Data'!F:F) -> 3501.61 | H30: =G30*12 -> 42019.32
D31: thg-influencer | E31: =COUNTIF('BQ-added-Data'!A:A,D31) -> 54 | F31: =SUMIF('BQ-added-Data'!A:A,D31,'BQ-added-Data'!E:E) -> 1628.41 | G31: =SUMIF('BQ-added-Data'!A:A,D31,'BQ-added-Data'!F:F) -> 32.52 | H31: =G31*12 -> 390.24
D32: thg-content | E32: =COUNTIF('BQ-added-Data'!A:A,D32) -> 5 | F32: =SUMIF('BQ-added-Data'!A:A,D32,'BQ-added-Data'!E:E) -> 3526.35 | G32: =SUMIF('BQ-added-Data'!A:A,D32,'BQ-added-Data'!F:F) -> 70.52 | H32: =G32*12 -> 846.24
D33: thg-seoclarity | E33: =COUNTIF('BQ-added-Data'!A:A,D33) -> 2 | F33: =SUMIF('BQ-added-Data'!A:A,D33,'BQ-added-Data'!E:E) -> 2285.07 | G33: =SUMIF('BQ-added-Data'!A:A,D33,'BQ-added-Data'!F:F) -> 45.7 | H33: =G33*12 -> 548.4
D34: All Others | E34: =E12-SUM(E24:E33) -> -1331 | F34: =F12-SUM(F24:F33) -> -1955762.4 | G34: =G12-SUM(G24:G33) -> -39115.02 | H34: =G34*12 -> -469380.24
D35: TOTAL | E35: =SUM(E24:E34) -> 643 | F35: =SUM(F24:F34) -> 7629.44 | G35: =SUM(G24:G34) -> 152.54 | H35: =SUM(H24:H34) -> 1830.48
A38: TOP 20 CLEANUP CANDIDATES BY MONTHLY COST (excl. Active prod)
A39: Rank | B39: Project | C39: Dataset | D39: Tranche | E39: Priority | F39: Size (GB) | G39: Monthly $ | H39: Annual $
A40: 1 | B40: {=INDEX('BQ-added-Data'!$A:$A,MATCH(LARGE('BQ-added-Data'!#REF!-ROW('BQ-added-Data'!#REF!)/10^10,$A40),'BQ-added-Data'!#REF!-ROW('BQ-added-Data'!#REF!)/10^10,0)+1)} -> #REF! | C40: {=INDEX('BQ-added-Data'!$C:$C,MATCH(LARGE('BQ-added-Data'!#REF!-ROW('BQ-added-Data'!#REF!)/10^10,$A40),'BQ-added-Data'!#REF!-ROW('BQ-added-Data'!#REF!)/10^10,0)+1)} -> #REF! | D40: {=INDEX('BQ-added-Data'!$G:$G,MATCH(LARGE('BQ-added-Data'!#REF!-ROW('BQ-added-Data'!#REF!)/10^10,$A40),'BQ-added-Data'!#REF!-ROW('BQ-added-Data'!#REF!)/10^10,0)+1)} -> #REF! | E40: {=INDEX('BQ-added-Data'!$H:$H,MATCH(LARGE('BQ-added-Data'!#REF!-ROW('BQ-added-Data'!#REF!)/10^10,$A40),'BQ-added-Data'!#REF!-ROW('BQ-added-Data'!#REF!)/10^10,0)+1)} -> #REF! | F40: {=INDEX('BQ-added-Data'!$E:$E,MATCH(LARGE('BQ-added-Data'!#REF!-ROW('BQ-added-Data'!#REF!)/10^10,$A40),'BQ-added-Data'!#REF!-ROW('BQ-added-Data'!#REF!)/10^10,0)+1)} -> #REF! | G40: {=INDEX('BQ-added-Data'!$F:$F,MATCH(LARGE('BQ-added-Data'!#REF!-ROW('BQ-added-Data'!#REF!)/10^10,$A40),'BQ-added-Data'!#REF!-ROW('BQ-added-Data'!#REF!)/10^10,0)+1)} -> #REF! | H40: =G40*12 -> #REF!
A41: 2 | B41: {=INDEX('BQ-added-Data'!$A:$A,MATCH(LARGE('BQ-added-Data'!#REF!-ROW('BQ-added-Data'!#REF!)/10^10,$A41),'BQ-added-Data'!#REF!-ROW('BQ-added-Data'!#REF!)/10^10,0)+1)} -> #REF! | C41: {=INDEX('BQ-added-Data'!$C:$C,MATCH(LARGE('BQ-added-Data'!#REF!-ROW('BQ-added-Data'!#REF!)/10^10,$A41),'BQ-added-Data'!#REF!-ROW('BQ-added-Data'!#REF!)/10^10,0)+1)} -> #REF! | D41: {=INDEX('BQ-added-Data'!$G:$G,MATCH(LARGE('BQ-added-Data'!#REF!-ROW('BQ-added-Data'!#REF!)/10^10,$A41),'BQ-added-Data'!#REF!-ROW('BQ-added-Data'!#REF!)/10^10,0)+1)} -> #REF! | E41: {=INDEX('BQ-added-Data'!$H:$H,MATCH(LARGE('BQ-added-Data'!#REF!-ROW('BQ-added-Data'!#REF!)/10^10,$A41),'BQ-added-Data'!#REF!-ROW('BQ-added-Data'!#REF!)/10^10,0)+1)} -> #REF! | F41: {=INDEX('BQ-added-Data'!$E:$E,MATCH(LARGE('BQ-added-Data'!#REF!-ROW('BQ-added-Data'!#REF!)/10^10,$A41),'BQ-added-Data'!#REF!-ROW('BQ-added-Data'!#REF!)/10^10,0)+1)} -> #REF! | G41: {=INDEX('BQ-added-Data'!$F:$F,MATCH(LARGE('BQ-added-Data'!#REF!-ROW('BQ-added-Data'!#REF!)/10^10,$A41),'BQ-added-Data'!#REF!-ROW('BQ-added-Data'!#REF!)/10^10,0)+1)} -> #REF! | H41: =G41*12 -> #REF!
A42: 3 | B42: {=INDEX('BQ-added-Data'!$A:$A,MATCH(LARGE('BQ-added-Data'!#REF!-ROW('BQ-added-Data'!#REF!)/10^10,$A42),'BQ-added-Data'!#REF!-ROW('BQ-added-Data'!#REF!)/10^10,0)+1)} -> #REF! | C42: {=INDEX('BQ-added-Data'!$C:$C,MATCH(LARGE('BQ-added-Data'!#REF!-ROW('BQ-added-Data'!#REF!)/10^10,$A42),'BQ-added-Data'!#REF!-ROW('BQ-added-Data'!#REF!)/10^10,0)+1)} -> #REF! | D42: {=INDEX('BQ-added-Data'!$G:$G,MATCH(LARGE('BQ-added-Data'!#REF!-ROW('BQ-added-Data'!#REF!)/10^10,$A42),'BQ-added-Data'!#REF!-ROW('BQ-added-Data'!#REF!)/10^10,0)+1)} -> #REF! | E42: {=INDEX('BQ-added-Data'!$H:$H,MATCH(LARGE('BQ-added-Data'!#REF!-ROW('BQ-added-Data'!#REF!)/10^10,$A42),'BQ-added-Data'!#REF!-ROW('BQ-added-Data'!#REF!)/10^10,0)+1)} -> #REF! | F42: {=INDEX('BQ-added-Data'!$E:$E,MATCH(LARGE('BQ-added-Data'!#REF!-ROW('BQ-added-Data'!#REF!)/10^10,$A42),'BQ-added-Data'!#REF!-ROW('BQ-added-Data'!#REF!)/10^10,0)+1)} -> #REF! | G42: {=INDEX('BQ-added-Data'!$F:$F,MATCH(LARGE('BQ-added-Data'!#REF!-ROW('BQ-added-Data'!#REF!)/10^10,$A42),'BQ-added-Data'!#REF!-ROW('BQ-added-Data'!#REF!)/10^10,0)+1)} -> #REF! | H42: =G42*12 -> #REF!
A43: 4 | B43: {=INDEX('BQ-added-Data'!$A:$A,MATCH(LARGE('BQ-added-Data'!#REF!-ROW('BQ-added-Data'!#REF!)/10^10,$A43),'BQ-added-Data'!#REF!-ROW('BQ-added-Data'!#REF!)/10^10,0)+1)} -> #REF! | C43: {=INDEX('BQ-added-Data'!$C:$C,MATCH(LARGE('BQ-added-Data'!#REF!-ROW('BQ-added-Data'!#REF!)/10^10,$A43),'BQ-added-Data'!#REF!-ROW('BQ-added-Data'!#REF!)/10^10,0)+1)} -> #REF! | D43: {=INDEX('BQ-added-Data'!$G:$G,MATCH(LARGE('BQ-added-Data'!#REF!-ROW('BQ-added-Data'!#REF!)/10^10,$A43),'BQ-added-Data'!#REF!-ROW('BQ-added-Data'!#REF!)/10^10,0)+1)} -> #REF! | E43: {=INDEX('BQ-added-Data'!$H:$H,MATCH(LARGE('BQ-added-Data'!#REF!-ROW('BQ-added-Data'!#REF!)/10^10,$A43),'BQ-added-Data'!#REF!-ROW('BQ-added-Data'!#REF!)/10^10,0)+1)} -> #REF! | F43: {=INDEX('BQ-added-Data'!$E:$E,MATCH(LARGE('BQ-added-Data'!#REF!-ROW('BQ-added-Data'!#REF!)/10^10,$A43),'BQ-added-Data'!#REF!-ROW('BQ-added-Data'!#REF!)/10^10,0)+1)} -> #REF! | G43: {=INDEX('BQ-added-Data'!$F:$F,MATCH(LARGE('BQ-added-Data'!#REF!-ROW('BQ-added-Data'!#REF!)/10^10,$A43),'BQ-added-Data'!#REF!-ROW('BQ-added-Data'!#REF!)/10^10,0)+1)} -> #REF! | H43: =G43*12 -> #REF!
A44: 5 | B44: {=INDEX('BQ-added-Data'!$A:$A,MATCH(LARGE('BQ-added-Data'!#REF!-ROW('BQ-added-Data'!#REF!)/10^10,$A44),'BQ-added-Data'!#REF!-ROW('BQ-added-Data'!#REF!)/10^10,0)+1)} -> #REF! | C44: {=INDEX('BQ-added-Data'!$C:$C,MATCH(LARGE('BQ-added-Data'!#REF!-ROW('BQ-added-Data'!#REF!)/10^10,$A44),'BQ-added-Data'!#REF!-ROW('BQ-added-Data'!#REF!)/10^10,0)+1)} -> #REF! | D44: {=INDEX('BQ-added-Data'!$G:$G,MATCH(LARGE('BQ-added-Data'!#REF!-ROW('BQ-added-Data'!#REF!)/10^10,$A44),'BQ-added-Data'!#REF!-ROW('BQ-added-Data'!#REF!)/10^10,0)+1)} -> #REF! | E44: {=INDEX('BQ-added-Data'!$H:$H,MATCH(LARGE('BQ-added-Data'!#REF!-ROW('BQ-added-Data'!#REF!)/10^10,$A44),'BQ-added-Data'!#REF!-ROW('BQ-added-Data'!#REF!)/10^10,0)+1)} -> #REF! | F44: {=INDEX('BQ-added-Data'!$E:$E,MATCH(LARGE('BQ-added-Data'!#REF!-ROW('BQ-added-Data'!#REF!)/10^10,$A44),'BQ-added-Data'!#REF!-ROW('BQ-added-Data'!#REF!)/10^10,0)+1)} -> #REF! | G44: {=INDEX('BQ-added-Data'!$F:$F,MATCH(LARGE('BQ-added-Data'!#REF!-ROW('BQ-added-Data'!#REF!)/10^10,$A44),'BQ-added-Data'!#REF!-ROW('BQ-added-Data'!#REF!)/10^10,0)+1)} -> #REF! | H44: =G44*12 -> #REF!
A45: 6 | B45: {=INDEX('BQ-added-Data'!$A:$A,MATCH(LARGE('BQ-added-Data'!#REF!-ROW('BQ-added-Data'!#REF!)/10^10,$A45),'BQ-added-Data'!#REF!-ROW('BQ-added-Data'!#REF!)/10^10,0)+1)} -> #REF! | C45: {=INDEX('BQ-added-Data'!$C:$C,MATCH(LARGE('BQ-added-Data'!#REF!-ROW('BQ-added-Data'!#REF!)/10^10,$A45),'BQ-added-Data'!#REF!-ROW('BQ-added-Data'!#REF!)/10^10,0)+1)} -> #REF! | D45: {=INDEX('BQ-added-Data'!$G:$G,MATCH(LARGE('BQ-added-Data'!#REF!-ROW('BQ-added-Data'!#REF!)/10^10,$A45),'BQ-added-Data'!#REF!-ROW('BQ-added-Data'!#REF!)/10^10,0)+1)} -> #REF! | E45: {=INDEX('BQ-added-Data'!$H:$H,MATCH(LARGE('BQ-added-Data'!#REF!-ROW('BQ-added-Data'!#REF!)/10^10,$A45),'BQ-added-Data'!#REF!-ROW('BQ-added-Data'!#REF!)/10^10,0)+1)} -> #REF! | F45: {=INDEX('BQ-added-Data'!$E:$E,MATCH(LARGE('BQ-added-Data'!#REF!-ROW('BQ-added-Data'!#REF!)/10^10,$A45),'BQ-added-Data'!#REF!-ROW('BQ-added-Data'!#REF!)/10^10,0)+1)} -> #REF! | G45: {=INDEX('BQ-added-Data'!$F:$F,MATCH(LARGE('BQ-added-Data'!#REF!-ROW('BQ-added-Data'!#REF!)/10^10,$A45),'BQ-added-Data'!#REF!-ROW('BQ-added-Data'!#REF!)/10^10,0)+1)} -> #REF! | H45: =G45*12 -> #REF!
A46: 7 | B46: {=INDEX('BQ-added-Data'!$A:$A,MATCH(LARGE('BQ-added-Data'!#REF!-ROW('BQ-added-Data'!#REF!)/10^10,$A46),'BQ-added-Data'!#REF!-ROW('BQ-added-Data'!#REF!)/10^10,0)+1)} -> #REF! | C46: {=INDEX('BQ-added-Data'!$C:$C,MATCH(LARGE('BQ-added-Data'!#REF!-ROW('BQ-added-Data'!#REF!)/10^10,$A46),'BQ-added-Data'!#REF!-ROW('BQ-added-Data'!#REF!)/10^10,0)+1)} -> #REF! | D46: {=INDEX('BQ-added-Data'!$G:$G,MATCH(LARGE('BQ-added-Data'!#REF!-ROW('BQ-added-Data'!#REF!)/10^10,$A46),'BQ-added-Data'!#REF!-ROW('BQ-added-Data'!#REF!)/10^10,0)+1)} -> #REF! | E46: {=INDEX('BQ-added-Data'!$H:$H,MATCH(LARGE('BQ-added-Data'!#REF!-ROW('BQ-added-Data'!#REF!)/10^10,$A46),'BQ-added-Data'!#REF!-ROW('BQ-added-Data'!#REF!)/10^10,0)+1)} -> #REF! | F46: {=INDEX('BQ-added-Data'!$E:$E,MATCH(LARGE('BQ-added-Data'!#REF!-ROW('BQ-added-Data'!#REF!)/10^10,$A46),'BQ-added-Data'!#REF!-ROW('BQ-added-Data'!#REF!)/10^10,0)+1)} -> #REF! | G46: {=INDEX('BQ-added-Data'!$F:$F,MATCH(LARGE('BQ-added-Data'!#REF!-ROW('BQ-added-Data'!#REF!)/10^10,$A46),'BQ-added-Data'!#REF!-ROW('BQ-added-Data'!#REF!)/10^10,0)+1)} -> #REF! | H46: =G46*12 -> #REF!
A47: BONBON PROJECT DECISIONS (agile-bonbon-662)
A48: Decision | B48: # Datasets | C48: Size (GB) | D48: Monthly $ | E48: Annual $ | F48: Notes
A49: DELETE — Tranche 1 | B49: =COUNTIFS('BQ-added-Data'!A:A,"agile-bonbon-662",'BQ-added-Data'!Q:Q,"DELETE") -> 12 | C49: =SUMIFS('BQ-added-Data'!E:E,'BQ-added-Data'!A:A,"agile-bonbon-662",'BQ-added-Data'!Q:Q,"DELETE") -> 1871.4 | D49: =SUMIFS('BQ-added-Data'!F:F,'BQ-added-Data'!A:A,"agile-bonbon-662",'BQ-added-Data'!Q:Q,"DELETE") -> 37.43 | E49: =D49*12 -> 449.16 | F49: All Tranche 1 bonbon datasets — proceed to deletion
A50: REVIEW — UA raw logs (numeric IDs) | B50: =COUNTIFS('BQ-added-Data'!A:A,"agile-bonbon-662",'BQ-added-Data'!Q:Q,"REVIEW — UA raw logs") -> 340 | C50: =SUMIFS('BQ-added-Data'!E:E,'BQ-added-Data'!A:A,"agile-bonbon-662",'BQ-added-Data'!Q:Q,"REVIEW — UA raw logs") -> 220646.51 | D50: =SUMIFS('BQ-added-Data'!F:F,'BQ-added-Data'!A:A,"agile-bonbon-662",'BQ-added-Data'!Q:Q,"REVIEW — UA raw logs") -> 4412.95 | E50: =D50*12 -> 52955.4 | F50: Old UA raw site logs — confirm audit-retention requirement before deciding
A51: KEEP — Sessions_Level_1_All_Sites | B51: =COUNTIFS('BQ-added-Data'!A:A,"agile-bonbon-662",'BQ-added-Data'!C:C,"Sessions_Level_1_All_Sites") -> 1 | C51: =SUMIFS('BQ-added-Data'!E:E,'BQ-added-Data'!A:A,"agile-bonbon-662",'BQ-added-Data'!C:C,"Sessions_Level_1_All_Sites") -> 8510.55 | D51: =SUMIFS('BQ-added-Data'!F:F,'BQ-added-Data'!A:A,"agile-bonbon-662",'BQ-added-Data'!C:C,"Sessions_Level_1_All_Sites") -> 170.21 | E51: =D51*12 -> 2042.52 | F51: Downstream UA aggregation — keep if raw tables are removed
A52: KEEP — Emag_Reporting | B52: =COUNTIFS('BQ-added-Data'!A:A,"agile-bonbon-662",'BQ-added-Data'!C:C,"Emag_Reporting") -> 1 | C52: =SUMIFS('BQ-added-Data'!E:E,'BQ-added-Data'!A:A,"agile-bonbon-662",'BQ-added-Data'!C:C,"Emag_Reporting") -> 9.38 | D52: =SUMIFS('BQ-added-Data'!F:F,'BQ-added-Data'!A:A,"agile-bonbon-662",'BQ-added-Data'!C:C,"Emag_Reporting") -> 0.19 | E52: =D52*12 -> 2.28 | F52: Legacy but likely to be needed
A53: KEEP — Nutrition_Data_Archived_Tables | B53: =COUNTIFS('BQ-added-Data'!A:A,"agile-bonbon-662",'BQ-added-Data'!C:C,"Nutrition_Data_Archived_Tables") -> 1 | C53: =SUMIFS('BQ-added-Data'!E:E,'BQ-added-Data'!A:A,"agile-bonbon-662",'BQ-added-Data'!C:C,"Nutrition_Data_Archived_Tables") -> 3.48 | D53: =SUMIFS('BQ-added-Data'!F:F,'BQ-added-Data'!A:A,"agile-bonbon-662",'BQ-added-Data'!C:C,"Nutrition_Data_Archived_Tables") -> 0.07 | E53: =D53*12 -> 0.84 | F53: Worth keeping
A54: KEEP — EU_Data | B54: =COUNTIFS('BQ-added-Data'!A:A,"agile-bonbon-662",'BQ-added-Data'!C:C,"EU_Data") -> 1 | C54: =SUMIFS('BQ-added-Data'!E:E,'BQ-added-Data'!A:A,"agile-bonbon-662",'BQ-added-Data'!C:C,"EU_Data") -> 72.79 | D54: =SUMIFS('BQ-added-Data'!F:F,'BQ-added-Data'!A:A,"agile-bonbon-662",'BQ-added-Data'!C:C,"EU_Data") -> 1.46 | E54: =D54*12 -> 17.52 | F54: Static lookup tables — scripts still reference, would break smoke test
A55: REVIEW — other (T2/T3/T4/T5) | B55: =COUNTIFS('BQ-added-Data'!A:A,"agile-bonbon-662",'BQ-added-Data'!Q:Q,"REVIEW") -> 558 | C55: =SUMIFS('BQ-added-Data'!E:E,'BQ-added-Data'!A:A,"agile-bonbon-662",'BQ-added-Data'!Q:Q,"REVIEW") -> 511635.71 | D55: =SUMIFS('BQ-added-Data'!F:F,'BQ-added-Data'!A:A,"agile-bonbon-662",'BQ-added-Data'!Q:Q,"REVIEW") -> 10232.63 | E55: =D55*12 -> 122791.56 | F55: Remaining bonbon datasets not yet triaged
A56: TOTAL (Bonbon) | B56: =SUM(B49:B55) -> 914 | C56: =SUM(C49:C55) -> 742749.82 | D56: =SUM(D49:D55) -> 14854.94 | E56: =SUM(E49:E55) -> 178259.28
A58: Open question: UA raw logs retention — do audits require us to keep numeric-account-ID datasets? Decision drives ~$4k/mo across Tranche 2.
A60: HOLD — PROJECTS PAUSED PENDING CHARLIE STRINGER REVIEW
A61: Project | B61: # Datasets | C61: Size (GB) | D61: Monthly $ | E61: Annual $ | F61: Status
A62: thg-influencer | B62: =COUNTIF('BQ-added-Data'!A:A,A62) -> 54 | C62: =SUMIF('BQ-added-Data'!A:A,A62,'BQ-added-Data'!E:E) -> 1628.41 | D62: =SUMIF('BQ-added-Data'!A:A,A62,'BQ-added-Data'!F:F) -> 32.52 | E62: =D62*12 -> 390.24 | F62: HOLD — review before deletion
A63: thg-ingenuity | B63: =COUNTIF('BQ-added-Data'!A:A,A63) -> 534 | C63: =SUMIF('BQ-added-Data'!A:A,A63,'BQ-added-Data'!E:E) -> 44539.12 | D63: =SUMIF('BQ-added-Data'!A:A,A63,'BQ-added-Data'!F:F) -> 890.72 | E63: =D63*12 -> 10688.64 | F63: HOLD — review before deletion
A64: thg-central-marketing | B64: =COUNTIF('BQ-added-Data'!A:A,A64) -> 66 | C64: =SUMIF('BQ-added-Data'!A:A,A64,'BQ-added-Data'!E:E) -> 175082.62 | D64: =SUMIF('BQ-added-Data'!A:A,A64,'BQ-added-Data'!F:F) -> 3501.61 | E64: =D64*12 -> 42019.32 | F64: HOLD — review before deletion
A65: thg-seoclarity | B65: =COUNTIF('BQ-added-Data'!A:A,A65) -> 2 | C65: =SUMIF('BQ-added-Data'!A:A,A65,'BQ-added-Data'!E:E) -> 2285.07 | D65: =SUMIF('BQ-added-Data'!A:A,A65,'BQ-added-Data'!F:F) -> 45.7 | E65: =D65*12 -> 548.4 | F65: HOLD — review before deletion
A66: TOTAL (HOLD) | B66: =SUM(B62:B65) -> 656 | C66: =SUM(C62:C65) -> 223535.22 | D66: =SUM(D62:D65) -> 4470.55 | E66: =SUM(E62:E65) -> 53646.6
A68: Note: No deletion action on these four projects until Charlie returns and reviews. All other tranche/decision work continues.

Sheet BigQuery
A1: Organisation | B1: Project | C1: Dataset | D1: Deletion Reason | E1: Tables | F1: Total GB | G1: Monthly Saving ($) | H1: Action | I1: Validation SQL (Storage) | J1: Validation SQL (Read/Usage) | K1: Decision | L1: Decision Notes
A2: thehutgroup.com | B2: vibrant-map-107910 | C2: bigquery_pipeline_manager | D2: Stale Production: Idle 460 days. | E2: 6549 | F2: 105879.22 | G2: 2117.58 | H2: DROP DATASET vibrant-map-107910.bigquery_pipeline_manager | I2: SELECT COUNT(*), SUM(total_logical_bytes)/1024/1024/1024 as gb, MAX(storage_last_modified_time) FROM `vibrant-map-107910.region-eu.INFORMATION_SCHEMA.TABLE_STORAGE` WHERE table_schema = 'bigquery_pipeline_manager' | J2: SELECT job_id, user_email FROM `vibrant-map-107910.region-eu.INFORMATION_SCHEMA.JOBS_BY_PROJECT` WHERE creation_time > TIMESTAMP_SUB(CURRENT_TIMESTAMP(), INTERVAL 180 DAY) AND (destination_table.dataset_id = 'bigquery_pipeline_manager' OR EXISTS(SELECT 1 FROM UNNEST(referenced_tables) ref WHERE ref.dataset_id = 'bigquery_pipeline_manager')) LIMIT 1 | K2: {=_xlfn.IFS(OR($C2="abtest_results",$C2="experimentation_sessions_colour_swatch"),"DROP CONFIRMED",OR($B2="thg-influencer",$B2="thg-ingenuity",$B2="thg-central-marketing",$B2="thg-seoclarity"),"HOLD",TRUE,"REVIEW")} -> REVIEW | L2: {=_xlfn.IFS(OR($C2="abtest_results",$C2="experimentation_sessions_colour_swatch"),"Experimentation team — unused, deprecated format. Safe to drop.",OR($B2="thg-influencer",$B2="thg-ingenuity",$B2="thg-central-marketing",$B2="thg-seoclarity"),"HOLD — Charlie Stringer to review before deletion",TRUE,"")}
A3: thehutgroup.com | B3: agile-bonbon-662 | C3: 94144777 | D3: Stale Production: Idle 721 days. | E3: 4627 | F3: 65273.34 | G3: 1305.47 | H3: DROP DATASET agile-bonbon-662.94144777 | I3: SELECT COUNT(*), SUM(total_logical_bytes)/1024/1024/1024 as gb, MAX(storage_last_modified_time) FROM `agile-bonbon-662.region-eu.INFORMATION_SCHEMA.TABLE_STORAGE` WHERE table_schema = '94144777' | J3: SELECT job_id, user_email FROM `agile-bonbon-662.region-eu.INFORMATION_SCHEMA.JOBS_BY_PROJECT` WHERE creation_time > TIMESTAMP_SUB(CURRENT_TIMESTAMP(), INTERVAL 180 DAY) AND (destination_table.dataset_id = '94144777' OR EXISTS(SELECT 1 FROM UNNEST(referenced_tables) ref WHERE ref.dataset_id = '94144777')) LIMIT 1 | K3: {=_xlfn.IFS(OR($C3="abtest_results",$C3="experimentation_sessions_colour_swatch"),"DROP CONFIRMED",OR($B3="thg-influencer",$B3="thg-ingenuity",$B3="thg-central-marketing",$B3="thg-seoclarity"),"HOLD",TRUE,"REVIEW")} -> REVIEW | L3: {=_xlfn.IFS(OR($C3="abtest_results",$C3="experimentation_sessions_colour_swatch"),"Experimentation team — unused, deprecated format. Safe to drop.",OR($B3="thg-influencer",$B3="thg-ingenuity",$B3="thg-central-marketing",$B3="thg-seoclarity"),"HOLD — Charlie Stringer to review before deletion",TRUE,"")}
A4: thehutgroup.com | B4: the-hut-group | C4: abtest_results | D4: Expired Experiment: Idle 488 days. | E4: 37993 | F4: 21960.2 | G4: 439.2 | H4: DROP DATASET the-hut-group.abtest_results | I4: SELECT COUNT(*), SUM(total_logical_bytes)/1024/1024/1024 as gb, MAX(storage_last_modified_time) FROM `the-hut-group.region-eu.INFORMATION_SCHEMA.TABLE_STORAGE` WHERE table_schema = 'abtest_results' | J4: SELECT job_id, user_email FROM `the-hut-group.region-eu.INFORMATION_SCHEMA.JOBS_BY_PROJECT` WHERE creation_time > TIMESTAMP_SUB(CURRENT_TIMESTAMP(), INTERVAL 180 DAY) AND (destination_table.dataset_id = 'abtest_results' OR EXISTS(SELECT 1 FROM UNNEST(referenced_tables) ref WHERE ref.dataset_id = 'abtest_results')) LIMIT 1 | K4: {=_xlfn.IFS(OR($C4="abtest_results",$C4="experimentation_sessions_colour_swatch"),"DROP CONFIRMED",OR($B4="thg-influencer",$B4="thg-ingenuity",$B4="thg-central-marketing",$B4="thg-seoclarity"),"HOLD",TRUE,"REVIEW")} -> DROP CONFIRMED | L4: {=_xlfn.IFS(OR($C4="abtest_results",$C4="experimentation_sessions_colour_swatch"),"Experimentation team — unused, deprecated format. Safe to drop.",OR($B4="thg-influencer",$B4="thg-ingenuity",$B4="thg-central-marketing",$B4="thg-seoclarity"),"HOLD — Charlie Stringer to review before deletion",TRUE,"")} -> Experimentation team — unused, deprecated format. Safe to drop.
A5: thehutgroup.com | B5: agile-bonbon-662 | C5: SessionsAllSites | D5: Stale Production: Idle 2516 days. | E5: 1960 | F5: 21579.93 | G5: 431.6 | H5: DROP DATASET agile-bonbon-662.SessionsAllSites | I5: SELECT COUNT(*), SUM(total_logical_bytes)/1024/1024/1024 as gb, MAX(storage_last_modified_time) FROM `agile-bonbon-662.region-eu.INFORMATION_SCHEMA.TABLE_STORAGE` WHERE table_schema = 'SessionsAllSites' | J5: SELECT job_id, user_email FROM `agile-bonbon-662.region-eu.INFORMATION_SCHEMA.JOBS_BY_PROJECT` WHERE creation_time > TIMESTAMP_SUB(CURRENT_TIMESTAMP(), INTERVAL 180 DAY) AND (destination_table.dataset_id = 'SessionsAllSites' OR EXISTS(SELECT 1 FROM UNNEST(referenced_tables) ref WHERE ref.dataset_id = 'SessionsAllSites')) LIMIT 1 | K5: {=_xlfn.IFS(OR($C5="abtest_results",$C5="experimentation_sessions_colour_swatch"),"DROP CONFIRMED",OR($B5="thg-influencer",$B5="thg-ingenuity",$B5="thg-central-marketing",$B5="thg-seoclarity"),"HOLD",TRUE,"REVIEW")} -> REVIEW | L5: {=_xlfn.IFS(OR($C5="abtest_results",$C5="experimentation_sessions_colour_swatch"),"Experimentation team — unused, deprecated format. Safe to drop.",OR($B5="thg-influencer",$B5="thg-ingenuity",$B5="thg-central-marketing",$B5="thg-seoclarity"),"HOLD — Charlie Stringer to review before deletion",TRUE,"")}
A6: thehutgroup.com | B6: agile-bonbon-662 | C6: US_Data | D6: Stale Production: Idle 1964 days. | E6: 5210 | F6: 20085.74 | G6: 401.71 | H6: DROP DATASET agile-bonbon-662.US_Data | I6: SELECT COUNT(*), SUM(total_logical_bytes)/1024/1024/1024 as gb, MAX(storage_last_modified_time) FROM `agile-bonbon-662.region-eu.INFORMATION_SCHEMA.TABLE_STORAGE` WHERE table_schema = 'US_Data' | J6: SELECT job_id, user_email FROM `agile-bonbon-662.region-eu.INFORMATION_SCHEMA.JOBS_BY_PROJECT` WHERE creation_time > TIMESTAMP_SUB(CURRENT_TIMESTAMP(), INTERVAL 180 DAY) AND (destination_table.dataset_id = 'US_Data' OR EXISTS(SELECT 1 FROM UNNEST(referenced_tables) ref WHERE ref.dataset_id = 'US_Data')) LIMIT 1 | K6: {=_xlfn.IFS(OR($C6="abtest_results",$C6="experimentation_sessions_colour_swatch"),"DROP CONFIRMED",OR($B6="thg-influencer",$B6="thg-ingenuity",$B6="thg-central-marketing",$B6="thg-seoclarity"),"HOLD",TRUE,"REVIEW")} -> REVIEW | L6: {=_xlfn.IFS(OR($C6="abtest_results",$C6="experimentation_sessions_colour_swatch"),"Experimentation team — unused, deprecated format. Safe to drop.",OR($B6="thg-influencer",$B6="thg-ingenuity",$B6="thg-central-marketing",$B6="thg-seoclarity"),"HOLD — Charlie Stringer to review before deletion",TRUE,"")}
A7: thehutgroup.com | B7: the-hut-group | C7: metrics | D7: Stale Production: Idle 1456 days. | E7: 3672 | F7: 18031.47 | G7: 360.63 | H7: DROP DATASET the-hut-group.metrics | I7: SELECT COUNT(*), SUM(total_logical_bytes)/1024/1024/1024 as gb, MAX(storage_last_modified_time) FROM `the-hut-group.region-eu.INFORMATION_SCHEMA.TABLE_STORAGE` WHERE table_schema = 'metrics' | J7: SELECT job_id, user_email FROM `the-hut-group.region-eu.INFORMATION_SCHEMA.JOBS_BY_PROJECT` WHERE creation_time > TIMESTAMP_SUB(CURRENT_TIMESTAMP(), INTERVAL 180 DAY) AND (destination_table.dataset_id = 'metrics' OR EXISTS(SELECT 1 FROM UNNEST(referenced_tables) ref WHERE ref.dataset_id = 'metrics')) LIMIT 1 | K7: {=_xlfn.IFS(OR($C7="abtest_results",$C7="experimentation_sessions_colour_swatch"),"DROP CONFIRMED",OR($B7="thg-influencer",$B7="thg-ingenuity",$B7="thg-central-marketing",$B7="thg-seoclarity"),"HOLD",TRUE,"REVIEW")} -> REVIEW | L7: {=_xlfn.IFS(OR($C7="abtest_results",$C7="experimentation_sessions_colour_swatch"),"Experimentation team — unused, deprecated format. Safe to drop.",OR($B7="thg-influencer",$B7="thg-ingenuity",$B7="thg-central-marketing",$B7="thg-seoclarity"),"HOLD — Charlie Stringer to review before deletion",TRUE,"")}
A8: thehutgroup.com | B8: agile-bonbon-662 | C8: 18809831 | D8: Stale Production: Idle 721 days. | E8: 3834 | F8: 17344.72 | G8: 346.89 | H8: DROP DATASET agile-bonbon-662.18809831 | I8: SELECT COUNT(*), SUM(total_logical_bytes)/1024/1024/1024 as gb, MAX(storage_last_modified_time) FROM `agile-bonbon-662.region-eu.INFORMATION_SCHEMA.TABLE_STORAGE` WHERE table_schema = '18809831' | J8: SELECT job_id, user_email FROM `agile-bonbon-662.region-eu.INFORMATION_SCHEMA.JOBS_BY_PROJECT` WHERE creation_time > TIMESTAMP_SUB(CURRENT_TIMESTAMP(), INTERVAL 180 DAY) AND (destination_table.dataset_id = '18809831' OR EXISTS(SELECT 1 FROM UNNEST(referenced_tables) ref WHERE ref.dataset_id = '18809831')) LIMIT 1 | K8: {=_xlfn.IFS(OR($C8="abtest_results",$C8="experimentation_sessions_colour_swatch"),"DROP CONFIRMED",OR($B8="thg-influencer",$B8="thg-ingenuity",$B8="thg-central-marketing",$B8="thg-seoclarity"),"HOLD",TRUE,"REVIEW")} -> REVIEW | L8: {=_xlfn.IFS(OR($C8="abtest_results",$C8="experimentation_sessions_colour_swatch"),"Experimentation team — unused, deprecated format. Safe to drop.",OR($B8="thg-influencer",$B8="thg-ingenuity",$B8="thg-central-marketing",$B8="thg-seoclarity"),"HOLD — Charlie Stringer to review before deletion",TRUE,"")}
A9: thehutgroup.com | B9: agile-bonbon-662 | C9: 88617117 | D9: Stale Production: Idle 721 days. | E9: 1231 | F9: 15588.53 | G9: 311.77 | H9: DROP DATASET agile-bonbon-662.88617117 | I9: SELECT COUNT(*), SUM(total_logical_bytes)/1024/1024/1024 as gb, MAX(storage_last_modified_time) FROM `agile-bonbon-662.region-eu.INFORMATION_SCHEMA.TABLE_STORAGE` WHERE table_schema = '88617117' | J9: SELECT job_id, user_email FROM `agile-bonbon-662.region-eu.INFORMATION_SCHEMA.JOBS_BY_PROJECT` WHERE creation_time > TIMESTAMP_SUB(CURRENT_TIMESTAMP(), INTERVAL 180 DAY) AND (destination_table.dataset_id = '88617117' OR EXISTS(SELECT 1 FROM UNNEST(referenced_tables) ref WHERE ref.dataset_id = '88617117')) LIMIT 1 | K9: {=_xlfn.IFS(OR($C9="abtest_results",$C9="experimentation_sessions_colour_swatch"),"DROP CONFIRMED",OR($B9="thg-influencer",$B9="thg-ingenuity",$B9="thg-central-marketing",$B9="thg-seoclarity"),"HOLD",TRUE,"REVIEW")} -> REVIEW | L9: {=_xlfn.IFS(OR($C9="abtest_results",$C9="experimentation_sessions_colour_swatch"),"Experimentation team — unused, deprecated format. Safe to drop.",OR($B9="thg-influencer",$B9="thg-ingenuity",$B9="thg-central-marketing",$B9="thg-seoclarity"),"HOLD — Charlie Stringer to review before deletion",TRUE,"")}
A10: thehutgroup.com | B10: agile-bonbon-662 | C10: 773825 | D10: Stale Production: Idle 721 days. | E10: 3837 | F10: 11641.81 | G10: 232.84 | H10: DROP DATASET agile-bonbon-662.773825 | I10: SELECT COUNT(*), SUM(total_logical_bytes)/1024/1024/1024 as gb, MAX(storage_last_modified_time) FROM `agile-bonbon-662.region-eu.INFORMATION_SCHEMA.TABLE_STORAGE` WHERE table_schema = '773825' | J10: SELECT job_id, user_email FROM `agile-bonbon-662.region-eu.INFORMATION_SCHEMA.JOBS_BY_PROJECT` WHERE creation_time > TIMESTAMP_SUB(CURRENT_TIMESTAMP(), INTERVAL 180 DAY) AND (destination_table.dataset_id = '773825' OR EXISTS(SELECT 1 FROM UNNEST(referenced_tables) ref WHERE ref.dataset_id = '773825')) LIMIT 1 | K10: {=_xlfn.IFS(OR($C10="abtest_results",$C10="experimentation_sessions_colour_swatch"),"DROP CONFIRMED",OR($B10="thg-influencer",$B10="thg-ingenuity",$B10="thg-central-marketing",$B10="thg-seoclarity"),"HOLD",TRUE,"REVIEW")} -> REVIEW | L10: {=_xlfn.IFS(OR($C10="abtest_results",$C10="experimentation_sessions_colour_swatch"),"Experimentation team — unused, deprecated format. Safe to drop.",OR($B10="thg-influencer",$B10="thg-ingenuity",$B10="thg-central-marketing",$B10="thg-seoclarity"),"HOLD — Charlie Stringer to review before deletion",TRUE,"")}
A11: thehutgroup.com | B11: agile-bonbon-662 | C11: SA360_ML_Ad_Copy | D11: Stale Production: Idle 750 days. | E11: 260 | F11: 11047.96 | G11: 220.96 | H11: DROP DATASET agile-bonbon-662.SA360_ML_Ad_Copy | I11: SELECT COUNT(*), SUM(total_logical_bytes)/1024/1024/1024 as gb, MAX(storage_last_modified_time) FROM `agile-bonbon-662.region-eu.INFORMATION_SCHEMA.TABLE_STORAGE` WHERE table_schema = 'SA360_ML_Ad_Copy' | J11: SELECT job_id, user_email FROM `agile-bonbon-662.region-eu.INFORMATION_SCHEMA.JOBS_BY_PROJECT` WHERE creation_time > TIMESTAMP_SUB(CURRENT_TIMESTAMP(), INTERVAL 180 DAY) AND (destination_table.dataset_id = 'SA360_ML_Ad_Copy' OR EXISTS(SELECT 1 FROM UNNEST(referenced_tables) ref WHERE ref.dataset_id = 'SA360_ML_Ad_Copy')) LIMIT 1 | K11: {=_xlfn.IFS(OR($C11="abtest_results",$C11="experimentation_sessions_colour_swatch"),"DROP CONFIRMED",OR($B11="thg-influencer",$B11="thg-ingenuity",$B11="thg-central-marketing",$B11="thg-seoclarity"),"HOLD",TRUE,"REVIEW")} -> REVIEW | L11: {=_xlfn.IFS(OR($C11="abtest_results",$C11="experimentation_sessions_colour_swatch"),"Experimentation team — unused, deprecated format. Safe to drop.",OR($B11="thg-influencer",$B11="thg-ingenuity",$B11="thg-central-marketing",$B11="thg-seoclarity"),"HOLD — Charlie Stringer to review before deletion",TRUE,"")}
A12: thehutgroup.com | B12: the-hut-group | C12: archived_unity | D12: Abandoned Archive: Idle 1963 days. | E12: 335 | F12: 10315.79 | G12: 206.32 | H12: DROP DATASET the-hut-group.archived_unity | I12: SELECT COUNT(*), SUM(total_logical_bytes)/1024/1024/1024 as gb, MAX(storage_last_modified_time) FROM `the-hut-group.region-eu.INFORMATION_SCHEMA.TABLE_STORAGE` WHERE table_schema = 'archived_unity' | J12: SELECT job_id, user_email FROM `the-hut-group.region-eu.INFORMATION_SCHEMA.JOBS_BY_PROJECT` WHERE creation_time > TIMESTAMP_SUB(CURRENT_TIMESTAMP(), INTERVAL 180 DAY) AND (destination_table.dataset_id = 'archived_unity' OR EXISTS(SELECT 1 FROM UNNEST(referenced_tables) ref WHERE ref.dataset_id = 'archived_unity')) LIMIT 1 | K12: {=_xlfn.IFS(OR($C12="abtest_results",$C12="experimentation_sessions_colour_swatch"),"DROP CONFIRMED",OR($B12="thg-influencer",$B12="thg-ingenuity",$B12="thg-central-marketing",$B12="thg-seoclarity"),"HOLD",TRUE,"REVIEW")} -> REVIEW | L12: {=_xlfn.IFS(OR($C12="abtest_results",$C12="experimentation_sessions_colour_swatch"),"Experimentation team — unused, deprecated format. Safe to drop.",OR($B12="thg-influencer",$B12="thg-ingenuity",$B12="thg-central-marketing",$B12="thg-seoclarity"),"HOLD — Charlie Stringer to review before deletion",TRUE,"")}
A13: thehutgroup.com | B13: the-hut-group | C13: segmentation | D13: Stale Production: Idle 1964 days. | E13: 5360 | F13: 8843.08 | G13: 176.86 | H13: DROP DATASET the-hut-group.segmentation | I13: SELECT COUNT(*), SUM(total_logical_bytes)/1024/1024/1024 as gb, MAX(storage_last_modified_time) FROM `the-hut-group.region-eu.INFORMATION_SCHEMA.TABLE_STORAGE` WHERE table_schema = 'segmentation' | J13: SELECT job_id, user_email FROM `the-hut-group.region-eu.INFORMATION_SCHEMA.JOBS_BY_PROJECT` WHERE creation_time > TIMESTAMP_SUB(CURRENT_TIMESTAMP(), INTERVAL 180 DAY) AND (destination_table.dataset_id = 'segmentation' OR EXISTS(SELECT 1 FROM UNNEST(referenced_tables) ref WHERE ref.dataset_id = 'segmentation')) LIMIT 1 | K13: {=_xlfn.IFS(OR($C13="abtest_results",$C13="experimentation_sessions_colour_swatch"),"DROP CONFIRMED",OR($B13="thg-influencer",$B13="thg-ingenuity",$B13="thg-central-marketing",$B13="thg-seoclarity"),"HOLD",TRUE,"REVIEW")} -> REVIEW | L13: {=_xlfn.IFS(OR($C13="abtest_results",$C13="experimentation_sessions_colour_swatch"),"Experimentation team — unused, deprecated format. Safe to drop.",OR($B13="thg-influencer",$B13="thg-ingenuity",$B13="thg-central-marketing",$B13="thg-seoclarity"),"HOLD — Charlie Stringer to review before deletion",TRUE,"")}
... A334: thehutgroup.com | B334: agile-bonbon-662 | C334: analytics_294922532 | D334: Stale Production: Idle 815 days. | E334: 531 | F334: 10.55 | G334: 0.21 | H334: DROP DATASET agile-bonbon-662.analytics_294922532 | I334: SELECT COUNT(*), SUM(total_logical_bytes)/1024/1024/1024 as gb, MAX(storage_last_modified_time) FROM `agile-bonbon-662.region-eu.INFORMATION_SCHEMA.TABLE_STORAGE` WHERE table_schema = 'analytics_294922532' | J334: SELECT job_id, user_email FROM `agile-bonbon-662.region-eu.INFORMATION_SCHEMA.JOBS_BY_PROJECT` WHERE creation_time > TIMESTAMP_SUB(CURRENT_TIMESTAMP(), INTERVAL 180 DAY) AND (destination_table.dataset_id = 'analytics_294922532' OR EXISTS(SELECT 1 FROM UNNEST(referenced_tables) ref WHERE ref.dataset_id = 'analytics_294922532')) LIMIT 1 | K334: {=_xlfn.IFS(OR($C334="abtest_results",$C334="experimentation_sessions_colour_swatch"),"DROP CONFIRMED",OR($B334="thg-influencer",$B334="thg-ingenuity",$B334="thg-central-marketing",$B334="thg-seoclarity"),"HOLD",TRUE,"REVIEW")} -> REVIEW | L334: {=_xlfn.IFS(OR($C334="abtest_results",$C334="experimentation_sessions_colour_swatch"),"Experimentation team — unused, deprecated format. Safe to drop.",OR($B334="thg-influencer",$B334="thg-ingenuity",$B334="thg-central-marketing",$B334="thg-seoclarity"),"HOLD — Charlie Stringer to review before deletion",TRUE,"")}

Sheet BQ-added-Data
A1: Project | B1: Region | C1: Dataset | D1: Description | E1: Size (GB) | F1: Monthly Cost ($) | G1: Tranche | H1: Cleanup Priority | I1: Days Since Last Activity | J1: Days Since Last Modified | K1: Last Read Time | L1: Last Write Time | M1: Last 5 Reads (Who/When) | N1: Last 5 Writes (Who/When) | O1: Last Storage Update | P1: Defensible Deletion Status | Q1: Decision | R1: Decision Notes | S1: Original Defensible Deletion Status
A2: thg-beauty | B2: eu | C2: Commercial_Marketing | D2: No Description | E2: 13280.86 | F2: 265.62 | G2: Active | H2: Low | I2: 0 | J2: 0 | K2: 46197.42 | L2: 46197.241 | M2: 2026-06-24 10:04 (beauty-data@agile-bonbon-662.iam.gserviceaccount.com) 2026-06-24 10:04 (beauty-data@agile-bonbon-662.iam.gserviceaccount.com) 2026-06-24 10:04 (beauty-data@agile-bonbon-662.iam.gserviceaccount.com) 2026-06-24 10:01 (beauty-data@agile-bonbon-662.iam.gserviceaccount.com) 2026-06-24 07:06 (beauty-data@agile-bonbon-662.iam.gserviceaccount.com) | N2: 2026-06-24 05:47 (beauty-data@agile-bonbon-662.iam.gserviceaccount.com) 2026-06-24 05:46 (beauty-data@agile-bonbon-662.iam.gserviceaccount.com) 2026-06-24 05:46 (beauty-data@agile-bonbon-662.iam.gserviceaccount.com) 2026-06-24 05:46 (beauty-data@agile-bonbon-662.iam.gserviceaccount.com) 2026-06-24 05:16 (sa-bpswcbdsql01@thg-beauty.iam.gserviceaccount.com) | O2: 46197.241 | P2: =IF($Q2="DELETE",IF($S2="CONFIRMED: NO MODS > 1YR","CONFIRMED: NO MODS > 1YR","DO NOT DELETE — not defensibly confirmed"),IF($Q2="HOLD","DO NOT DELETE — HOLD (Charlie review)",IF($Q2="KEEP","DO NOT DELETE — KEEP",IF(ISNUMBER(SEARCH("REVIEW",$Q2)),"DO NOT DELETE — REVIEW pending",$S2)))) -> CONFIRMED: NO MODS > 1YR | Q2: {=_xlfn.IFS(AND($A2="thg-beauty",ISNUMBER(SEARCH("liveramp",$C2))),"DELETE",$A2="agile-bonbon-662",_xlfn.IFS(LEFT($G2,9)="Tranche 1","DELETE",$C2="Sessions_Level_1_All_Sites","KEEP",ISNUMBER(--$C2),"REVIEW — UA raw logs",$C2="Emag_Reporting","KEEP",$C2="Nutrition_Data_Archived_Tables","KEEP",$C2="EU_Data","KEEP",TRUE,"REVIEW"),OR($A2="thg-influencer",$A2="thg-ingenuity",$A2="thg-central-marketing",$A2="thg-seoclarity"),"HOLD",TRUE,"")} | R2: {=_xlfn.IFS(AND($A2="thg-beauty",ISNUMBER(SEARCH("liveramp",$C2))),"thg-beauty Liveramp dataset — confirmed safe to delete",$A2="agile-bonbon-662",_xlfn.IFS(LEFT($G2,9)="Tranche 1","Tranche 1: cleared",$C2="Sessions_Level_1_All_Sites","Downstream aggregation of UA raw logs — keep if raw tables go",ISNUMBER(--$C2),"UA raw site logs (account ID) — keep pending audit-retention check",$C2="Emag_Reporting","Legacy but likely needed",$C2="Nutrition_Data_Archived_Tables","Worth keeping",$C2="EU_Data","Static lookup tables — scripts still reference (smoke-test risk)",TRUE,"Review"),OR($A2="thg-influencer",$A2="thg-ingenuity",$A2="thg-central-marketing",$A2="thg-seoclarity"),"HOLD — Charlie Stringer to review before deletion",TRUE,"")} | S2: CONFIRMED: NO MODS > 1YR
A3: thg-beauty | B3: eu | C3: Site_Reporting | D3: No Description | E3: 6902.77 | F3: 138.06 | G3: Active | H3: Low | I3: 0 | J3: 0 | K3: 46197.446 | L3: 46197.437 | M3: 2026-06-24 10:42 (vy.nguyen12@thehutgroup.com) 2026-06-24 10:41 (vy.nguyen12@thehutgroup.com) 2026-06-24 10:37 (vy.nguyen12@thehutgroup.com) 2026-06-24 10:36 (vy.nguyen12@thehutgroup.com) 2026-06-24 10:36 (vy.nguyen12@thehutgroup.com) | N3: 2026-06-24 10:28 (sa-bpswcbdsql01@thg-beauty.iam.gserviceaccount.com) 2026-06-24 10:28 (sa-bpswcbdsql01@thg-beauty.iam.gserviceaccount.com) 2026-06-24 10:28 (sa-bpswcbdsql01@thg-beauty.iam.gserviceaccount.com) 2026-06-24 10:27 (sa-bpswcbdsql01@thg-beauty.iam.gserviceaccount.com) 2026-06-24 10:27 (sa-bpswcbdsql01@thg-beauty.iam.gserviceaccount.com) | O3: 46197.44 | P3: =IF($Q3="DELETE",IF($S3="CONFIRMED: NO MODS > 1YR","CONFIRMED: NO MODS > 1YR","DO NOT DELETE — not defensibly confirmed"),IF($Q3="HOLD","DO NOT DELETE — HOLD (Charlie review)",IF($Q3="KEEP","DO NOT DELETE — KEEP",IF(ISNUMBER(SEARCH("REVIEW",$Q3)),"DO NOT DELETE — REVIEW pending",$S3)))) -> CONFIRMED: NO MODS > 1YR | Q3: {=_xlfn.IFS(AND($A3="thg-beauty",ISNUMBER(SEARCH("liveramp",$C3))),"DELETE",$A3="agile-bonbon-662",_xlfn.IFS(LEFT($G3,9)="Tranche 1","DELETE",$C3="Sessions_Level_1_All_Sites","KEEP",ISNUMBER(--$C3),"REVIEW — UA raw logs",$C3="Emag_Reporting","KEEP",$C3="Nutrition_Data_Archived_Tables","KEEP",$C3="EU_Data","KEEP",TRUE,"REVIEW"),OR($A3="thg-influencer",$A3="thg-ingenuity",$A3="thg-central-marketing",$A3="thg-seoclarity"),"HOLD",TRUE,"")} | R3: {=_xlfn.IFS(AND($A3="thg-beauty",ISNUMBER(SEARCH("liveramp",$C3))),"thg-beauty Liveramp dataset — confirmed safe to delete",$A3="agile-bonbon-662",_xlfn.IFS(LEFT($G3,9)="Tranche 1","Tranche 1: cleared",$C3="Sessions_Level_1_All_Sites","Downstream aggregation of UA raw logs — keep if raw tables go",ISNUMBER(--$C3),"UA raw site logs (account ID) — keep pending audit-retention check",$C3="Emag_Reporting","Legacy but likely needed",$C3="Nutrition_Data_Archived_Tables","Worth keeping",$C3="EU_Data","Static lookup tables — scripts still reference (smoke-test risk)",TRUE,"Review"),OR($A3="thg-influencer",$A3="thg-ingenuity",$A3="thg-central-marketing",$A3="thg-seoclarity"),"HOLD — Charlie Stringer to review before deletion",TRUE,"")} | S3: CONFIRMED: NO MODS > 1YR
A4: thg-beauty | B4: eu | C4: beauty_email | D4: No Description | E4: 4983.25 | F4: 99.66 | G4: Active | H4: Low | I4: 0 | J4: 0 | K4: 46197.403 | L4: 46197.271 | M4: 2026-06-24 09:40 (amalu.thevalakara21@thg.com) 2026-06-24 09:33 (shilpa.veedu03@thg.com) 2026-06-24 09:33 (shilpa.veedu03@thg.com) 2026-06-24 09:33 (shilpa.veedu03@thg.com) 2026-06-24 09:33 (shilpa.veedu03@thg.com) | N4: 2026-06-24 06:30 (amalu.thevalakara21@thg.com) 2026-06-24 02:39 (sa-bpswcbdsql01@thg-beauty.iam.gserviceaccount.com) 2026-06-24 02:39 (sa-bpswcbdsql01@thg-beauty.iam.gserviceaccount.com) 2026-06-24 02:39 (sa-bpswcbdsql01@thg-beauty.iam.gserviceaccount.com) 2026-06-24 02:39 (sa-bpswcbdsql01@thg-beauty.iam.gserviceaccount.com) | O4: 46197.272 | P4: =IF($Q4="DELETE",IF($S4="CONFIRMED: NO MODS > 1YR","CONFIRMED: NO MODS > 1YR","DO NOT DELETE — not defensibly confirmed"),IF($Q4="HOLD","DO NOT DELETE — HOLD (Charlie review)",IF($Q4="KEEP","DO NOT DELETE — KEEP",IF(ISNUMBER(SEARCH("REVIEW",$Q4)),"DO NOT DELETE — REVIEW pending",$S4)))) -> REVIEW | Q4: {=_xlfn.IFS(AND($A4="thg-beauty",ISNUMBER(SEARCH("liveramp",$C4))),"DELETE",$A4="agile-bonbon-662",_xlfn.IFS(LEFT($G4,9)="Tranche 1","DELETE",$C4="Sessions_Level_1_All_Sites","KEEP",ISNUMBER(--$C4),"REVIEW — UA raw logs",$C4="Emag_Reporting","KEEP",$C4="Nutrition_Data_Archived_Tables","KEEP",$C4="EU_Data","KEEP",TRUE,"REVIEW"),OR($A4="thg-influencer",$A4="thg-ingenuity",$A4="thg-central-marketing",$A4="thg-seoclarity"),"HOLD",TRUE,"")} | R4: {=_xlfn.IFS(AND($A4="thg-beauty",ISNUMBER(SEARCH("liveramp",$C4))),"thg-beauty Liveramp dataset — confirmed safe to delete",$A4="agile-bonbon-662",_xlfn.IFS(LEFT($G4,9)="Tranche 1","Tranche 1: cleared",$C4="Sessions_Level_1_All_Sites","Downstream aggregation of UA raw logs — keep if raw tables go",ISNUMBER(--$C4),"UA raw site logs (account ID) — keep pending audit-retention check",$C4="Emag_Reporting","Legacy but likely needed",$C4="Nutrition_Data_Archived_Tables","Worth keeping",$C4="EU_Data","Static lookup tables — scripts still reference (smoke-test risk)",TRUE,"Review"),OR($A4="thg-influencer",$A4="thg-ingenuity",$A4="thg-central-marketing",$A4="thg-seoclarity"),"HOLD — Charlie Stringer to review before deletion",TRUE,"")} | S4: REVIEW
A5: thg-beauty | B5: eu | C5: Merch | D5: No Description | E5: 3742.88 | F5: 74.86 | G5: Active | H5: Low | I5: 0 | J5: 0 | K5: 46197.351 | L5: 46197.326 | M5: 2026-06-24 08:25 (beauty-data@agile-bonbon-662.iam.gserviceaccount.com) 2026-06-24 08:14 (beauty-data@agile-bonbon-662.iam.gserviceaccount.com) 2026-06-24 08:14 (beauty-data@agile-bonbon-662.iam.gserviceaccount.com) 2026-06-24 08:09 (haleema.anbreen45@thg.com) 2026-06-24 08:04 (beauty-data@agile-bonbon-662.iam.gserviceaccount.com) | N5: 2026-06-24 07:49 (beauty-data@agile-bonbon-662.iam.gserviceaccount.com) 2026-06-24 07:48 (beauty-data@agile-bonbon-662.iam.gserviceaccount.com) 2026-06-24 07:48 (beauty-data@agile-bonbon-662.iam.gserviceaccount.com) 2026-06-24 07:48 (beauty-data@agile-bonbon-662.iam.gserviceaccount.com) 2026-06-24 07:45 (beauty-data@agile-bonbon-662.iam.gserviceaccount.com) | O5: 46197.326 | P5: =IF($Q5="DELETE",IF($S5="CONFIRMED: NO MODS > 1YR","CONFIRMED: NO MODS > 1YR","DO NOT DELETE — not defensibly confirmed"),IF($Q5="HOLD","DO NOT DELETE — HOLD (Charlie review)",IF($Q5="KEEP","DO NOT DELETE — KEEP",IF(ISNUMBER(SEARCH("REVIEW",$Q5)),"DO NOT DELETE — REVIEW pending",$S5)))) -> CONFIRMED: NO MODS > 1YR | Q5: {=_xlfn.IFS(AND($A5="thg-beauty",ISNUMBER(SEARCH("liveramp",$C5))),"DELETE",$A5="agile-bonbon-662",_xlfn.IFS(LEFT($G5,9)="Tranche 1","DELETE",$C5="Sessions_Level_1_All_Sites","KEEP",ISNUMBER(--$C5),"REVIEW — UA raw logs",$C5="Emag_Reporting","KEEP",$C5="Nutrition_Data_Archived_Tables","KEEP",$C5="EU_Data","KEEP",TRUE,"REVIEW"),OR($A5="thg-influencer",$A5="thg-ingenuity",$A5="thg-central-marketing",$A5="thg-seoclarity"),"HOLD",TRUE,"")} | R5: {=_xlfn.IFS(AND($A5="thg-beauty",ISNUMBER(SEARCH("liveramp",$C5))),"thg-beauty Liveramp dataset — confirmed safe to delete",$A5="agile-bonbon-662",_xlfn.IFS(LEFT($G5,9)="Tranche 1","Tranche 1: cleared",$C5="Sessions_Level_1_All_Sites","Downstream aggregation of UA raw logs — keep if raw tables go",ISNUMBER(--$C5),"UA raw site logs (account ID) — keep pending audit-retention check",$C5="Emag_Reporting","Legacy but likely needed",$C5="Nutrition_Data_Archived_Tables","Worth keeping",$C5="EU_Data","Static lookup tables — scripts still reference (smoke-test risk)",TRUE,"Review"),OR($A5="thg-influencer",$A5="thg-ingenuity",$A5="thg-central-marketing",$A5="thg-seoclarity"),"HOLD — Charlie Stringer to review before deletion",TRUE,"")} | S5: CONFIRMED: NO MODS > 1YR
A6: thg-beauty | B6: eu | C6: Workspace_Sandbox | D6: No Description | E6: 2765.99 | F6: 55.32 | G6: Active | H6: Low | I6: 0 | J6: 0 | K6: 46197.451 | L6: 46197.39 | M6: 2026-06-24 10:49 (vy.nguyen12@thehutgroup.com) 2026-06-24 10:42 (vy.nguyen12@thehutgroup.com) 2026-06-24 10:41 (vy.nguyen12@thehutgroup.com) 2026-06-24 10:37 (vy.nguyen12@thehutgroup.com) 2026-06-24 10:36 (vy.nguyen12@thehutgroup.com) | N6: 2026-06-24 09:22 (aakash.kalantre61@thehutgroup.com) 2026-06-24 09:22 (aakash.kalantre61@thehutgroup.com) 2026-06-24 06:16 (amalu.thevalakara21@thg.com) 2026-06-24 06:10 (amalu.thevalakara21@thg.com) 2026-06-24 06:01 (aakash.kalantre61@thehutgroup.com) | O6: 46197.391 | P6: =IF($Q6="DELETE",IF($S6="CONFIRMED: NO MODS > 1YR","CONFIRMED: NO MODS > 1YR","DO NOT DELETE — not defensibly confirmed"),IF($Q6="HOLD","DO NOT DELETE — HOLD (Charlie review)",IF($Q6="KEEP","DO NOT DELETE — KEEP",IF(ISNUMBER(SEARCH("REVIEW",$Q6)),"DO NOT DELETE — REVIEW pending",$S6)))) -> CONFIRMED: NO MODS > 1YR | Q6: {=_xlfn.IFS(AND($A6="thg-beauty",ISNUMBER(SEARCH("liveramp",$C6))),"DELETE",$A6="agile-bonbon-662",_xlfn.IFS(LEFT($G6,9)="Tranche 1","DELETE",$C6="Sessions_Level_1_All_Sites","KEEP",ISNUMBER(--$C6),"REVIEW — UA raw logs",$C6="Emag_Reporting","KEEP",$C6="Nutrition_Data_Archived_Tables","KEEP",$C6="EU_Data","KEEP",TRUE,"REVIEW"),OR($A6="thg-influencer",$A6="thg-ingenuity",$A6="thg-central-marketing",$A6="thg-seoclarity"),"HOLD",TRUE,"")} | R6: {=_xlfn.IFS(AND($A6="thg-beauty",ISNUMBER(SEARCH("liveramp",$C6))),"thg-beauty Liveramp dataset — confirmed safe to delete",$A6="agile-bonbon-662",_xlfn.IFS(LEFT($G6,9)="Tranche 1","Tranche 1: cleared",$C6="Sessions_Level_1_All_Sites","Downstream aggregation of UA raw logs — keep if raw tables go",ISNUMBER(--$C6),"UA raw site logs (account ID) — keep pending audit-retention check",$C6="Emag_Reporting","Legacy but likely needed",$C6="Nutrition_Data_Archived_Tables","Worth keeping",$C6="EU_Data","Static lookup tables — scripts still reference (smoke-test risk)",TRUE,"Review"),OR($A6="thg-influencer",$A6="thg-ingenuity",$A6="thg-central-marketing",$A6="thg-seoclarity"),"HOLD — Charlie Stringer to review before deletion",TRUE,"")} | S6: CONFIRMED: NO MODS > 1YR
A7: thg-beauty | B7: eu | C7: Merch_WSSI | D7: No Description | E7: 2285.3 | F7: 45.71 | G7: Active | H7: Low | I7: 0 | J7: 0 | K7: 46197.337 | L7: 46197.296 | M7: 2026-06-24 08:04 (beauty-data@agile-bonbon-662.iam.gserviceaccount.com) 2026-06-24 07:31 (beauty-data@agile-bonbon-662.iam.gserviceaccount.com) 2026-06-24 07:31 (beauty-data@agile-bonbon-662.iam.gserviceaccount.com) 2026-06-24 07:27 (beauty-data@agile-bonbon-662.iam.gserviceaccount.com) 2026-06-24 07:27 (beauty-data@agile-bonbon-662.iam.gserviceaccount.com) | N7: 2026-06-24 07:06 (beauty-data@agile-bonbon-662.iam.gserviceaccount.com) 2026-06-24 06:52 (haleema.anbreen45@thg.com) 2026-06-24 06:47 (haleema.anbreen45@thg.com) 2026-06-24 05:11 (sa-bpswcbdsql01@thg-beauty.iam.gserviceaccount.com) 2026-06-24 05:00 (sa-bpswcbdsql01@thg-beauty.iam.gserviceaccount.com) | O7: 46197.296 | P7: =IF($Q7="DELETE",IF($S7="CONFIRMED: NO MODS > 1YR","CONFIRMED: NO MODS > 1YR","DO NOT DELETE — not defensibly confirmed"),IF($Q7="HOLD","DO NOT DELETE — HOLD (Charlie review)",IF($Q7="KEEP","DO NOT DELETE — KEEP",IF(ISNUMBER(SEARCH("REVIEW",$Q7)),"DO NOT DELETE — REVIEW pending",$S7)))) -> CONFIRMED: NO MODS > 1YR | Q7: {=_xlfn.IFS(AND($A7="thg-beauty",ISNUMBER(SEARCH("liveramp",$C7))),"DELETE",$A7="agile-bonbon-662",_xlfn.IFS(LEFT($G7,9)="Tranche 1","DELETE",$C7="Sessions_Level_1_All_Sites","KEEP",ISNUMBER(--$C7),"REVIEW — UA raw logs",$C7="Emag_Reporting","KEEP",$C7="Nutrition_Data_Archived_Tables","KEEP",$C7="EU_Data","KEEP",TRUE,"REVIEW"),OR($A7="thg-influencer",$A7="thg-ingenuity",$A7="thg-central-marketing",$A7="thg-seoclarity"),"HOLD",TRUE,"")} | R7: {=_xlfn.IFS(AND($A7="thg-beauty",ISNUMBER(SEARCH("liveramp",$C7))),"thg-beauty Liveramp dataset — confirmed safe to delete",$A7="agile-bonbon-662",_xlfn.IFS(LEFT($G7,9)="Tranche 1","Tranche 1: cleared",$C7="Sessions_Level_1_All_Sites","Downstream aggregation of UA raw logs — keep if raw tables go",ISNUMBER(--$C7),"UA raw site logs (account ID) — keep pending audit-retention check",$C7="Emag_Reporting","Legacy but likely needed",$C7="Nutrition_Data_Archived_Tables","Worth keeping",$C7="EU_Data","Static lookup tables — scripts still reference (smoke-test risk)",TRUE,"Review"),OR($A7="thg-influencer",$A7="thg-ingenuity",$A7="thg-central-marketing",$A7="thg-seoclarity"),"HOLD — Charlie Stringer to review before deletion",TRUE,"")} | S7: CONFIRMED: NO MODS > 1YR
A8: thg-beauty | B8: eu | C8: SUBS | D8: No Description | E8: 1922.79 | F8: 38.46 | G8: Active | H8: Low | I8: 0 | J8: 0 | K8: 46197.434 | L8: 46197.21 | M8: 2026-06-24 10:25 (sa-bpswcbdsql01@thg-beauty.iam.gserviceaccount.com) 2026-06-24 09:43 (aakash.kalantre61@thehutgroup.com) 2026-06-24 09:41 (aakash.kalantre61@thehutgroup.com) 2026-06-24 09:41 (aakash.kalantre61@thehutgroup.com) 2026-06-24 09:40 (aakash.kalantre61@thehutgroup.com) | N8: 2026-06-24 05:02 (sa-bpswcbdsql01@thg-beauty.iam.gserviceaccount.com) 2026-06-24 05:02 (sa-bpswcbdsql01@thg-beauty.iam.gserviceaccount.com) 2026-06-24 05:02 (sa-bpswcbdsql01@thg-beauty.iam.gserviceaccount.com) 2026-06-24 05:02 (sa-bpswcbdsql01@thg-beauty.iam.gserviceaccount.com) 2026-06-24 05:02 (sa-bpswcbdsql01@thg-beauty.iam.gserviceaccount.com) | O8: 46197.21 | P8: =IF($Q8="DELETE",IF($S8="CONFIRMED: NO MODS > 1YR","CONFIRMED: NO MODS > 1YR","DO NOT DELETE — not defensibly confirmed"),IF($Q8="HOLD","DO NOT DELETE — HOLD (Charlie review)",IF($Q8="KEEP","DO NOT DELETE — KEEP",IF(ISNUMBER(SEARCH("REVIEW",$Q8)),"DO NOT DELETE — REVIEW pending",$S8)))) -> CONFIRMED: NO MODS > 1YR | Q8: {=_xlfn.IFS(AND($A8="thg-beauty",ISNUMBER(SEARCH("liveramp",$C8))),"DELETE",$A8="agile-bonbon-662",_xlfn.IFS(LEFT($G8,9)="Tranche 1","DELETE",$C8="Sessions_Level_1_All_Sites","KEEP",ISNUMBER(--$C8),"REVIEW — UA raw logs",$C8="Emag_Reporting","KEEP",$C8="Nutrition_Data_Archived_Tables","KEEP",$C8="EU_Data","KEEP",TRUE,"REVIEW"),OR($A8="thg-influencer",$A8="thg-ingenuity",$A8="thg-central-marketing",$A8="thg-seoclarity"),"HOLD",TRUE,"")} | R8: {=_xlfn.IFS(AND($A8="thg-beauty",ISNUMBER(SEARCH("liveramp",$C8))),"thg-beauty Liveramp dataset — confirmed safe to delete",$A8="agile-bonbon-662",_xlfn.IFS(LEFT($G8,9)="Tranche 1","Tranche 1: cleared",$C8="Sessions_Level_1_All_Sites","Downstream aggregation of UA raw logs — keep if raw tables go",ISNUMBER(--$C8),"UA raw site logs (account ID) — keep pending audit-retention check",$C8="Emag_Reporting","Legacy but likely needed",$C8="Nutrition_Data_Archived_Tables","Worth keeping",$C8="EU_Data","Static lookup tables — scripts still reference (smoke-test risk)",TRUE,"Review"),OR($A8="thg-influencer",$A8="thg-ingenuity",$A8="thg-central-marketing",$A8="thg-seoclarity"),"HOLD — Charlie Stringer to review before deletion",TRUE,"")} | S8: CONFIRMED: NO MODS > 1YR
A9: thg-beauty | B9: eu | C9: Dataform_Sandbox | D9: No Description | E9: 1357.69 | F9: 27.15 | G9: Active | H9: Low | I9: 0 | J9: 0 | K9: 46197.175 | L9: 46197.109 | M9: 2026-06-24 04:12 (Liam.Lim79@thg.com) 2026-06-24 02:50 (sa-bpswcbdsql01@thg-beauty.iam.gserviceaccount.com) 2026-06-24 02:50 (sa-bpswcbdsql01@thg-beauty.iam.gserviceaccount.com) 2026-06-24 02:36 (sa-bpswcbdsql01@thg-beauty.iam.gserviceaccount.com) 2026-06-24 02:36 (sa-bpswcbdsql01@thg-beauty.iam.gserviceaccount.com) | N9: 2026-06-24 02:36 (sa-bpswcbdsql01@thg-beauty.iam.gserviceaccount.com) 2026-06-24 02:35 (sa-bpswcbdsql01@thg-beauty.iam.gserviceaccount.com) 2026-06-24 02:28 (sa-bpswcbdsql01@thg-beauty.iam.gserviceaccount.com) 2026-06-24 02:28 (sa-bpswcbdsql01@thg-beauty.iam.gserviceaccount.com) 2026-06-24 02:28 (sa-bpswcbdsql01@thg-beauty.iam.gserviceaccount.com) | O9: 46197.11 | P9: =IF($Q9="DELETE",IF($S9="CONFIRMED: NO MODS > 1YR","CONFIRMED: NO MODS > 1YR","DO NOT DELETE — not defensibly confirmed"),IF($Q9="HOLD","DO NOT DELETE — HOLD (Charlie review)",IF($Q9="KEEP","DO NOT DELETE — KEEP",IF(ISNUMBER(SEARCH("REVIEW",$Q9)),"DO NOT DELETE — REVIEW pending",$S9)))) -> CONFIRMED: NO MODS > 1YR | Q9: {=_xlfn.IFS(AND($A9="thg-beauty",ISNUMBER(SEARCH("liveramp",$C9))),"DELETE",$A9="agile-bonbon-662",_xlfn.IFS(LEFT($G9,9)="Tranche 1","DELETE",$C9="Sessions_Level_1_All_Sites","KEEP",ISNUMBER(--$C9),"REVIEW — UA raw logs",$C9="Emag_Reporting","KEEP",$C9="Nutrition_Data_Archived_Tables","KEEP",$C9="EU_Data","KEEP",TRUE,"REVIEW"),OR($A9="thg-influencer",$A9="thg-ingenuity",$A9="thg-central-marketing",$A9="thg-seoclarity"),"HOLD",TRUE,"")} | R9: {=_xlfn.IFS(AND($A9="thg-beauty",ISNUMBER(SEARCH("liveramp",$C9))),"thg-beauty Liveramp dataset — confirmed safe to delete",$A9="agile-bonbon-662",_xlfn.IFS(LEFT($G9,9)="Tranche 1","Tranche 1: cleared",$C9="Sessions_Level_1_All_Sites","Downstream aggregation of UA raw logs — keep if raw tables go",ISNUMBER(--$C9),"UA raw site logs (account ID) — keep pending audit-retention check",$C9="Emag_Reporting","Legacy but likely needed",$C9="Nutrition_Data_Archived_Tables","Worth keeping",$C9="EU_Data","Static lookup tables — scripts still reference (smoke-test risk)",TRUE,"Review"),OR($A9="thg-influencer",$A9="thg-ingenuity",$A9="thg-central-marketing",$A9="thg-seoclarity"),"HOLD — Charlie Stringer to review before deletion",TRUE,"")} | S9: CONFIRMED: NO MODS > 1YR
A10: thg-beauty | B10: eu | C10: Traffic_Data | D10: No Description | E10: 1302.1 | F10: 26.04 | G10: Active | H10: Low | I10: 0 | J10: 0 | K10: 46197.451 | L10: 46197.099 | M10: 2026-06-24 10:49 (vy.nguyen12@thehutgroup.com) 2026-06-24 10:42 (vy.nguyen12@thehutgroup.com) 2026-06-24 10:41 (vy.nguyen12@thehutgroup.com) 2026-06-24 10:37 (vy.nguyen12@thehutgroup.com) 2026-06-24 10:36 (vy.nguyen12@thehutgroup.com) | N10: 2026-06-24 02:23 (sa-bpswcbdsql01@thg-beauty.iam.gserviceaccount.com) 2026-06-24 02:23 (sa-bpswcbdsql01@thg-beauty.iam.gserviceaccount.com) 2026-06-24 02:23 (sa-bpswcbdsql01@thg-beauty.iam.gserviceaccount.com) 2026-06-24 02:23 (sa-bpswcbdsql01@thg-beauty.iam.gserviceaccount.com) 2026-06-24 02:23 (sa-bpswcbdsql01@thg-beauty.iam.gserviceaccount.com) | O10: 46197.1 | P10: =IF($Q10="DELETE",IF($S10="CONFIRMED: NO MODS > 1YR","CONFIRMED: NO MODS > 1YR","DO NOT DELETE — not defensibly confirmed"),IF($Q10="HOLD","DO NOT DELETE — HOLD (Charlie review)",IF($Q10="KEEP","DO NOT DELETE — KEEP",IF(ISNUMBER(SEARCH("REVIEW",$Q10)),"DO NOT DELETE — REVIEW pending",$S10)))) -> CONFIRMED: NO MODS > 1YR | Q10: {=_xlfn.IFS(AND($A10="thg-beauty",ISNUMBER(SEARCH("liveramp",$C10))),"DELETE",$A10="agile-bonbon-662",_xlfn.IFS(LEFT($G10,9)="Tranche 1","DELETE",$C10="Sessions_Level_1_All_Sites","KEEP",ISNUMBER(--$C10),"REVIEW — UA raw logs",$C10="Emag_Reporting","KEEP",$C10="Nutrition_Data_Archived_Tables","KEEP",$C10="EU_Data","KEEP",TRUE,"REVIEW"),OR($A10="thg-influencer",$A10="thg-ingenuity",$A10="thg-central-marketing",$A10="thg-seoclarity"),"HOLD",TRUE,"")} | R10: {=_xlfn.IFS(AND($A10="thg-beauty",ISNUMBER(SEARCH("liveramp",$C10))),"thg-beauty Liveramp dataset — confirmed safe to delete",$A10="agile-bonbon-662",_xlfn.IFS(LEFT($G10,9)="Tranche 1","Tranche 1: cleared",$C10="Sessions_Level_1_All_Sites","Downstream aggregation of UA raw logs — keep if raw tables go",ISNUMBER(--$C10),"UA raw site logs (account ID) — keep pending audit-retention check",$C10="Emag_Reporting","Legacy but likely needed",$C10="Nutrition_Data_Archived_Tables","Worth keeping",$C10="EU_Data","Static lookup tables — scripts still reference (smoke-test risk)",TRUE,"Review"),OR($A10="thg-influencer",$A10="thg-ingenuity",$A10="thg-central-marketing",$A10="thg-seoclarity"),"HOLD — Charlie Stringer to review before deletion",TRUE,"")} | S10: CONFIRMED: NO MODS > 1YR
A11: thg-beauty | B11: eu | C11: Retention | D11: No Description | E11: 850.97 | F11: 17.02 | G11: Active | H11: Low | I11: 0 | J11: 0 | K11: 46197.423 | L11: 46197.313 | M11: 2026-06-24 10:09 (beauty-data@agile-bonbon-662.iam.gserviceaccount.com) 2026-06-24 10:05 (beauty-data@agile-bonbon-662.iam.gserviceaccount.com) 2026-06-24 10:05 (beauty-data@agile-bonbon-662.iam.gserviceaccount.com) 2026-06-24 10:05 (beauty-data@agile-bonbon-662.iam.gserviceaccount.com) 2026-06-24 10:05 (beauty-data@agile-bonbon-662.iam.gserviceaccount.com) | N11: 2026-06-24 07:30 (Liam.Lim79@thg.com) 2026-06-24 06:15 (amalu.thevalakara21@thg.com) 2026-06-24 06:15 (amalu.thevalakara21@thg.com) 2026-06-24 06:10 (amalu.thevalakara21@thg.com) 2026-06-24 05:12 (sa-bpswcbdsql01@thg-beauty.iam.gserviceaccount.com) | O11: 46197.313 | P11: =IF($Q11="DELETE",IF($S11="CONFIRMED: NO MODS > 1YR","CONFIRMED: NO MODS > 1YR","DO NOT DELETE — not defensibly confirmed"),IF($Q11="HOLD","DO NOT DELETE — HOLD (Charlie review)",IF($Q11="KEEP","DO NOT DELETE — KEEP",IF(ISNUMBER(SEARCH("REVIEW",$Q11)),"DO NOT DELETE — REVIEW pending",$S11)))) -> CONFIRMED: NO MODS > 1YR | Q11: {=_xlfn.IFS(AND($A11="thg-beauty",ISNUMBER(SEARCH("liveramp",$C11))),"DELETE",$A11="agile-bonbon-662",_xlfn.IFS(LEFT($G11,9)="Tranche 1","DELETE",$C11="Sessions_Level_1_All_Sites","KEEP",ISNUMBER(--$C11),"REVIEW — UA raw logs",$C11="Emag_Reporting","KEEP",$C11="Nutrition_Data_Archived_Tables","KEEP",$C11="EU_Data","KEEP",TRUE,"REVIEW"),OR($A11="thg-influencer",$A11="thg-ingenuity",$A11="thg-central-marketing",$A11="thg-seoclarity"),"HOLD",TRUE,"")} | R11: {=_xlfn.IFS(AND($A11="thg-beauty",ISNUMBER(SEARCH("liveramp",$C11))),"thg-beauty Liveramp dataset — confirmed safe to delete",$A11="agile-bonbon-662",_xlfn.IFS(LEFT($G11,9)="Tranche 1","Tranche 1: cleared",$C11="Sessions_Level_1_All_Sites","Downstream aggregation of UA raw logs — keep if raw tables go",ISNUMBER(--$C11),"UA raw site logs (account ID) — keep pending audit-retention check",$C11="Emag_Reporting","Legacy but likely needed",$C11="Nutrition_Data_Archived_Tables","Worth keeping",$C11="EU_Data","Static lookup tables — scripts still reference (smoke-test risk)",TRUE,"Review"),OR($A11="thg-influencer",$A11="thg-ingenuity",$A11="thg-central-marketing",$A11="thg-seoclarity"),"HOLD — Charlie Stringer to review before deletion",TRUE,"")} | S11: CONFIRMED: NO MODS > 1YR
A12: thg-beauty | B12: eu | C12: Foundation_Finder | D12: No Description | E12: 740.27 | F12: 14.81 | G12: Active | H12: Low | I12: 0 | J12: 0 | K12: 46197.336 | L12: 46197.107 | M12: 2026-06-24 08:03 (beauty-data@agile-bonbon-662.iam.gserviceaccount.com) 2026-06-24 08:03 (beauty-data@agile-bonbon-662.iam.gserviceaccount.com) 2026-06-24 08:03 (beauty-data@agile-bonbon-662.iam.gserviceaccount.com) 2026-06-24 08:03 (beauty-data@agile-bonbon-662.iam.gserviceaccount.com) 2026-06-24 08:02 (beauty-data@agile-bonbon-662.iam.gserviceaccount.com) | N12: 2026-06-24 02:34 (sa-bpswcbdsql01@thg-beauty.iam.gserviceaccount.com) 2026-06-24 02:34 (sa-bpswcbdsql01@thg-beauty.iam.gserviceaccount.com) 2026-06-24 02:34 (sa-bpswcbdsql01@thg-beauty.iam.gserviceaccount.com) 2026-06-24 02:34 (sa-bpswcbdsql01@thg-beauty.iam.gserviceaccount.com) 2026-06-24 02:34 (sa-bpswcbdsql01@thg-beauty.iam.gserviceaccount.com) | O12: 46197.107 | P12: =IF($Q12="DELETE",IF($S12="CONFIRMED: NO MODS > 1YR","CONFIRMED: NO MODS > 1YR","DO NOT DELETE — not defensibly confirmed"),IF($Q12="HOLD","DO NOT DELETE — HOLD (Charlie review)",IF($Q12="KEEP","DO NOT DELETE — KEEP",IF(ISNUMBER(SEARCH("REVIEW",$Q12)),"DO NOT DELETE — REVIEW pending",$S12)))) -> CONFIRMED: NO MODS > 1YR | Q12: {=_xlfn.IFS(AND($A12="thg-beauty",ISNUMBER(SEARCH("liveramp",$C12))),"DELETE",$A12="agile-bonbon-662",_xlfn.IFS(LEFT($G12,9)="Tranche 1","DELETE",$C12="Sessions_Level_1_All_Sites","KEEP",ISNUMBER(--$C12),"REVIEW — UA raw logs",$C12="Emag_Reporting","KEEP",$C12="Nutrition_Data_Archived_Tables","KEEP",$C12="EU_Data","KEEP",TRUE,"REVIEW"),OR($A12="thg-influencer",$A12="thg-ingenuity",$A12="thg-central-marketing",$A12="thg-seoclarity"),"HOLD",TRUE,"")} | R12: {=_xlfn.IFS(AND($A12="thg-beauty",ISNUMBER(SEARCH("liveramp",$C12))),"thg-beauty Liveramp dataset — confirmed safe to delete",$A12="agile-bonbon-662",_xlfn.IFS(LEFT($G12,9)="Tranche 1","Tranche 1: cleared",$C12="Sessions_Level_1_All_Sites","Downstream aggregation of UA raw logs — keep if raw tables go",ISNUMBER(--$C12),"UA raw site logs (account ID) — keep pending audit-retention check",$C12="Emag_Reporting","Legacy but likely needed",$C12="Nutrition_Data_Archived_Tables","Worth keeping",$C12="EU_Data","Static lookup tables — scripts still reference (smoke-test risk)",TRUE,"Review"),OR($A12="thg-influencer",$A12="thg-ingenuity",$A12="thg-central-marketing",$A12="thg-seoclarity"),"HOLD — Charlie Stringer to review before deletion",TRUE,"")} | S12: CONFIRMED: NO MODS > 1YR
A13: thg-beauty | B13: eu | C13: Category_KPI | D13: No Description | E13: 719.05 | F13: 14.38 | G13: Active | H13: Low | I13: 0 | J13: 0 | K13: 46197.377 | L13: 46197.121 | M13: 2026-06-24 09:03 (jasmin.cengeloglu96@thehutgroup.com) 2026-06-24 07:03 (beauty-data@agile-bonbon-662.iam.gserviceaccount.com) 2026-06-24 07:03 (beauty-data@agile-bonbon-662.iam.gserviceaccount.com) 2026-06-24 06:19 (beauty-data@agile-bonbon-662.iam.gserviceaccount.com) 2026-06-24 06:03 (beauty-data@agile-bonbon-662.iam.gserviceaccount.com) | N13: 2026-06-24 02:54 (sa-bpswcbdsql01@thg-beauty.iam.gserviceaccount.com) 2026-06-24 02:54 (sa-bpswcbdsql01@thg-beauty.iam.gserviceaccount.com) 2026-06-24 02:51 (sa-bpswcbdsql01@thg-beauty.iam.gserviceaccount.com) 2026-06-24 02:51 (sa-bpswcbdsql01@thg-beauty.iam.gserviceaccount.com) 2026-06-24 02:51 (sa-bpswcbdsql01@thg-beauty.iam.gserviceaccount.com) | O13: 46197.121 | P13: =IF($Q13="DELETE",IF($S13="CONFIRMED: NO MODS > 1YR","CONFIRMED: NO MODS > 1YR","DO NOT DELETE — not defensibly confirmed"),IF($Q13="HOLD","DO NOT DELETE — HOLD (Charlie review)",IF($Q13="KEEP","DO NOT DELETE — KEEP",IF(ISNUMBER(SEARCH("REVIEW",$Q13)),"DO NOT DELETE — REVIEW pending",$S13)))) -> CONFIRMED: NO MODS > 1YR | Q13: {=_xlfn.IFS(AND($A13="thg-beauty",ISNUMBER(SEARCH("liveramp",$C13))),"DELETE",$A13="agile-bonbon-662",_xlfn.IFS(LEFT($G13,9)="Tranche 1","DELETE",$C13="Sessions_Level_1_All_Sites","KEEP",ISNUMBER(--$C13),"REVIEW — UA raw logs",$C13="Emag_Reporting","KEEP",$C13="Nutrition_Data_Archived_Tables","KEEP",$C13="EU_Data","KEEP",TRUE,"REVIEW"),OR($A13="thg-influencer",$A13="thg-ingenuity",$A13="thg-central-marketing",$A13="thg-seoclarity"),"HOLD",TRUE,"")} | R13: {=_xlfn.IFS(AND($A13="thg-beauty",ISNUMBER(SEARCH("liveramp",$C13))),"thg-beauty Liveramp dataset — confirmed safe to delete",$A13="agile-bonbon-662",_xlfn.IFS(LEFT($G13,9)="Tranche 1","Tranche 1: cleared",$C13="Sessions_Level_1_All_Sites","Downstream aggregation of UA raw logs — keep if raw tables go",ISNUMBER(--$C13),"UA raw site logs (account ID) — keep pending audit-retention check",$C13="Emag_Reporting","Legacy but likely needed",$C13="Nutrition_Data_Archived_Tables","Worth keeping",$C13="EU_Data","Static lookup tables — scripts still reference (smoke-test risk)",TRUE,"Review"),OR($A13="thg-influencer",$A13="thg-ingenuity",$A13="thg-central-marketing",$A13="thg-seoclarity"),"HOLD — Charlie Stringer to review before deletion",TRUE,"")} | S13: CONFIRMED: NO MODS > 1YR
... A27: thg-ml-dev | B27: eu | C27: logistics__permanent | D27: No Description | E27: 0.07 | F27: 0 | G27: Active | H27: Low | I27: 169 | J27: 170 | K27: 46027.463 | L27: 46027.382 | M27: 2026-01-05 11:07 (laid@thehutgroup.com) 2026-01-05 09:09 (logistics@thg-ml-dev.iam.gserviceaccount.com) 2026-01-05 09:09 (logistics@thg-ml-dev.iam.gserviceaccount.com) 2026-01-05 09:03 (logistics@thg-ml-dev.iam.gserviceaccount.com) 2026-01-05 09:03 (logistics@thg-ml-dev.iam.gserviceaccount.com) | N27: 2026-01-05 09:09 (logistics@thg-ml-dev.iam.gserviceaccount.com) 2026-01-05 09:09 (logistics@thg-ml-dev.iam.gserviceaccount.com) | O27: 46027.382 | P27: =IF($Q27="DELETE",IF($S27="CONFIRMED: NO MODS > 1YR","CONFIRMED: NO MODS > 1YR","DO NOT DELETE — not defensibly confirmed"),IF($Q27="HOLD","DO NOT DELETE — HOLD (Charlie review)",IF($Q27="KEEP","DO NOT DELETE — KEEP",IF(ISNUMBER(SEARCH("REVIEW",$Q27)),"DO NOT DELETE — REVIEW pending",$S27)))) -> CONFIRMED: NO MODS > 1YR | Q27: {=_xlfn.IFS(AND($A27="thg-beauty",ISNUMBER(SEARCH("liveramp",$C27))),"DELETE",$A27="agile-bonbon-662",_xlfn.IFS(LEFT($G27,9)="Tranche 1","DELETE",$C27="Sessions_Level_1_All_Sites","KEEP",ISNUMBER(--$C27),"REVIEW — UA raw logs",$C27="Emag_Reporting","KEEP",$C27="Nutrition_Data_Archived_Tables","KEEP",$C27="EU_Data","KEEP",TRUE,"REVIEW"),OR($A27="thg-influencer",$A27="thg-ingenuity",$A27="thg-central-marketing",$A27="thg-seoclarity"),"HOLD",TRUE,"")} | R27: {=_xlfn.IFS(AND($A27="thg-beauty",ISNUMBER(SEARCH("liveramp",$C27))),"thg-beauty Liveramp dataset — confirmed safe to delete",$A27="agile-bonbon-662",_xlfn.IFS(LEFT($G27,9)="Tranche 1","Tranche 1: cleared",$C27="Sessions_Level_1_All_Sites","Downstream aggregation of UA raw logs — keep if raw tables go",ISNUMBER(--$C27),"UA raw site logs (account ID) — keep pending audit-retention check",$C27="Emag_Reporting","Legacy but likely needed",$C27="Nutrition_Data_Archived_Tables","Worth keeping",$C27="EU_Data","Static lookup tables — scripts still reference (smoke-test risk)",TRUE,"Review"),OR($A27="thg-influencer",$A27="thg-ingenuity",$A27="thg-central-marketing",$A27="thg-seoclarity"),"HOLD — Charlie Stringer to review before deletion",TRUE,"")} | S27: CONFIRMED: NO MODS > 1YR
A28: thg-ml-dev | B28: eu | C28: geekplus_sku_classification | D28: No Description | E28: 0.05 | F28: 0 | G28: Active | H28: Low | I28: 169 | J28: 169 | K28: 46027.46 | M28: 2026-01-05 11:01 (laid@thehutgroup.com) 2026-01-05 10:33 (laid@thehutgroup.com) | N28: No Write Access (180d) | O28: 46027.483 | P28: =IF($Q28="DELETE",IF($S28="CONFIRMED: NO MODS > 1YR","CONFIRMED: NO MODS > 1YR","DO NOT DELETE — not defensibly confirmed"),IF($Q28="HOLD","DO NOT DELETE — HOLD (Charlie review)",IF($Q28="KEEP","DO NOT DELETE — KEEP",IF(ISNUMBER(SEARCH("REVIEW",$Q28)),"DO NOT DELETE — REVIEW pending",$S28)))) -> CONFIRMED: NO MODS > 1YR | Q28: {=_xlfn.IFS(AND($A28="thg-beauty",ISNUMBER(SEARCH("liveramp",$C28))),"DELETE",$A28="agile-bonbon-662",_xlfn.IFS(LEFT($G28,9)="Tranche 1","DELETE",$C28="Sessions_Level_1_All_Sites","KEEP",ISNUMBER(--$C28),"REVIEW — UA raw logs",$C28="Emag_Reporting","KEEP",$C28="Nutrition_Data_Archived_Tables","KEEP",$C28="EU_Data","KEEP",TRUE,"REVIEW"),OR($A28="thg-influencer",$A28="thg-ingenuity",$A28="thg-central-marketing",$A28="thg-seoclarity"),"HOLD",TRUE,"")} | R28: {=_xlfn.IFS(AND($A28="thg-beauty",ISNUMBER(SEARCH("liveramp",$C28))),"thg-beauty Liveramp dataset — confirmed safe to delete",$A28="agile-bonbon-662",_xlfn.IFS(LEFT($G28,9)="Tranche 1","Tranche 1: cleared",$C28="Sessions_Level_1_All_Sites","Downstream aggregation of UA raw logs — keep if raw tables go",ISNUMBER(--$C28),"UA raw site logs (account ID) — keep pending audit-retention check",$C28="Emag_Reporting","Legacy but likely needed",$C28="Nutrition_Data_Archived_Tables","Worth keeping",$C28="EU_Data","Static lookup tables — scripts still reference (smoke-test risk)",TRUE,"Review"),OR($A28="thg-influencer",$A28="thg-ingenuity",$A28="thg-central-marketing",$A28="thg-seoclarity"),"HOLD — Charlie Stringer to review before deletion",TRUE,"")} | S28: CONFIRMED: NO MODS > 1YR
A29: thg-ml-staging | B29: eu | C29: autostore_simulator | D29: No Description | E29: 0.16 | F29: 0 | G29: Active | H29: Low | I29: 166 | J29: 172 | K29: 46030.467 | M29: 2026-01-08 11:12 (ml-spaces@thg-ml-staging.iam.gserviceaccount.com) 2026-01-08 11:12 (ml-spaces@thg-ml-staging.iam.gserviceaccount.com) 2026-01-08 11:12 (ml-spaces@thg-ml-staging.iam.gserviceaccount.com) 2026-01-08 11:12 (ml-spaces@thg-ml-staging.iam.gserviceaccount.com) 2026-01-08 11:12 (ml-spaces@thg-ml-staging.iam.gserviceaccount.com) | N29: No Write Access (180d) | O29: 46024.515 | P29: =IF($Q29="DELETE",IF($S29="CONFIRMED: NO MODS > 1YR","CONFIRMED: NO MODS > 1YR","DO NOT DELETE — not defensibly confirmed"),IF($Q29="HOLD","DO NOT DELETE — HOLD (Charlie review)",IF($Q29="KEEP","DO NOT DELETE — KEEP",IF(ISNUMBER(SEARCH("REVIEW",$Q29)),"DO NOT DELETE — REVIEW pending",$S29)))) -> CONFIRMED: NO MODS > 1YR | Q29: {=_xlfn.IFS(AND($A29="thg-beauty",ISNUMBER(SEARCH("liveramp",$C29))),"DELETE",$A29="agile-bonbon-662",_xlfn.IFS(LEFT($G29,9)="Tranche 1","DELETE",$C29="Sessions_Level_1_All_Sites","KEEP",ISNUMBER(--$C29),"REVIEW — UA raw logs",$C29="Emag_Reporting","KEEP",$C29="Nutrition_Data_Archived_Tables","KEEP",$C29="EU_Data","KEEP",TRUE,"REVIEW"),OR($A29="thg-influencer",$A29="thg-ingenuity",$A29="thg-central-marketing",$A29="thg-seoclarity"),"HOLD",TRUE,"")} | R29: {=_xlfn.IFS(AND($A29="thg-beauty",ISNUMBER(SEARCH("liveramp",$C29))),"thg-beauty Liveramp dataset — confirmed safe to delete",$A29="agile-bonbon-662",_xlfn.IFS(LEFT($G29,9)="Tranche 1","Tranche 1: cleared",$C29="Sessions_Level_1_All_Sites","Downstream aggregation of UA raw logs — keep if raw tables go",ISNUMBER(--$C29),"UA raw site logs (account ID) — keep pending audit-retention check",$C29="Emag_Reporting","Legacy but likely needed",$C29="Nutrition_Data_Archived_Tables","Worth keeping",$C29="EU_Data","Static lookup tables — scripts still reference (smoke-test risk)",TRUE,"Review"),OR($A29="thg-influencer",$A29="thg-ingenuity",$A29="thg-central-marketing",$A29="thg-seoclarity"),"HOLD — Charlie Stringer to review before deletion",TRUE,"")} | S29: CONFIRMED: NO MODS > 1YR
A30: thg-content | B30: eu | C30: THG_Content_Details | D30: No Description | E30: 1.7 | F30: 0.03 | G30: Active | H30: Low | I30: 156 | J30: 156 | K30: 46041.212 | L30: 46041.328 | M30: 2026-01-19 05:05 (central-marketing-credentials@thg-central-marketing.iam.gserviceaccount.com) 2026-01-19 05:05 (central-marketing-credentials@thg-central-marketing.iam.gserviceaccount.com) 2026-01-19 05:05 (central-marketing-credentials@thg-central-marketing.iam.gserviceaccount.com) 2026-01-17 05:05 (central-marketing-credentials@thg-central-marketing.iam.gserviceaccount.com) 2026-01-17 05:05 (central-marketing-credentials@thg-central-marketing.iam.gserviceaccount.com) | N30: 2026-01-19 07:52 (central-marketing-credentials@thg-central-marketing.iam.gserviceaccount.com) 2026-01-18 07:52 (central-marketing-credentials@thg-central-marketing.iam.gserviceaccount.com) 2026-01-17 07:52 (central-marketing-credentials@thg-central-marketing.iam.gserviceaccount.com) 2026-01-16 07:52 (central-marketing-credentials@thg-central-marketing.iam.gserviceaccount.com) 2026-01-15 07:52 (central-marketing-credentials@thg-central-marketing.iam.gserviceaccount.com) | O30: 46041.328 | P30: =IF($Q30="DELETE",IF($S30="CONFIRMED: NO MODS > 1YR","CONFIRMED: NO MODS > 1YR","DO NOT DELETE — not defensibly confirmed"),IF($Q30="HOLD","DO NOT DELETE — HOLD (Charlie review)",IF($Q30="KEEP","DO NOT DELETE — KEEP",IF(ISNUMBER(SEARCH("REVIEW",$Q30)),"DO NOT DELETE — REVIEW pending",$S30)))) -> CONFIRMED: NO MODS > 1YR | Q30: {=_xlfn.IFS(AND($A30="thg-beauty",ISNUMBER(SEARCH("liveramp",$C30))),"DELETE",$A30="agile-bonbon-662",_xlfn.IFS(LEFT($G30,9)="Tranche 1","DELETE",$C30="Sessions_Level_1_All_Sites","KEEP",ISNUMBER(--$C30),"REVIEW — UA raw logs",$C30="Emag_Reporting","KEEP",$C30="Nutrition_Data_Archived_Tables","KEEP",$C30="EU_Data","KEEP",TRUE,"REVIEW"),OR($A30="thg-influencer",$A30="thg-ingenuity",$A30="thg-central-marketing",$A30="thg-seoclarity"),"HOLD",TRUE,"")} | R30: {=_xlfn.IFS(AND($A30="thg-beauty",ISNUMBER(SEARCH("liveramp",$C30))),"thg-beauty Liveramp dataset — confirmed safe to delete",$A30="agile-bonbon-662",_xlfn.IFS(LEFT($G30,9)="Tranche 1","Tranche 1: cleared",$C30="Sessions_Level_1_All_Sites","Downstream aggregation of UA raw logs — keep if raw tables go",ISNUMBER(--$C30),"UA raw site logs (account ID) — keep pending audit-retention check",$C30="Emag_Reporting","Legacy but likely needed",$C30="Nutrition_Data_Archived_Tables","Worth keeping",$C30="EU_Data","Static lookup tables — scripts still reference (smoke-test risk)",TRUE,"Review"),OR($A30="thg-influencer",$A30="thg-ingenuity",$A30="thg-central-marketing",$A30="thg-seoclarity"),"HOLD — Charlie Stringer to review before deletion",TRUE,"")} | S30: CONFIRMED: NO MODS > 1YR
A31: thg-ingenuity | B31: eu | C31: analytics_351380246 | D31: No Description | E31: 0.06 | F31: 0 | G31: Active | H31: Low | I31: 152 | J31: 152 | K31: 46045.419 | L31: 46045.368 | M31: 2026-01-23 10:03 (ga4-sessions-level-1-ingenuity@thg-ingenuity.iam.gserviceaccount.com) 2026-01-22 22:03 (ga4-sessions-level-1-ingenuity@thg-ingenuity.iam.gserviceaccount.com) 2026-01-22 20:03 (ga4-sessions-level-1-ingenuity@thg-ingenuity.iam.gserviceaccount.com) 2026-01-20 10:03 (ga4-sessions-level-1-ingenuity@thg-ingenuity.iam.gserviceaccount.com) 2026-01-19 14:04 (ga4-sessions-level-1-ingenuity@thg-ingenuity.iam.gserviceaccount.com) | N31: 2026-01-23 08:50 (firebase-measurement@system.gserviceaccount.com) 2026-01-20 08:57 (firebase-measurement@system.gserviceaccount.com) 2026-01-19 09:39 (firebase-measurement@system.gserviceaccount.com) 2026-01-18 08:31 (firebase-measurement@system.gserviceaccount.com) 2026-01-17 09:04 (firebase-measurement@system.gserviceaccount.com) | O31: 46045.368 | P31: =IF($Q31="DELETE",IF($S31="CONFIRMED: NO MODS > 1YR","CONFIRMED: NO MODS > 1YR","DO NOT DELETE — not defensibly confirmed"),IF($Q31="HOLD","DO NOT DELETE — HOLD (Charlie review)",IF($Q31="KEEP","DO NOT DELETE — KEEP",IF(ISNUMBER(SEARCH("REVIEW",$Q31)),"DO NOT DELETE — REVIEW pending",$S31)))) -> DO NOT DELETE — HOLD (Charlie review) | Q31: {=_xlfn.IFS(AND($A31="thg-beauty",ISNUMBER(SEARCH("liveramp",$C31))),"DELETE",$A31="agile-bonbon-662",_xlfn.IFS(LEFT($G31,9)="Tranche 1","DELETE",$C31="Sessions_Level_1_All_Sites","KEEP",ISNUMBER(--$C31),"REVIEW — UA raw logs",$C31="Emag_Reporting","KEEP",$C31="Nutrition_Data_Archived_Tables","KEEP",$C31="EU_Data","KEEP",TRUE,"REVIEW"),OR($A31="thg-influencer",$A31="thg-ingenuity",$A31="thg-central-marketing",$A31="thg-seoclarity"),"HOLD",TRUE,"")} -> HOLD | R31: {=_xlfn.IFS(AND($A31="thg-beauty",ISNUMBER(SEARCH("liveramp",$C31))),"thg-beauty Liveramp dataset — confirmed safe to delete",$A31="agile-bonbon-662",_xlfn.IFS(LEFT($G31,9)="Tranche 1","Tranche 1: cleared",$C31="Sessions_Level_1_All_Sites","Downstream aggregation of UA raw logs — keep if raw tables go",ISNUMBER(--$C31),"UA raw site logs (account ID) — keep pending audit-retention check",$C31="Emag_Reporting","Legacy but likely needed",$C31="Nutrition_Data_Archived_Tables","Worth keeping",$C31="EU_Data","Static lookup tables — scripts still reference (smoke-test risk)",TRUE,"Review"),OR($A31="thg-influencer",$A31="thg-ingenuity",$A31="thg-central-marketing",$A31="thg-seoclarity"),"HOLD — Charlie Stringer to review before deletion",TRUE,"")} -> HOLD — Charlie Stringer to review before deletion | S31: CONFIRMED: NO MODS > 1YR
A32: thg-data-personify | B32: eu | C32: bulk_load | D32: No Description | E32: 89.15 | F32: 1.78 | G32: Active | H32: Low | I32: 147 | J32: 355 | K32: 46049.821 | L32: 46049.821 | M32: 2026-01-27 19:42 (whitejo@thehutgroup.com) 2026-01-27 19:34 (whitejo@thehutgroup.com) 2026-01-27 19:34 (whitejo@thehutgroup.com) 2026-01-27 19:31 (whitejo@thehutgroup.com) 2026-01-27 18:25 (whitejo@thehutgroup.com) | N32: 2026-01-27 19:42 (whitejo@thehutgroup.com) 2026-01-27 19:42 (whitejo@thehutgroup.com) 2026-01-27 19:40 (whitejo@thehutgroup.com) 2026-01-27 19:34 (whitejo@thehutgroup.com) 2026-01-27 19:31 (whitejo@thehutgroup.com) | O32: 45842.374 | P32: =IF($Q32="DELETE",IF($S32="CONFIRMED: NO MODS > 1YR","CONFIRMED: NO MODS > 1YR","DO NOT DELETE — not defensibly confirmed"),IF($Q32="HOLD","DO NOT DELETE — HOLD (Charlie review)",IF($Q32="KEEP","DO NOT DELETE — KEEP",IF(ISNUMBER(SEARCH("REVIEW",$Q32)),"DO NOT DELETE — REVIEW pending",$S32)))) -> CONFIRMED: NO MODS > 1YR | Q32: {=_xlfn.IFS(AND($A32="thg-beauty",ISNUMBER(SEARCH("liveramp",$C32))),"DELETE",$A32="agile-bonbon-662",_xlfn.IFS(LEFT($G32,9)="Tranche 1","DELETE",$C32="Sessions_Level_1_All_Sites","KEEP",ISNUMBER(--$C32),"REVIEW — UA raw logs",$C32="Emag_Reporting","KEEP",$C32="Nutrition_Data_Archived_Tables","KEEP",$C32="EU_Data","KEEP",TRUE,"REVIEW"),OR($A32="thg-influencer",$A32="thg-ingenuity",$A32="thg-central-marketing",$A32="thg-seoclarity"),"HOLD",TRUE,"")} | R32: {=_xlfn.IFS(AND($A32="thg-beauty",ISNUMBER(SEARCH("liveramp",$C32))),"thg-beauty Liveramp dataset — confirmed safe to delete",$A32="agile-bonbon-662",_xlfn.IFS(LEFT($G32,9)="Tranche 1","Tranche 1: cleared",$C32="Sessions_Level_1_All_Sites","Downstream aggregation of UA raw logs — keep if raw tables go",ISNUMBER(--$C32),"UA raw site logs (account ID) — keep pending audit-retention check",$C32="Emag_Reporting","Legacy but likely needed",$C32="Nutrition_Data_Archived_Tables","Worth keeping",$C32="EU_Data","Static lookup tables — scripts still reference (smoke-test risk)",TRUE,"Review"),OR($A32="thg-influencer",$A32="thg-ingenuity",$A32="thg-central-marketing",$A32="thg-seoclarity"),"HOLD — Charlie Stringer to review before deletion",TRUE,"")} | S32: CONFIRMED: NO MODS > 1YR
A33: thg-ingenuity | B33: eu | C33: analytics_376106118 | D33: No Description | E33: 0.01 | F33: 0 | G33: Active | H33: Low | I33: 133 | J33: 133 | L33: 46064.397 | M33: No Read Access (180d) | N33: 2026-02-11 09:32 (firebase-measurement@system.gserviceaccount.com) | O33: 46064.397 | P33: =IF($Q33="DELETE",IF($S33="CONFIRMED: NO MODS > 1YR","CONFIRMED: NO MODS > 1YR","DO NOT DELETE — not defensibly confirmed"),IF($Q33="HOLD","DO NOT DELETE — HOLD (Charlie review)",IF($Q33="KEEP","DO NOT DELETE — KEEP",IF(ISNUMBER(SEARCH("REVIEW",$Q33)),"DO NOT DELETE — REVIEW pending",$S33)))) -> DO NOT DELETE — HOLD (Charlie review) | Q33: {=_xlfn.IFS(AND($A33="thg-beauty",ISNUMBER(SEARCH("liveramp",$C33))),"DELETE",$A33="agile-bonbon-662",_xlfn.IFS(LEFT($G33,9)="Tranche 1","DELETE",$C33="Sessions_Level_1_All_Sites","KEEP",ISNUMBER(--$C33),"REVIEW — UA raw logs",$C33="Emag_Reporting","KEEP",$C33="Nutrition_Data_Archived_Tables","KEEP",$C33="EU_Data","KEEP",TRUE,"REVIEW"),OR($A33="thg-influencer",$A33="thg-ingenuity",$A33="thg-central-marketing",$A33="thg-seoclarity"),"HOLD",TRUE,"")} -> HOLD | R33: {=_xlfn.IFS(AND($A33="thg-beauty",ISNUMBER(SEARCH("liveramp",$C33))),"thg-beauty Liveramp dataset — confirmed safe to delete",$A33="agile-bonbon-662",_xlfn.IFS(LEFT($G33,9)="Tranche 1","Tranche 1: cleared",$C33="Sessions_Level_1_All_Sites","Downstream aggregation of UA raw logs — keep if raw tables go",ISNUMBER(--$C33),"UA raw site logs (account ID) — keep pending audit-retention check",$C33="Emag_Reporting","Legacy but likely needed",$C33="Nutrition_Data_Archived_Tables","Worth keeping",$C33="EU_Data","Static lookup tables — scripts still reference (smoke-test risk)",TRUE,"Review"),OR($A33="thg-influencer",$A33="thg-ingenuity",$A33="thg-central-marketing",$A33="thg-seoclarity"),"HOLD — Charlie Stringer to review before deletion",TRUE,"")} -> HOLD — Charlie Stringer to review before deletion | S33: CONFIRMED: NO MODS > 1YR
A34: thg-ml-dev | B34: eu | C34: product_gen__permanent | D34: No Description | E34: 0.02 | F34: 0 | G34: Active | H34: Low | I34: 124 | J34: 124 | K34: 46072.482 | L34: 46072.474 | M34: 2026-02-19 11:34 (marije.vanhattum74@thehutgroup.com) 2026-02-19 11:23 (marije.vanhattum74@thehutgroup.com) 2026-02-19 11:23 (marije.vanhattum74@thehutgroup.com) 2026-02-19 11:21 (marije.vanhattum74@thehutgroup.com) 2026-02-19 11:21 (marije.vanhattum74@thehutgroup.com) | N34: 2026-02-19 11:23 (marije.vanhattum74@thehutgroup.com) 2026-02-19 11:21 (marije.vanhattum74@thehutgroup.com) 2026-02-19 11:21 (marije.vanhattum74@thehutgroup.com) 2026-02-19 11:21 (marije.vanhattum74@thehutgroup.com) 2026-02-19 11:21 (marije.vanhattum74@thehutgroup.com) | O34: 46072.474 | P34: =IF($Q34="DELETE",IF($S34="CONFIRMED: NO MODS > 1YR","CONFIRMED: NO MODS > 1YR","DO NOT DELETE — not defensibly confirmed"),IF($Q34="HOLD","DO NOT DELETE — HOLD (Charlie review)",IF($Q34="KEEP","DO NOT DELETE — KEEP",IF(ISNUMBER(SEARCH("REVIEW",$Q34)),"DO NOT DELETE — REVIEW pending",$S34)))) -> CONFIRMED: NO MODS > 1YR | Q34: {=_xlfn.IFS(AND($A34="thg-beauty",ISNUMBER(SEARCH("liveramp",$C34))),"DELETE",$A34="agile-bonbon-662",_xlfn.IFS(LEFT($G34,9)="Tranche 1","DELETE",$C34="Sessions_Level_1_All_Sites","KEEP",ISNUMBER(--$C34),"REVIEW — UA raw logs",$C34="Emag_Reporting","KEEP",$C34="Nutrition_Data_Archived_Tables","KEEP",$C34="EU_Data","KEEP",TRUE,"REVIEW"),OR($A34="thg-influencer",$A34="thg-ingenuity",$A34="thg-central-marketing",$A34="thg-seoclarity"),"HOLD",TRUE,"")} | R34: {=_xlfn.IFS(AND($A34="thg-beauty",ISNUMBER(SEARCH("liveramp",$C34))),"thg-beauty Liveramp dataset — confirmed safe to delete",$A34="agile-bonbon-662",_xlfn.IFS(LEFT($G34,9)="Tranche 1","Tranche 1: cleared",$C34="Sessions_Level_1_All_Sites","Downstream aggregation of UA raw logs — keep if raw tables go",ISNUMBER(--$C34),"UA raw site logs (account ID) — keep pending audit-retention check",$C34="Emag_Reporting","Legacy but likely needed",$C34="Nutrition_Data_Archived_Tables","Worth keeping",$C34="EU_Data","Static lookup tables — scripts still reference (smoke-test risk)",TRUE,"Review"),OR($A34="thg-influencer",$A34="thg-ingenuity",$A34="thg-central-marketing",$A34="thg-seoclarity"),"HOLD — Charlie Stringer to review before deletion",TRUE,"")} | S34: CONFIRMED: NO MODS > 1YR
A35: thg-beauty | B35: eu | C35: brand_packs | D35: No Description | E35: 135.36 | F35: 2.71 | G35: Active | H35: Low | I35: 0 | J35: 0 | K35: 46196.51 | L35: 46197.25 | M35: 2026-06-23 12:14 (oksana.zherebetska23@thg.com) 2026-06-23 12:14 (oksana.zherebetska23@thg.com) 2026-06-23 11:37 (oksana.zherebetska23@thg.com) 2026-06-23 11:37 (oksana.zherebetska23@thg.com) 2026-06-23 11:35 (oksana.zherebetska23@thg.com) | N35: 2026-06-24 06:00 (jasmin.cengeloglu96@thehutgroup.com) 2026-06-24 06:00 (jasmin.cengeloglu96@thehutgroup.com) 2026-06-24 06:00 (jasmin.cengeloglu96@thehutgroup.com) 2026-06-24 06:00 (jasmin.cengeloglu96@thehutgroup.com) 2026-06-24 06:00 (jasmin.cengeloglu96@thehutgroup.com) | O35: 46197.251 | P35: =IF($Q35="DELETE",IF($S35="CONFIRMED: NO MODS > 1YR","CONFIRMED: NO MODS > 1YR","DO NOT DELETE — not defensibly confirmed"),IF($Q35="HOLD","DO NOT DELETE — HOLD (Charlie review)",IF($Q35="KEEP","DO NOT DELETE — KEEP",IF(ISNUMBER(SEARCH("REVIEW",$Q35)),"DO NOT DELETE — REVIEW pending",$S35)))) -> CONFIRMED: NO MODS > 1YR | Q35: {=_xlfn.IFS(AND($A35="thg-beauty",ISNUMBER(SEARCH("liveramp",$C35))),"DELETE",$A35="agile-bonbon-662",_xlfn.IFS(LEFT($G35,9)="Tranche 1","DELETE",$C35="Sessions_Level_1_All_Sites","KEEP",ISNUMBER(--$C35),"REVIEW — UA raw logs",$C35="Emag_Reporting","KEEP",$C35="Nutrition_Data_Archived_Tables","KEEP",$C35="EU_Data","KEEP",TRUE,"REVIEW"),OR($A35="thg-influencer",$A35="thg-ingenuity",$A35="thg-central-marketing",$A35="thg-seoclarity"),"HOLD",TRUE,"")} | R35: {=_xlfn.IFS(AND($A35="thg-beauty",ISNUMBER(SEARCH("liveramp",$C35))),"thg-beauty Liveramp dataset — confirmed safe to delete",$A35="agile-bonbon-662",_xlfn.IFS(LEFT($G35,9)="Tranche 1","Tranche 1: cleared",$C35="Sessions_Level_1_All_Sites","Downstream aggregation of UA raw logs — keep if raw tables go",ISNUMBER(--$C35),"UA raw site logs (account ID) — keep pending audit-retention check",$C35="Emag_Reporting","Legacy but likely needed",$C35="Nutrition_Data_Archived_Tables","Worth keeping",$C35="EU_Data","Static lookup tables — scripts still reference (smoke-test risk)",TRUE,"Review"),OR($A35="thg-influencer",$A35="thg-ingenuity",$A35="thg-central-marketing",$A35="thg-seoclarity"),"HOLD — Charlie Stringer to review before deletion",TRUE,"")} | S35: CONFIRMED: NO MODS > 1YR
A36: thg-finops-prod | B36: europe-west2 | C36: finops_recommendations | D36: Terraform managed. | E36: 0 | F36: 0 | G36: Active | H36: Low | I36: 120 | K36: 46077.375 | M36: 2026-02-24 08:59 (alan.dodd82@thgingenuity.com) 2026-02-17 09:12 (alan.dodd82@thgingenuity.com) | N36: No Write Access (180d) | P36: =IF($Q36="DELETE",IF($S36="CONFIRMED: NO MODS > 1YR","CONFIRMED: NO MODS > 1YR","DO NOT DELETE — not defensibly confirmed"),IF($Q36="HOLD","DO NOT DELETE — HOLD (Charlie review)",IF($Q36="KEEP","DO NOT DELETE — KEEP",IF(ISNUMBER(SEARCH("REVIEW",$Q36)),"DO NOT DELETE — REVIEW pending",$S36)))) -> REVIEW | Q36: {=_xlfn.IFS(AND($A36="thg-beauty",ISNUMBER(SEARCH("liveramp",$C36))),"DELETE",$A36="agile-bonbon-662",_xlfn.IFS(LEFT($G36,9)="Tranche 1","DELETE",$C36="Sessions_Level_1_All_Sites","KEEP",ISNUMBER(--$C36),"REVIEW — UA raw logs",$C36="Emag_Reporting","KEEP",$C36="Nutrition_Data_Archived_Tables","KEEP",$C36="EU_Data","KEEP",TRUE,"REVIEW"),OR($A36="thg-influencer",$A36="thg-ingenuity",$A36="thg-central-marketing",$A36="thg-seoclarity"),"HOLD",TRUE,"")} | R36: {=_xlfn.IFS(AND($A36="thg-beauty",ISNUMBER(SEARCH("liveramp",$C36))),"thg-beauty Liveramp dataset — confirmed safe to delete",$A36="agile-bonbon-662",_xlfn.IFS(LEFT($G36,9)="Tranche 1","Tranche 1: cleared",$C36="Sessions_Level_1_All_Sites","Downstream aggregation of UA raw logs — keep if raw tables go",ISNUMBER(--$C36),"UA raw site logs (account ID) — keep pending audit-retention check",$C36="Emag_Reporting","Legacy but likely needed",$C36="Nutrition_Data_Archived_Tables","Worth keeping",$C36="EU_Data","Static lookup tables — scripts still reference (smoke-test risk)",TRUE,"Review"),OR($A36="thg-influencer",$A36="thg-ingenuity",$A36="thg-central-marketing",$A36="thg-seoclarity"),"HOLD — Charlie Stringer to review before deletion",TRUE,"")} | S36: REVIEW
A37: thg-finops-prod | B37: europe-west2 | C37: audit_logs | D37: Terraform managed. | E37: 0 | F37: 0 | G37: Active | H37: Low | I37: 120 | K37: 46077.374 | M37: 2026-02-24 08:59 (alan.dodd82@thgingenuity.com) 2026-02-23 12:15 (alan.dodd82@thgingenuity.com) 2026-02-23 12:15 (alan.dodd82@thgingenuity.com) | N37: No Write Access (180d) | P37: =IF($Q37="DELETE",IF($S37="CONFIRMED: NO MODS > 1YR","CONFIRMED: NO MODS > 1YR","DO NOT DELETE — not defensibly confirmed"),IF($Q37="HOLD","DO NOT DELETE — HOLD (Charlie review)",IF($Q37="KEEP","DO NOT DELETE — KEEP",IF(ISNUMBER(SEARCH("REVIEW",$Q37)),"DO NOT DELETE — REVIEW pending",$S37)))) -> CONFIRMED: NO MODS > 1YR | Q37: {=_xlfn.IFS(AND($A37="thg-beauty",ISNUMBER(SEARCH("liveramp",$C37))),"DELETE",$A37="agile-bonbon-662",_xlfn.IFS(LEFT($G37,9)="Tranche 1","DELETE",$C37="Sessions_Level_1_All_Sites","KEEP",ISNUMBER(--$C37),"REVIEW — UA raw logs",$C37="Emag_Reporting","KEEP",$C37="Nutrition_Data_Archived_Tables","KEEP",$C37="EU_Data","KEEP",TRUE,"REVIEW"),OR($A37="thg-influencer",$A37="thg-ingenuity",$A37="thg-central-marketing",$A37="thg-seoclarity"),"HOLD",TRUE,"")} | R37: {=_xlfn.IFS(AND($A37="thg-beauty",ISNUMBER(SEARCH("liveramp",$C37))),"thg-beauty Liveramp dataset — confirmed safe to delete",$A37="agile-bonbon-662",_xlfn.IFS(LEFT($G37,9)="Tranche 1","Tranche 1: cleared",$C37="Sessions_Level_1_All_Sites","Downstream aggregation of UA raw logs — keep if raw tables go",ISNUMBER(--$C37),"UA raw site logs (account ID) — keep pending audit-retention check",$C37="Emag_Reporting","Legacy but likely needed",$C37="Nutrition_Data_Archived_Tables","Worth keeping",$C37="EU_Data","Static lookup tables — scripts still reference (smoke-test risk)",TRUE,"Review"),OR($A37="thg-influencer",$A37="thg-ingenuity",$A37="thg-central-marketing",$A37="thg-seoclarity"),"HOLD — Charlie Stringer to review before deletion",TRUE,"")} | S37: CONFIRMED: NO MODS > 1YR
A38: thg-beauty | B38: eu | C38: Product_Replen | D38: No Description | E38: 99.6 | F38: 1.99 | G38: Active | H38: Low | I38: 1 | J38: 42 | K38: 46195.467 | L38: 46155.389 | M38: 2026-06-22 11:11 (clare.isakson58@thehutgroup.com) 2026-06-22 11:06 (clare.isakson58@thehutgroup.com) 2026-06-21 11:11 (clare.isakson58@thehutgroup.com) 2026-06-21 11:05 (clare.isakson58@thehutgroup.com) 2026-06-19 11:06 (clare.isakson58@thehutgroup.com) | N38: 2026-05-13 09:19 (clare.isakson58@thehutgroup.com) 2026-05-13 09:19 (clare.isakson58@thehutgroup.com) 2026-05-13 09:19 (clare.isakson58@thehutgroup.com) 2026-05-13 09:19 (clare.isakson58@thehutgroup.com) 2026-03-23 14:03 (clare.isakson58@thehutgroup.com) | O38: 46155.389 | P38: =IF($Q38="DELETE",IF($S38="CONFIRMED: NO MODS > 1YR","CONFIRMED: NO MODS > 1YR","DO NOT DELETE — not defensibly confirmed"),IF($Q38="HOLD","DO NOT DELETE — HOLD (Charlie review)",IF($Q38="KEEP","DO NOT DELETE — KEEP",IF(ISNUMBER(SEARCH("REVIEW",$Q38)),"DO NOT DELETE — REVIEW pending",$S38)))) -> CONFIRMED: NO MODS > 1YR | Q38: {=_xlfn.IFS(AND($A38="thg-beauty",ISNUMBER(SEARCH("liveramp",$C38))),"DELETE",$A38="agile-bonbon-662",_xlfn.IFS(LEFT($G38,9)="Tranche 1","DELETE",$C38="Sessions_Level_1_All_Sites","KEEP",ISNUMBER(--$C38),"REVIEW — UA raw logs",$C38="Emag_Reporting","KEEP",$C38="Nutrition_Data_Archived_Tables","KEEP",$C38="EU_Data","KEEP",TRUE,"REVIEW"),OR($A38="thg-influencer",$A38="thg-ingenuity",$A38="thg-central-marketing",$A38="thg-seoclarity"),"HOLD",TRUE,"")} | R38: {=_xlfn.IFS(AND($A38="thg-beauty",ISNUMBER(SEARCH("liveramp",$C38))),"thg-beauty Liveramp dataset — confirmed safe to delete",$A38="agile-bonbon-662",_xlfn.IFS(LEFT($G38,9)="Tranche 1","Tranche 1: cleared",$C38="Sessions_Level_1_All_Sites","Downstream aggregation of UA raw logs — keep if raw tables go",ISNUMBER(--$C38),"UA raw site logs (account ID) — keep pending audit-retention check",$C38="Emag_Reporting","Legacy but likely needed",$C38="Nutrition_Data_Archived_Tables","Worth keeping",$C38="EU_Data","Static lookup tables — scripts still reference (smoke-test risk)",TRUE,"Review"),OR($A38="thg-influencer",$A38="thg-ingenuity",$A38="thg-central-marketing",$A38="thg-seoclarity"),"HOLD — Charlie Stringer to review before deletion",TRUE,"")} | S38: CONFIRMED: NO MODS > 1YR
A39: thg-ingenuity | B39: eu | C39: CustomerInsights_Deepdive_Segmentation | D39: No Description | E39: 4.76 | F39: 0.1 | G39: Active | H39: Low | I39: 116 | J39: 116 | K39: 46081.042 | L39: 46081.042 | M39: 2026-02-28 01:00 (aikenc@thehutgroup.com) 2026-02-28 01:00 (aikenc@thehutgroup.com) 2026-02-27 23:10 (aikenc@thehutgroup.com) 2026-02-27 01:00 (aikenc@thehutgroup.com) 2026-02-27 01:00 (aikenc@thehutgroup.com) | N39: 2026-02-28 01:00 (aikenc@thehutgroup.com) 2026-02-27 23:10 (aikenc@thehutgroup.com) 2026-02-27 23:00 (aikenc@thehutgroup.com) 2026-02-27 01:00 (aikenc@thehutgroup.com) 2026-02-26 23:10 (aikenc@thehutgroup.com) | O39: 46081.042 | P39: =IF($Q39="DELETE",IF($S39="CONFIRMED: NO MODS > 1YR","CONFIRMED: NO MODS > 1YR","DO NOT DELETE — not defensibly confirmed"),IF($Q39="HOLD","DO NOT DELETE — HOLD (Charlie review)",IF($Q39="KEEP","DO NOT DELETE — KEEP",IF(ISNUMBER(SEARCH("REVIEW",$Q39)),"DO NOT DELETE — REVIEW pending",$S39)))) -> DO NOT DELETE — HOLD (Charlie review) | Q39: {=_xlfn.IFS(AND($A39="thg-beauty",ISNUMBER(SEARCH("liveramp",$C39))),"DELETE",$A39="agile-bonbon-662",_xlfn.IFS(LEFT($G39,9)="Tranche 1","DELETE",$C39="Sessions_Level_1_All_Sites","KEEP",ISNUMBER(--$C39),"REVIEW — UA raw logs",$C39="Emag_Reporting","KEEP",$C39="Nutrition_Data_Archived_Tables","KEEP",$C39="EU_Data","KEEP",TRUE,"REVIEW"),OR($A39="thg-influencer",$A39="thg-ingenuity",$A39="thg-central-marketing",$A39="thg-seoclarity"),"HOLD",TRUE,"")} -> HOLD | R39: {=_xlfn.IFS(AND($A39="thg-beauty",ISNUMBER(SEARCH("liveramp",$C39))),"thg-beauty Liveramp dataset — confirmed safe to delete",$A39="agile-bonbon-662",_xlfn.IFS(LEFT($G39,9)="Tranche 1","Tranche 1: cleared",$C39="Sessions_Level_1_All_Sites","Downstream aggregation of UA raw logs — keep if raw tables go",ISNUMBER(--$C39),"UA raw site logs (account ID) — keep pending audit-retention check",$C39="Emag_Reporting","Legacy but likely needed",$C39="Nutrition_Data_Archived_Tables","Worth keeping",$C39="EU_Data","Static lookup tables — scripts still reference (smoke-test risk)",TRUE,"Review"),OR($A39="thg-influencer",$A39="thg-ingenuity",$A39="thg-central-marketing",$A39="thg-seoclarity"),"HOLD — Charlie Stringer to review before deletion",TRUE,"")} -> HOLD — Charlie Stringer to review before deletion | S39: CONFIRMED: NO MODS > 1YR
A40: thg-ingenuity | B40: eu | C40: 01_Fidelia | D40: No Description | E40: 0.02 | F40: 0 | G40: Active | H40: Low | I40: 116 | J40: 116 | L40: 46080.615 | M40: No Read Access (180d) | N40: 2026-02-27 14:46 (GunawanF@thehutgroup.com) 2026-02-27 05:00 (GunawanF@thehutgroup.com) 2026-02-26 14:46 (GunawanF@thehutgroup.com) 2026-02-26 05:00 (GunawanF@thehutgroup.com) 2026-02-25 14:46 (GunawanF@thehutgroup.com) | O40: 46080.616 | P40: =IF($Q40="DELETE",IF($S40="CONFIRMED: NO MODS > 1YR","CONFIRMED: NO MODS > 1YR","DO NOT DELETE — not defensibly confirmed"),IF($Q40="HOLD","DO NOT DELETE — HOLD (Charlie review)",IF($Q40="KEEP","DO NOT DELETE — KEEP",IF(ISNUMBER(SEARCH("REVIEW",$Q40)),"DO NOT DELETE — REVIEW pending",$S40)))) -> DO NOT DELETE — HOLD (Charlie review) | Q40: {=_xlfn.IFS(AND($A40="thg-beauty",ISNUMBER(SEARCH("liveramp",$C40))),"DELETE",$A40="agile-bonbon-662",_xlfn.IFS(LEFT($G40,9)="Tranche 1","DELETE",$C40="Sessions_Level_1_All_Sites","KEEP",ISNUMBER(--$C40),"REVIEW — UA raw logs",$C40="Emag_Reporting","KEEP",$C40="Nutrition_Data_Archived_Tables","KEEP",$C40="EU_Data","KEEP",TRUE,"REVIEW"),OR($A40="thg-influencer",$A40="thg-ingenuity",$A40="thg-central-marketing",$A40="thg-seoclarity"),"HOLD",TRUE,"")} -> HOLD | R40: {=_xlfn.IFS(AND($A40="thg-beauty",ISNUMBER(SEARCH("liveramp",$C40))),"thg-beauty Liveramp dataset — confirmed safe to delete",$A40="agile-bonbon-662",_xlfn.IFS(LEFT($G40,9)="Tranche 1","Tranche 1: cleared",$C40="Sessions_Level_1_All_Sites","Downstream aggregation of UA raw logs — keep if raw tables go",ISNUMBER(--$C40),"UA raw site logs (account ID) — keep pending audit-retention check",$C40="Emag_Reporting","Legacy but likely needed",$C40="Nutrition_Data_Archived_Tables","Worth keeping",$C40="EU_Data","Static lookup tables — scripts still reference (smoke-test risk)",TRUE,"Review"),OR($A40="thg-influencer",$A40="thg-ingenuity",$A40="thg-central-marketing",$A40="thg-seoclarity"),"HOLD — Charlie Stringer to review before deletion",TRUE,"")} -> HOLD — Charlie Stringer to review before deletion | S40: CONFIRMED: NO MODS > 1YR
A41: thg-machine-learning-fraud | B41: europe-west2 | C41: refunds__permanent | D41: No Description | E41: 81.97 | F41: 1.64 | G41: Active | H41: Low | I41: 114 | J41: 308 | K41: 46083.414 | M41: 2026-03-02 09:56 (ChunYen.Tay15@thehutgroup.com) 2026-03-02 09:55 (ChunYen.Tay15@thehutgroup.com) 2026-03-02 09:55 (ChunYen.Tay15@thehutgroup.com) 2026-03-02 09:55 (ChunYen.Tay15@thehutgroup.com) 2026-03-02 09:53 (ChunYen.Tay15@thehutgroup.com) | N41: No Write Access (180d) | O41: 45889.05 | P41: =IF($Q41="DELETE",IF($S41="CONFIRMED: NO MODS > 1YR","CONFIRMED: NO MODS > 1YR","DO NOT DELETE — not defensibly confirmed"),IF($Q41="HOLD","DO NOT DELETE — HOLD (Charlie review)",IF($Q41="KEEP","DO NOT DELETE — KEEP",IF(ISNUMBER(SEARCH("REVIEW",$Q41)),"DO NOT DELETE — REVIEW pending",$S41)))) -> CONFIRMED: NO MODS > 1YR | Q41: {=_xlfn.IFS(AND($A41="thg-beauty",ISNUMBER(SEARCH("liveramp",$C41))),"DELETE",$A41="agile-bonbon-662",_xlfn.IFS(LEFT($G41,9)="Tranche 1","DELETE",$C41="Sessions_Level_1_All_Sites","KEEP",ISNUMBER(--$C41),"REVIEW — UA raw logs",$C41="Emag_Reporting","KEEP",$C41="Nutrition_Data_Archived_Tables","KEEP",$C41="EU_Data","KEEP",TRUE,"REVIEW"),OR($A41="thg-influencer",$A41="thg-ingenuity",$A41="thg-central-marketing",$A41="thg-seoclarity"),"HOLD",TRUE,"")} | R41: {=_xlfn.IFS(AND($A41="thg-beauty",ISNUMBER(SEARCH("liveramp",$C41))),"thg-beauty Liveramp dataset — confirmed safe to delete",$A41="agile-bonbon-662",_xlfn.IFS(LEFT($G41,9)="Tranche 1","Tranche 1: cleared",$C41="Sessions_Level_1_All_Sites","Downstream aggregation of UA raw logs — keep if raw tables go",ISNUMBER(--$C41),"UA raw site logs (account ID) — keep pending audit-retention check",$C41="Emag_Reporting","Legacy but likely needed",$C41="Nutrition_Data_Archived_Tables","Worth keeping",$C41="EU_Data","Static lookup tables — scripts still reference (smoke-test risk)",TRUE,"Review"),OR($A41="thg-influencer",$A41="thg-ingenuity",$A41="thg-central-marketing",$A41="thg-seoclarity"),"HOLD — Charlie Stringer to review before deletion",TRUE,"")} | S41: CONFIRMED: NO MODS > 1YR
A42: thg-ingenuity | B42: eu | C42: analytics_315280056 | D42: No Description | E42: 1.96 | F42: 0.04 | G42: Active | H42: Low | I42: 111 | J42: 111 | K42: 46086.419 | L42: 46086.363 | M42: 2026-03-05 10:03 (ga4-sessions-level-1-ingenuity@thg-ingenuity.iam.gserviceaccount.com) 2026-03-04 10:03 (ga4-sessions-level-1-ingenuity@thg-ingenuity.iam.gserviceaccount.com) 2026-03-03 10:03 (ga4-sessions-level-1-ingenuity@thg-ingenuity.iam.gserviceaccount.com) 2026-03-02 10:03 (ga4-sessions-level-1-ingenuity@thg-ingenuity.iam.gserviceaccount.com) 2026-03-01 08:03 (ga4-sessions-level-1-ingenuity@thg-ingenuity.iam.gserviceaccount.com) | N42: 2026-03-05 08:43 (firebase-measurement@system.gserviceaccount.com) 2026-03-04 08:11 (firebase-measurement@system.gserviceaccount.com) 2026-03-03 09:12 (firebase-measurement@system.gserviceaccount.com) 2026-03-02 08:24 (firebase-measurement@system.gserviceaccount.com) 2026-03-01 07:53 (firebase-measurement@system.gserviceaccount.com) | O42: 46086.363 | P42: =IF($Q42="DELETE",IF($S42="CONFIRMED: NO MODS > 1YR","CONFIRMED: NO MODS > 1YR","DO NOT DELETE — not defensibly confirmed"),IF($Q42="HOLD","DO NOT DELETE — HOLD (Charlie review)",IF($Q42="KEEP","DO NOT DELETE — KEEP",IF(ISNUMBER(SEARCH("REVIEW",$Q42)),"DO NOT DELETE — REVIEW pending",$S42)))) -> DO NOT DELETE — HOLD (Charlie review) | Q42: {=_xlfn.IFS(AND($A42="thg-beauty",ISNUMBER(SEARCH("liveramp",$C42))),"DELETE",$A42="agile-bonbon-662",_xlfn.IFS(LEFT($G42,9)="Tranche 1","DELETE",$C42="Sessions_Level_1_All_Sites","KEEP",ISNUMBER(--$C42),"REVIEW — UA raw logs",$C42="Emag_Reporting","KEEP",$C42="Nutrition_Data_Archived_Tables","KEEP",$C42="EU_Data","KEEP",TRUE,"REVIEW"),OR($A42="thg-influencer",$A42="thg-ingenuity",$A42="thg-central-marketing",$A42="thg-seoclarity"),"HOLD",TRUE,"")} -> HOLD | R42: {=_xlfn.IFS(AND($A42="thg-beauty",ISNUMBER(SEARCH("liveramp",$C42))),"thg-beauty Liveramp dataset — confirmed safe to delete",$A42="agile-bonbon-662",_xlfn.IFS(LEFT($G42,9)="Tranche 1","Tranche 1: cleared",$C42="Sessions_Level_1_All_Sites","Downstream aggregation of UA raw logs — keep if raw tables go",ISNUMBER(--$C42),"UA raw site logs (account ID) — keep pending audit-retention check",$C42="Emag_Reporting","Legacy but likely needed",$C42="Nutrition_Data_Archived_Tables","Worth keeping",$C42="EU_Data","Static lookup tables — scripts still reference (smoke-test risk)",TRUE,"Review"),OR($A42="thg-influencer",$A42="thg-ingenuity",$A42="thg-central-marketing",$A42="thg-seoclarity"),"HOLD — Charlie Stringer to review before deletion",TRUE,"")} -> HOLD — Charlie Stringer to review before deletion | S42: CONFIRMED: NO MODS > 1YR
A43: thg-ingenuity | B43: eu | C43: analytics_422302097 | D43: No Description | E43: 5.33 | F43: 0.11 | G43: Active | H43: Low | I43: 110 | J43: 110 | L43: 46087.336 | M43: No Read Access (180d) | N43: 2026-03-06 08:04 (firebase-measurement@system.gserviceaccount.com) 2026-03-05 08:00 (firebase-measurement@system.gserviceaccount.com) 2026-03-04 09:10 (firebase-measurement@system.gserviceaccount.com) 2026-03-03 08:43 (firebase-measurement@system.gserviceaccount.com) 2026-03-02 11:59 (firebase-measurement@system.gserviceaccount.com) | O43: 46087.337 | P43: =IF($Q43="DELETE",IF($S43="CONFIRMED: NO MODS > 1YR","CONFIRMED: NO MODS > 1YR","DO NOT DELETE — not defensibly confirmed"),IF($Q43="HOLD","DO NOT DELETE — HOLD (Charlie review)",IF($Q43="KEEP","DO NOT DELETE — KEEP",IF(ISNUMBER(SEARCH("REVIEW",$Q43)),"DO NOT DELETE — REVIEW pending",$S43)))) -> DO NOT DELETE — HOLD (Charlie review) | Q43: {=_xlfn.IFS(AND($A43="thg-beauty",ISNUMBER(SEARCH("liveramp",$C43))),"DELETE",$A43="agile-bonbon-662",_xlfn.IFS(LEFT($G43,9)="Tranche 1","DELETE",$C43="Sessions_Level_1_All_Sites","KEEP",ISNUMBER(--$C43),"REVIEW — UA raw logs",$C43="Emag_Reporting","KEEP",$C43="Nutrition_Data_Archived_Tables","KEEP",$C43="EU_Data","KEEP",TRUE,"REVIEW"),OR($A43="thg-influencer",$A43="thg-ingenuity",$A43="thg-central-marketing",$A43="thg-seoclarity"),"HOLD",TRUE,"")} -> HOLD | R43: {=_xlfn.IFS(AND($A43="thg-beauty",ISNUMBER(SEARCH("liveramp",$C43))),"thg-beauty Liveramp dataset — confirmed safe to delete",$A43="agile-bonbon-662",_xlfn.IFS(LEFT($G43,9)="Tranche 1","Tranche 1: cleared",$C43="Sessions_Level_1_All_Sites","Downstream aggregation of UA raw logs — keep if raw tables go",ISNUMBER(--$C43),"UA raw site logs (account ID) — keep pending audit-retention check",$C43="Emag_Reporting","Legacy but likely needed",$C43="Nutrition_Data_Archived_Tables","Worth keeping",$C43="EU_Data","Static lookup tables — scripts still reference (smoke-test risk)",TRUE,"Review"),OR($A43="thg-influencer",$A43="thg-ingenuity",$A43="thg-central-marketing",$A43="thg-seoclarity"),"HOLD — Charlie Stringer to review before deletion",TRUE,"")} -> HOLD — Charlie Stringer to review before deletion | S43: CONFIRMED: NO MODS > 1YR
A44: thg-beauty | B44: eu | C44: Brands_Category | D44: No Description | E44: 98.55 | F44: 1.97 | G44: Active | H44: Low | I44: 0 | J44: 0 | K44: 46197.449 | L44: 46197.121 | M44: 2026-06-24 10:46 (chanv@thehutgroup.com) 2026-06-24 10:46 (chanv@thehutgroup.com) 2026-06-24 10:44 (chanv@thehutgroup.com) 2026-06-24 10:44 (chanv@thehutgroup.com) 2026-06-24 10:27 (sa-bpswcbdsql01@thg-beauty.iam.gserviceaccount.com) | N44: 2026-06-24 02:53 (sa-bpswcbdsql01@thg-beauty.iam.gserviceaccount.com) 2026-06-24 02:53 (sa-bpswcbdsql01@thg-beauty.iam.gserviceaccount.com) 2026-06-24 02:53 (sa-bpswcbdsql01@thg-beauty.iam.gserviceaccount.com) 2026-06-24 02:53 (sa-bpswcbdsql01@thg-beauty.iam.gserviceaccount.com) 2026-06-24 02:53 (sa-bpswcbdsql01@thg-beauty.iam.gserviceaccount.com) | O44: 46197.125 | P44: =IF($Q44="DELETE",IF($S44="CONFIRMED: NO MODS > 1YR","CONFIRMED: NO MODS > 1YR","DO NOT DELETE — not defensibly confirmed"),IF($Q44="HOLD","DO NOT DELETE — HOLD (Charlie review)",IF($Q44="KEEP","DO NOT DELETE — KEEP",IF(ISNUMBER(SEARCH("REVIEW",$Q44)),"DO NOT DELETE — REVIEW pending",$S44)))) -> CONFIRMED: NO MODS > 1YR | Q44: {=_xlfn.IFS(AND($A44="thg-beauty",ISNUMBER(SEARCH("liveramp",$C44))),"DELETE",$A44="agile-bonbon-662",_xlfn.IFS(LEFT($G44,9)="Tranche 1","DELETE",$C44="Sessions_Level_1_All_Sites","KEEP",ISNUMBER(--$C44),"REVIEW — UA raw logs",$C44="Emag_Reporting","KEEP",$C44="Nutrition_Data_Archived_Tables","KEEP",$C44="EU_Data","KEEP",TRUE,"REVIEW"),OR($A44="thg-influencer",$A44="thg-ingenuity",$A44="thg-central-marketing",$A44="thg-seoclarity"),"HOLD",TRUE,"")} | R44: {=_xlfn.IFS(AND($A44="thg-beauty",ISNUMBER(SEARCH("liveramp",$C44))),"thg-beauty Liveramp dataset — confirmed safe to delete",$A44="agile-bonbon-662",_xlfn.IFS(LEFT($G44,9)="Tranche 1","Tranche 1: cleared",$C44="Sessions_Level_1_All_Sites","Downstream aggregation of UA raw logs — keep if raw tables go",ISNUMBER(--$C44),"UA raw site logs (account ID) — keep pending audit-retention check",$C44="Emag_Reporting","Legacy but likely needed",$C44="Nutrition_Data_Archived_Tables","Worth keeping",$C44="EU_Data","Static lookup tables — scripts still reference (smoke-test risk)",TRUE,"Review"),OR($A44="thg-influencer",$A44="thg-ingenuity",$A44="thg-central-marketing",$A44="thg-seoclarity"),"HOLD — Charlie Stringer to review before deletion",TRUE,"")} | S44: CONFIRMED: NO MODS > 1YR
A45: thg-finops-nonprod | B45: europe-west2 | C45: finops_data | D45: Terraform managed. | E45: 0 | F45: 0 | G45: Active | H45: Low | I45: 98 | J45: 98 | K45: 46077.416 | L45: 46073.757 | M45: 2026-02-24 09:58 (alan.dodd82@thgingenuity.com) 2026-02-24 09:32 (alan.dodd82@thgingenuity.com) 2026-02-24 08:56 (alan.dodd82@thgingenuity.com) 2026-02-20 18:07 (alan.dodd82@thgingenuity.com) 2026-02-20 18:07 (alan.dodd82@thgingenuity.com) | N45: 2026-02-20 18:09 (alan.dodd82@thgingenuity.com) 2026-02-20 18:09 (alan.dodd82@thgingenuity.com) 2026-02-20 18:09 (alan.dodd82@thgingenuity.com) 2026-02-20 18:08 (alan.dodd82@thgingenuity.com) 2026-02-20 18:08 (alan.dodd82@thgingenuity.com) | O45: 46098.633 | P45: =IF($Q45="DELETE",IF($S45="CONFIRMED: NO MODS > 1YR","CONFIRMED: NO MODS > 1YR","DO NOT DELETE — not defensibly confirmed"),IF($Q45="HOLD","DO NOT DELETE — HOLD (Charlie review)",IF($Q45="KEEP","DO NOT DELETE — KEEP",IF(ISNUMBER(SEARCH("REVIEW",$Q45)),"DO NOT DELETE — REVIEW pending",$S45)))) -> CONFIRMED: NO MODS > 1YR | Q45: {=_xlfn.IFS(AND($A45="thg-beauty",ISNUMBER(SEARCH("liveramp",$C45))),"DELETE",$A45="agile-bonbon-662",_xlfn.IFS(LEFT($G45,9)="Tranche 1","DELETE",$C45="Sessions_Level_1_All_Sites","KEEP",ISNUMBER(--$C45),"REVIEW — UA raw logs",$C45="Emag_Reporting","KEEP",$C45="Nutrition_Data_Archived_Tables","KEEP",$C45="EU_Data","KEEP",TRUE,"REVIEW"),OR($A45="thg-influencer",$A45="thg-ingenuity",$A45="thg-central-marketing",$A45="thg-seoclarity"),"HOLD",TRUE,"")} | R45: {=_xlfn.IFS(AND($A45="thg-beauty",ISNUMBER(SEARCH("liveramp",$C45))),"thg-beauty Liveramp dataset — confirmed safe to delete",$A45="agile-bonbon-662",_xlfn.IFS(LEFT($G45,9)="Tranche 1","Tranche 1: cleared",$C45="Sessions_Level_1_All_Sites","Downstream aggregation of UA raw logs — keep if raw tables go",ISNUMBER(--$C45),"UA raw site logs (account ID) — keep pending audit-retention check",$C45="Emag_Reporting","Legacy but likely needed",$C45="Nutrition_Data_Archived_Tables","Worth keeping",$C45="EU_Data","Static lookup tables — scripts still reference (smoke-test risk)",TRUE,"Review"),OR($A45="thg-influencer",$A45="thg-ingenuity",$A45="thg-central-marketing",$A45="thg-seoclarity"),"HOLD — Charlie Stringer to review before deletion",TRUE,"")} | S45: CONFIRMED: NO MODS > 1YR
A46: thg-ml-dev | B46: eu | C46: parcel_id | D46: No Description | E46: 0 | F46: 0 | G46: Active | H46: Low | I46: 93 | J46: 148 | K46: 46104.384 | M46: 2026-03-23 09:13 (hicksc@thehutgroup.com) 2026-03-20 14:39 (hicksc@thehutgroup.com) 2026-03-20 14:38 (hicksc@thehutgroup.com) 2026-01-27 11:01 (hicksc@thehutgroup.com) 2026-01-27 11:01 (hicksc@thehutgroup.com) | N46: No Write Access (180d) | O46: 46049.431 | P46: =IF($Q46="DELETE",IF($S46="CONFIRMED: NO MODS > 1YR","CONFIRMED: NO MODS > 1YR","DO NOT DELETE — not defensibly confirmed"),IF($Q46="HOLD","DO NOT DELETE — HOLD (Charlie review)",IF($Q46="KEEP","DO NOT DELETE — KEEP",IF(ISNUMBER(SEARCH("REVIEW",$Q46)),"DO NOT DELETE — REVIEW pending",$S46)))) -> CONFIRMED: NO MODS > 1YR | Q46: {=_xlfn.IFS(AND($A46="thg-beauty",ISNUMBER(SEARCH("liveramp",$C46))),"DELETE",$A46="agile-bonbon-662",_xlfn.IFS(LEFT($G46,9)="Tranche 1","DELETE",$C46="Sessions_Level_1_All_Sites","KEEP",ISNUMBER(--$C46),"REVIEW — UA raw logs",$C46="Emag_Reporting","KEEP",$C46="Nutrition_Data_Archived_Tables","KEEP",$C46="EU_Data","KEEP",TRUE,"REVIEW"),OR($A46="thg-influencer",$A46="thg-ingenuity",$A46="thg-central-marketing",$A46="thg-seoclarity"),"HOLD",TRUE,"")} | R46: {=_xlfn.IFS(AND($A46="thg-beauty",ISNUMBER(SEARCH("liveramp",$C46))),"thg-beauty Liveramp dataset — confirmed safe to delete",$A46="agile-bonbon-662",_xlfn.IFS(LEFT($G46,9)="Tranche 1","Tranche 1: cleared",$C46="Sessions_Level_1_All_Sites","Downstream aggregation of UA raw logs — keep if raw tables go",ISNUMBER(--$C46),"UA raw site logs (account ID) — keep pending audit-retention check",$C46="Emag_Reporting","Legacy but likely needed",$C46="Nutrition_Data_Archived_Tables","Worth keeping",$C46="EU_Data","Static lookup tables — scripts still reference (smoke-test risk)",TRUE,"Review"),OR($A46="thg-influencer",$A46="thg-ingenuity",$A46="thg-central-marketing",$A46="thg-seoclarity"),"HOLD — Charlie Stringer to review before deletion",TRUE,"")} | S46: CONFIRMED: NO MODS > 1YR
A47: thg-ingenuity | B47: eu | C47: analytics_315289139 | D47: No Description | E47: 9.89 | F47: 0.2 | G47: Active | H47: Low | I47: 90 | J47: 90 | K47: 46107.335 | L47: 46107.324 | M47: 2026-03-26 08:02 (ga4-sessions-level-1-ingenuity@thg-ingenuity.iam.gserviceaccount.com) 2026-03-25 08:02 (ga4-sessions-level-1-ingenuity@thg-ingenuity.iam.gserviceaccount.com) 2026-03-18 08:02 (ga4-sessions-level-1-ingenuity@thg-ingenuity.iam.gserviceaccount.com) 2026-03-12 08:02 (ga4-sessions-level-1-ingenuity@thg-ingenuity.iam.gserviceaccount.com) 2026-03-10 10:03 (ga4-sessions-level-1-ingenuity@thg-ingenuity.iam.gserviceaccount.com) | N47: 2026-03-26 07:47 (firebase-measurement@system.gserviceaccount.com) 2026-03-25 07:52 (firebase-measurement@system.gserviceaccount.com) 2026-03-18 07:50 (firebase-measurement@system.gserviceaccount.com) 2026-03-12 07:28 (firebase-measurement@system.gserviceaccount.com) 2026-03-10 08:02 (firebase-measurement@system.gserviceaccount.com) | O47: 46107.325 | P47: =IF($Q47="DELETE",IF($S47="CONFIRMED: NO MODS > 1YR","CONFIRMED: NO MODS > 1YR","DO NOT DELETE — not defensibly confirmed"),IF($Q47="HOLD","DO NOT DELETE — HOLD (Charlie review)",IF($Q47="KEEP","DO NOT DELETE — KEEP",IF(ISNUMBER(SEARCH("REVIEW",$Q47)),"DO NOT DELETE — REVIEW pending",$S47)))) -> DO NOT DELETE — HOLD (Charlie review) | Q47: {=_xlfn.IFS(AND($A47="thg-beauty",ISNUMBER(SEARCH("liveramp",$C47))),"DELETE",$A47="agile-bonbon-662",_xlfn.IFS(LEFT($G47,9)="Tranche 1","DELETE",$C47="Sessions_Level_1_All_Sites","KEEP",ISNUMBER(--$C47),"REVIEW — UA raw logs",$C47="Emag_Reporting","KEEP",$C47="Nutrition_Data_Archived_Tables","KEEP",$C47="EU_Data","KEEP",TRUE,"REVIEW"),OR($A47="thg-influencer",$A47="thg-ingenuity",$A47="thg-central-marketing",$A47="thg-seoclarity"),"HOLD",TRUE,"")} -> HOLD | R47: {=_xlfn.IFS(AND($A47="thg-beauty",ISNUMBER(SEARCH("liveramp",$C47))),"thg-beauty Liveramp dataset — confirmed safe to delete",$A47="agile-bonbon-662",_xlfn.IFS(LEFT($G47,9)="Tranche 1","Tranche 1: cleared",$C47="Sessions_Level_1_All_Sites","Downstream aggregation of UA raw logs — keep if raw tables go",ISNUMBER(--$C47),"UA raw site logs (account ID) — keep pending audit-retention check",$C47="Emag_Reporting","Legacy but likely needed",$C47="Nutrition_Data_Archived_Tables","Worth keeping",$C47="EU_Data","Static lookup tables — scripts still reference (smoke-test risk)",TRUE,"Review"),OR($A47="thg-influencer",$A47="thg-ingenuity",$A47="thg-central-marketing",$A47="thg-seoclarity"),"HOLD — Charlie Stringer to review before deletion",TRUE,"")} -> HOLD — Charlie Stringer to review before deletion | S47: CONFIRMED: NO MODS > 1YR
A48: thg-ingenuity | B48: eu | C48: analytics_315279218 | D48: No Description | E48: 14.74 | F48: 0.29 | G48: Active | H48: Low | I48: 87 | J48: 87 | K48: 46110.335 | L48: 46110.323 | M48: 2026-03-29 08:02 (ga4-sessions-level-1-ingenuity@thg-ingenuity.iam.gserviceaccount.com) 2026-03-25 10:03 (ga4-sessions-level-1-ingenuity@thg-ingenuity.iam.gserviceaccount.com) 2026-03-23 10:03 (ga4-sessions-level-1-ingenuity@thg-ingenuity.iam.gserviceaccount.com) 2026-03-17 10:03 (ga4-sessions-level-1-ingenuity@thg-ingenuity.iam.gserviceaccount.com) 2026-03-15 10:03 (ga4-sessions-level-1-ingenuity@thg-ingenuity.iam.gserviceaccount.com) | N48: 2026-03-29 07:44 (firebase-measurement@system.gserviceaccount.com) 2026-03-25 08:34 (firebase-measurement@system.gserviceaccount.com) 2026-03-23 08:21 (firebase-measurement@system.gserviceaccount.com) 2026-03-17 09:21 (firebase-measurement@system.gserviceaccount.com) 2026-03-15 08:07 (firebase-measurement@system.gserviceaccount.com) | O48: 46110.324 | P48: =IF($Q48="DELETE",IF($S48="CONFIRMED: NO MODS > 1YR","CONFIRMED: NO MODS > 1YR","DO NOT DELETE — not defensibly confirmed"),IF($Q48="HOLD","DO NOT DELETE — HOLD (Charlie review)",IF($Q48="KEEP","DO NOT DELETE — KEEP",IF(ISNUMBER(SEARCH("REVIEW",$Q48)),"DO NOT DELETE — REVIEW pending",$S48)))) -> DO NOT DELETE — HOLD (Charlie review) | Q48: {=_xlfn.IFS(AND($A48="thg-beauty",ISNUMBER(SEARCH("liveramp",$C48))),"DELETE",$A48="agile-bonbon-662",_xlfn.IFS(LEFT($G48,9)="Tranche 1","DELETE",$C48="Sessions_Level_1_All_Sites","KEEP",ISNUMBER(--$C48),"REVIEW — UA raw logs",$C48="Emag_Reporting","KEEP",$C48="Nutrition_Data_Archived_Tables","KEEP",$C48="EU_Data","KEEP",TRUE,"REVIEW"),OR($A48="thg-influencer",$A48="thg-ingenuity",$A48="thg-central-marketing",$A48="thg-seoclarity"),"HOLD",TRUE,"")} -> HOLD | R48: {=_xlfn.IFS(AND($A48="thg-beauty",ISNUMBER(SEARCH("liveramp",$C48))),"thg-beauty Liveramp dataset — confirmed safe to delete",$A48="agile-bonbon-662",_xlfn.IFS(LEFT($G48,9)="Tranche 1","Tranche 1: cleared",$C48="Sessions_Level_1_All_Sites","Downstream aggregation of UA raw logs — keep if raw tables go",ISNUMBER(--$C48),"UA raw site logs (account ID) — keep pending audit-retention check",$C48="Emag_Reporting","Legacy but likely needed",$C48="Nutrition_Data_Archived_Tables","Worth keeping",$C48="EU_Data","Static lookup tables — scripts still reference (smoke-test risk)",TRUE,"Review"),OR($A48="thg-influencer",$A48="thg-ingenuity",$A48="thg-central-marketing",$A48="thg-seoclarity"),"HOLD — Charlie Stringer to review before deletion",TRUE,"")} -> HOLD — Charlie Stringer to review before deletion | S48: CONFIRMED: NO MODS > 1YR
A49: thg-beauty | B49: eu | C49: NC_Metrics | D49: No Description | E49: 80.65 | F49: 1.61 | G49: Active | H49: Low | I49: 0 | J49: 0 | K49: 46197.296 | L49: 46197.115 | M49: 2026-06-24 07:06 (beauty-data@agile-bonbon-662.iam.gserviceaccount.com) 2026-06-24 07:04 (beauty-data@agile-bonbon-662.iam.gserviceaccount.com) 2026-06-24 02:46 (sa-bpswcbdsql01@thg-beauty.iam.gserviceaccount.com) 2026-06-24 02:43 (sa-bpswcbdsql01@thg-beauty.iam.gserviceaccount.com) 2026-06-24 02:43 (sa-bpswcbdsql01@thg-beauty.iam.gserviceaccount.com) | N49: 2026-06-24 02:46 (sa-bpswcbdsql01@thg-beauty.iam.gserviceaccount.com) 2026-06-24 02:43 (sa-bpswcbdsql01@thg-beauty.iam.gserviceaccount.com) 2026-06-24 02:43 (sa-bpswcbdsql01@thg-beauty.iam.gserviceaccount.com) 2026-06-24 02:32 (sa-bpswcbdsql01@thg-beauty.iam.gserviceaccount.com) 2026-06-24 02:29 (sa-bpswcbdsql01@thg-beauty.iam.gserviceaccount.com) | O49: 46197.115 | P49: =IF($Q49="DELETE",IF($S49="CONFIRMED: NO MODS > 1YR","CONFIRMED: NO MODS > 1YR","DO NOT DELETE — not defensibly confirmed"),IF($Q49="HOLD","DO NOT DELETE — HOLD (Charlie review)",IF($Q49="KEEP","DO NOT DELETE — KEEP",IF(ISNUMBER(SEARCH("REVIEW",$Q49)),"DO NOT DELETE — REVIEW pending",$S49)))) -> CONFIRMED: NO MODS > 1YR | Q49: {=_xlfn.IFS(AND($A49="thg-beauty",ISNUMBER(SEARCH("liveramp",$C49))),"DELETE",$A49="agile-bonbon-662",_xlfn.IFS(LEFT($G49,9)="Tranche 1","DELETE",$C49="Sessions_Level_1_All_Sites","KEEP",ISNUMBER(--$C49),"REVIEW — UA raw logs",$C49="Emag_Reporting","KEEP",$C49="Nutrition_Data_Archived_Tables","KEEP",$C49="EU_Data","KEEP",TRUE,"REVIEW"),OR($A49="thg-influencer",$A49="thg-ingenuity",$A49="thg-central-marketing",$A49="thg-seoclarity"),"HOLD",TRUE,"")} | R49: {=_xlfn.IFS(AND($A49="thg-beauty",ISNUMBER(SEARCH("liveramp",$C49))),"thg-beauty Liveramp dataset — confirmed safe to delete",$A49="agile-bonbon-662",_xlfn.IFS(LEFT($G49,9)="Tranche 1","Tranche 1: cleared",$C49="Sessions_Level_1_All_Sites","Downstream aggregation of UA raw logs — keep if raw tables go",ISNUMBER(--$C49),"UA raw site logs (account ID) — keep pending audit-retention check",$C49="Emag_Reporting","Legacy but likely needed",$C49="Nutrition_Data_Archived_Tables","Worth keeping",$C49="EU_Data","Static lookup tables — scripts still reference (smoke-test risk)",TRUE,"Review"),OR($A49="thg-influencer",$A49="thg-ingenuity",$A49="thg-central-marketing",$A49="thg-seoclarity"),"HOLD — Charlie Stringer to review before deletion",TRUE,"")} | S49: CONFIRMED: NO MODS > 1YR
A50: thg-ingenuity | B50: eu | C50: analytics_330717871 | D50: No Description | E50: 56.48 | F50: 1.13 | G50: Active | H50: Low | I50: 82 | J50: 82 | K50: 46115.419 | L50: 46115.415 | M50: 2026-04-03 10:03 (ga4-sessions-level-1-ingenuity@thg-ingenuity.iam.gserviceaccount.com) | N50: 2026-04-03 09:57 (firebase-measurement@system.gserviceaccount.com) | O50: 46115.415 | P50: =IF($Q50="DELETE",IF($S50="CONFIRMED: NO MODS > 1YR","CONFIRMED: NO MODS > 1YR","DO NOT DELETE — not defensibly confirmed"),IF($Q50="HOLD","DO NOT DELETE — HOLD (Charlie review)",IF($Q50="KEEP","DO NOT DELETE — KEEP",IF(ISNUMBER(SEARCH("REVIEW",$Q50)),"DO NOT DELETE — REVIEW pending",$S50)))) -> DO NOT DELETE — HOLD (Charlie review) | Q50: {=_xlfn.IFS(AND($A50="thg-beauty",ISNUMBER(SEARCH("liveramp",$C50))),"DELETE",$A50="agile-bonbon-662",_xlfn.IFS(LEFT($G50,9)="Tranche 1","DELETE",$C50="Sessions_Level_1_All_Sites","KEEP",ISNUMBER(--$C50),"REVIEW — UA raw logs",$C50="Emag_Reporting","KEEP",$C50="Nutrition_Data_Archived_Tables","KEEP",$C50="EU_Data","KEEP",TRUE,"REVIEW"),OR($A50="thg-influencer",$A50="thg-ingenuity",$A50="thg-central-marketing",$A50="thg-seoclarity"),"HOLD",TRUE,"")} -> HOLD | R50: {=_xlfn.IFS(AND($A50="thg-beauty",ISNUMBER(SEARCH("liveramp",$C50))),"thg-beauty Liveramp dataset — confirmed safe to delete",$A50="agile-bonbon-662",_xlfn.IFS(LEFT($G50,9)="Tranche 1","Tranche 1: cleared",$C50="Sessions_Level_1_All_Sites","Downstream aggregation of UA raw logs — keep if raw tables go",ISNUMBER(--$C50),"UA raw site logs (account ID) — keep pending audit-retention check",$C50="Emag_Reporting","Legacy but likely needed",$C50="Nutrition_Data_Archived_Tables","Worth keeping",$C50="EU_Data","Static lookup tables — scripts still reference (smoke-test risk)",TRUE,"Review"),OR($A50="thg-influencer",$A50="thg-ingenuity",$A50="thg-central-marketing",$A50="thg-seoclarity"),"HOLD — Charlie Stringer to review before deletion",TRUE,"")} -> HOLD — Charlie Stringer to review before deletion | S50: CONFIRMED: NO MODS > 1YR
A51: thg-ml-dev | B51: eu | C51: autostore_simulator | D51: No Description | E51: 2.38 | F51: 0.05 | G51: Active | H51: Low | I51: 77 | J51: 77 | K51: 46043.248 | M51: 2026-01-21 05:56 (atharva.lipare32@thgingenuity.com) 2026-01-21 05:56 (atharva.lipare32@thgingenuity.com) 2026-01-21 05:56 (atharva.lipare32@thgingenuity.com) 2026-01-21 05:56 (atharva.lipare32@thgingenuity.com) 2026-01-21 05:56 (atharva.lipare32@thgingenuity.com) | N51: No Write Access (180d) | O51: 46120.384 | P51: =IF($Q51="DELETE",IF($S51="CONFIRMED: NO MODS > 1YR","CONFIRMED: NO MODS > 1YR","DO NOT DELETE — not defensibly confirmed"),IF($Q51="HOLD","DO NOT DELETE — HOLD (Charlie review)",IF($Q51="KEEP","DO NOT DELETE — KEEP",IF(ISNUMBER(SEARCH("REVIEW",$Q51)),"DO NOT DELETE — REVIEW pending",$S51)))) -> CONFIRMED: NO MODS > 1YR | Q51: {=_xlfn.IFS(AND($A51="thg-beauty",ISNUMBER(SEARCH("liveramp",$C51))),"DELETE",$A51="agile-bonbon-662",_xlfn.IFS(LEFT($G51,9)="Tranche 1","DELETE",$C51="Sessions_Level_1_All_Sites","KEEP",ISNUMBER(--$C51),"REVIEW — UA raw logs",$C51="Emag_Reporting","KEEP",$C51="Nutrition_Data_Archived_Tables","KEEP",$C51="EU_Data","KEEP",TRUE,"REVIEW"),OR($A51="thg-influencer",$A51="thg-ingenuity",$A51="thg-central-marketing",$A51="thg-seoclarity"),"HOLD",TRUE,"")} | R51: {=_xlfn.IFS(AND($A51="thg-beauty",ISNUMBER(SEARCH("liveramp",$C51))),"thg-beauty Liveramp dataset — confirmed safe to delete",$A51="agile-bonbon-662",_xlfn.IFS(LEFT($G51,9)="Tranche 1","Tranche 1: cleared",$C51="Sessions_Level_1_All_Sites","Downstream aggregation of UA raw logs — keep if raw tables go",ISNUMBER(--$C51),"UA raw site logs (account ID) — keep pending audit-retention check",$C51="Emag_Reporting","Legacy but likely needed",$C51="Nutrition_Data_Archived_Tables","Worth keeping",$C51="EU_Data","Static lookup tables — scripts still reference (smoke-test risk)",TRUE,"Review"),OR($A51="thg-influencer",$A51="thg-ingenuity",$A51="thg-central-marketing",$A51="thg-seoclarity"),"HOLD — Charlie Stringer to review before deletion",TRUE,"")} | S51: CONFIRMED: NO MODS > 1YR
A52: thg-ml-live | B52: eu | C52: product_gen__permanent | D52: No Description | E52: 0.02 | F52: 0 | G52: Active | H52: Low | I52: 68 | J52: 168 | K52: 46129.427 | L52: 46028.747 | M52: 2026-04-17 10:15 (marije.vanhattum74@thehutgroup.com) 2026-04-17 10:14 (marije.vanhattum74@thehutgroup.com) 2026-01-06 17:55 (product-gen@thg-ml-live.iam.gserviceaccount.com) 2026-01-06 17:55 (product-gen@thg-ml-live.iam.gserviceaccount.com) 2026-01-06 17:55 (product-gen@thg-ml-live.iam.gserviceaccount.com) | N52: 2026-01-06 17:55 (product-gen@thg-ml-live.iam.gserviceaccount.com) 2026-01-06 17:55 (product-gen@thg-ml-live.iam.gserviceaccount.com) 2026-01-06 17:55 (product-gen@thg-ml-live.iam.gserviceaccount.com) 2026-01-06 17:55 (product-gen@thg-ml-live.iam.gserviceaccount.com) 2026-01-06 17:53 (product-gen@thg-ml-live.iam.gserviceaccount.com) | O52: 46028.747 | P52: =IF($Q52="DELETE",IF($S52="CONFIRMED: NO MODS > 1YR","CONFIRMED: NO MODS > 1YR","DO NOT DELETE — not defensibly confirmed"),IF($Q52="HOLD","DO NOT DELETE — HOLD (Charlie review)",IF($Q52="KEEP","DO NOT DELETE — KEEP",IF(ISNUMBER(SEARCH("REVIEW",$Q52)),"DO NOT DELETE — REVIEW pending",$S52)))) -> CONFIRMED: NO MODS > 1YR | Q52: {=_xlfn.IFS(AND($A52="thg-beauty",ISNUMBER(SEARCH("liveramp",$C52))),"DELETE",$A52="agile-bonbon-662",_xlfn.IFS(LEFT($G52,9)="Tranche 1","DELETE",$C52="Sessions_Level_1_All_Sites","KEEP",ISNUMBER(--$C52),"REVIEW — UA raw logs",$C52="Emag_Reporting","KEEP",$C52="Nutrition_Data_Archived_Tables","KEEP",$C52="EU_Data","KEEP",TRUE,"REVIEW"),OR($A52="thg-influencer",$A52="thg-ingenuity",$A52="thg-central-marketing",$A52="thg-seoclarity"),"HOLD",TRUE,"")} | R52: {=_xlfn.IFS(AND($A52="thg-beauty",ISNUMBER(SEARCH("liveramp",$C52))),"thg-beauty Liveramp dataset — confirmed safe to delete",$A52="agile-bonbon-662",_xlfn.IFS(LEFT($G52,9)="Tranche 1","Tranche 1: cleared",$C52="Sessions_Level_1_All_Sites","Downstream aggregation of UA raw logs — keep if raw tables go",ISNUMBER(--$C52),"UA raw site logs (account ID) — keep pending audit-retention check",$C52="Emag_Reporting","Legacy but likely needed",$C52="Nutrition_Data_Archived_Tables","Worth keeping",$C52="EU_Data","Static lookup tables — scripts still reference (smoke-test risk)",TRUE,"Review"),OR($A52="thg-influencer",$A52="thg-ingenuity",$A52="thg-central-marketing",$A52="thg-seoclarity"),"HOLD — Charlie Stringer to review before deletion",TRUE,"")} | S52: CONFIRMED: NO MODS > 1YR
A53: thg-ml-dev | B53: eu | C53: demand_forecasting_gb4_dump | D53: No Description | E53: 174.5 | F53: 3.49 | G53: Active | H53: Low | I53: 66 | J53: 91 | K53: 46131.145 | L53: 46106.303 | M53: 2026-04-19 03:28 (vm-service@thg-demand-forecast-dev.iam.gserviceaccount.com) 2026-04-19 03:28 (vm-service@thg-demand-forecast-dev.iam.gserviceaccount.com) 2026-04-19 03:28 (vm-service@thg-demand-forecast-dev.iam.gserviceaccount.com) 2026-04-19 03:28 (vm-service@thg-demand-forecast-dev.iam.gserviceaccount.com) 2026-04-19 03:27 (vm-service@thg-demand-forecast-dev.iam.gserviceaccount.com) | N53: 2026-03-25 07:16 (atharva.lipare32@thgingenuity.com) 2026-03-24 08:46 (priestleyg@thehutgroup.com) 2026-03-24 08:46 (priestleyg@thehutgroup.com) 2026-03-24 08:45 (priestleyg@thehutgroup.com) 2026-03-24 08:45 (priestleyg@thehutgroup.com) | O53: 46106.303 | P53: =IF($Q53="DELETE",IF($S53="CONFIRMED: NO MODS > 1YR","CONFIRMED: NO MODS > 1YR","DO NOT DELETE — not defensibly confirmed"),IF($Q53="HOLD","DO NOT DELETE — HOLD (Charlie review)",IF($Q53="KEEP","DO NOT DELETE — KEEP",IF(ISNUMBER(SEARCH("REVIEW",$Q53)),"DO NOT DELETE — REVIEW pending",$S53)))) -> CONFIRMED: NO MODS > 1YR | Q53: {=_xlfn.IFS(AND($A53="thg-beauty",ISNUMBER(SEARCH("liveramp",$C53))),"DELETE",$A53="agile-bonbon-662",_xlfn.IFS(LEFT($G53,9)="Tranche 1","DELETE",$C53="Sessions_Level_1_All_Sites","KEEP",ISNUMBER(--$C53),"REVIEW — UA raw logs",$C53="Emag_Reporting","KEEP",$C53="Nutrition_Data_Archived_Tables","KEEP",$C53="EU_Data","KEEP",TRUE,"REVIEW"),OR($A53="thg-influencer",$A53="thg-ingenuity",$A53="thg-central-marketing",$A53="thg-seoclarity"),"HOLD",TRUE,"")} | R53: {=_xlfn.IFS(AND($A53="thg-beauty",ISNUMBER(SEARCH("liveramp",$C53))),"thg-beauty Liveramp dataset — confirmed safe to delete",$A53="agile-bonbon-662",_xlfn.IFS(LEFT($G53,9)="Tranche 1","Tranche 1: cleared",$C53="Sessions_Level_1_All_Sites","Downstream aggregation of UA raw logs — keep if raw tables go",ISNUMBER(--$C53),"UA raw site logs (account ID) — keep pending audit-retention check",$C53="Emag_Reporting","Legacy but likely needed",$C53="Nutrition_Data_Archived_Tables","Worth keeping",$C53="EU_Data","Static lookup tables — scripts still reference (smoke-test risk)",TRUE,"Review"),OR($A53="thg-influencer",$A53="thg-ingenuity",$A53="thg-central-marketing",$A53="thg-seoclarity"),"HOLD — Charlie Stringer to review before deletion",TRUE,"")} | S53: CONFIRMED: NO MODS > 1YR
A54: thg-beauty | B54: eu | C54: Nielsen_Feed | D54: No Description | E54: 63.43 | F54: 1.27 | G54: Active | H54: Low | I54: 0 | J54: 3 | K54: 46197.23 | L54: 46194.23 | M54: 2026-06-24 05:31 (ravi.subramaniam04@thehutgroup.com) 2026-06-24 05:30 (ravi.subramaniam04@thehutgroup.com) 2026-06-23 05:32 (ravi.subramaniam04@thehutgroup.com) 2026-06-23 05:30 (ravi.subramaniam04@thehutgroup.com) 2026-06-22 08:38 (beauty-data@agile-bonbon-662.iam.gserviceaccount.com) | N54: 2026-06-21 05:30 (ravi.subramaniam04@thehutgroup.com) 2026-06-21 05:30 (ravi.subramaniam04@thehutgroup.com) 2026-06-21 05:30 (ravi.subramaniam04@thehutgroup.com) 2026-06-21 05:30 (ravi.subramaniam04@thehutgroup.com) 2026-06-14 05:30 (ravi.subramaniam04@thehutgroup.com) | O54: 46194.23 | P54: =IF($Q54="DELETE",IF($S54="CONFIRMED: NO MODS > 1YR","CONFIRMED: NO MODS > 1YR","DO NOT DELETE — not defensibly confirmed"),IF($Q54="HOLD","DO NOT DELETE — HOLD (Charlie review)",IF($Q54="KEEP","DO NOT DELETE — KEEP",IF(ISNUMBER(SEARCH("REVIEW",$Q54)),"DO NOT DELETE — REVIEW pending",$S54)))) -> CONFIRMED: NO MODS > 1YR | Q54: {=_xlfn.IFS(AND($A54="thg-beauty",ISNUMBER(SEARCH("liveramp",$C54))),"DELETE",$A54="agile-bonbon-662",_xlfn.IFS(LEFT($G54,9)="Tranche 1","DELETE",$C54="Sessions_Level_1_All_Sites","KEEP",ISNUMBER(--$C54),"REVIEW — UA raw logs",$C54="Emag_Reporting","KEEP",$C54="Nutrition_Data_Archived_Tables","KEEP",$C54="EU_Data","KEEP",TRUE,"REVIEW"),OR($A54="thg-influencer",$A54="thg-ingenuity",$A54="thg-central-marketing",$A54="thg-seoclarity"),"HOLD",TRUE,"")} | R54: {=_xlfn.IFS(AND($A54="thg-beauty",ISNUMBER(SEARCH("liveramp",$C54))),"thg-beauty Liveramp dataset — confirmed safe to delete",$A54="agile-bonbon-662",_xlfn.IFS(LEFT($G54,9)="Tranche 1","Tranche 1: cleared",$C54="Sessions_Level_1_All_Sites","Downstream aggregation of UA raw logs — keep if raw tables go",ISNUMBER(--$C54),"UA raw site logs (account ID) — keep pending audit-retention check",$C54="Emag_Reporting","Legacy but likely needed",$C54="Nutrition_Data_Archived_Tables","Worth keeping",$C54="EU_Data","Static lookup tables — scripts still reference (smoke-test risk)",TRUE,"Review"),OR($A54="thg-influencer",$A54="thg-ingenuity",$A54="thg-central-marketing",$A54="thg-seoclarity"),"HOLD — Charlie Stringer to review before deletion",TRUE,"")} | S54: CONFIRMED: NO MODS > 1YR
A55: thg-ml-dev | B55: europe-west2 | C55: ml_spaces_v2 | D55: No Description | E55: 0.19 | F55: 0 | G55: Active | H55: Low | I55: 64 | J55: 64 | K55: 46132.461 | L55: 46132.461 | M55: 2026-04-20 11:04 (secera@thehutgroup.com) 2026-04-20 11:01 (secera@thehutgroup.com) 2026-04-20 10:58 (secera@thehutgroup.com) 2026-04-20 10:56 (secera@thehutgroup.com) 2026-04-20 10:54 (secera@thehutgroup.com) | N55: 2026-04-20 11:04 (secera@thehutgroup.com) 2026-04-20 11:01 (secera@thehutgroup.com) 2026-04-20 10:58 (secera@thehutgroup.com) 2026-04-20 10:56 (secera@thehutgroup.com) 2026-04-20 10:54 (secera@thehutgroup.com) | O55: 46132.461 | P55: =IF($Q55="DELETE",IF($S55="CONFIRMED: NO MODS > 1YR","CONFIRMED: NO MODS > 1YR","DO NOT DELETE — not defensibly confirmed"),IF($Q55="HOLD","DO NOT DELETE — HOLD (Charlie review)",IF($Q55="KEEP","DO NOT DELETE — KEEP",IF(ISNUMBER(SEARCH("REVIEW",$Q55)),"DO NOT DELETE — REVIEW pending",$S55)))) -> CONFIRMED: NO MODS > 1YR | Q55: {=_xlfn.IFS(AND($A55="thg-beauty",ISNUMBER(SEARCH("liveramp",$C55))),"DELETE",$A55="agile-bonbon-662",_xlfn.IFS(LEFT($G55,9)="Tranche 1","DELETE",$C55="Sessions_Level_1_All_Sites","KEEP",ISNUMBER(--$C55),"REVIEW — UA raw logs",$C55="Emag_Reporting","KEEP",$C55="Nutrition_Data_Archived_Tables","KEEP",$C55="EU_Data","KEEP",TRUE,"REVIEW"),OR($A55="thg-influencer",$A55="thg-ingenuity",$A55="thg-central-marketing",$A55="thg-seoclarity"),"HOLD",TRUE,"")} | R55: {=_xlfn.IFS(AND($A55="thg-beauty",ISNUMBER(SEARCH("liveramp",$C55))),"thg-beauty Liveramp dataset — confirmed safe to delete",$A55="agile-bonbon-662",_xlfn.IFS(LEFT($G55,9)="Tranche 1","Tranche 1: cleared",$C55="Sessions_Level_1_All_Sites","Downstream aggregation of UA raw logs — keep if raw tables go",ISNUMBER(--$C55),"UA raw site logs (account ID) — keep pending audit-retention check",$C55="Emag_Reporting","Legacy but likely needed",$C55="Nutrition_Data_Archived_Tables","Worth keeping",$C55="EU_Data","Static lookup tables — scripts still reference (smoke-test risk)",TRUE,"Review"),OR($A55="thg-influencer",$A55="thg-ingenuity",$A55="thg-central-marketing",$A55="thg-seoclarity"),"HOLD — Charlie Stringer to review before deletion",TRUE,"")} | S55: CONFIRMED: NO MODS > 1YR
A56: thg-machine-learning-fraud | B56: europe-west2 | C56: ctcl_curated | D56: No Description | E56: 0 | F56: 0 | G56: Active | H56: Low | I56: 64 | L56: 46132.533 | M56: No Read Access (180d) | N56: 2026-04-20 12:47 (ChunYen.Tay15@thehutgroup.com) 2026-04-20 12:46 (ChunYen.Tay15@thehutgroup.com) 2026-04-20 12:44 (ChunYen.Tay15@thehutgroup.com) | P56: =IF($Q56="DELETE",IF($S56="CONFIRMED: NO MODS > 1YR","CONFIRMED: NO MODS > 1YR","DO NOT DELETE — not defensibly confirmed"),IF($Q56="HOLD","DO NOT DELETE — HOLD (Charlie review)",IF($Q56="KEEP","DO NOT DELETE — KEEP",IF(ISNUMBER(SEARCH("REVIEW",$Q56)),"DO NOT DELETE — REVIEW pending",$S56)))) -> CONFIRMED: NO MODS > 1YR | Q56: {=_xlfn.IFS(AND($A56="thg-beauty",ISNUMBER(SEARCH("liveramp",$C56))),"DELETE",$A56="agile-bonbon-662",_xlfn.IFS(LEFT($G56,9)="Tranche 1","DELETE",$C56="Sessions_Level_1_All_Sites","KEEP",ISNUMBER(--$C56),"REVIEW — UA raw logs",$C56="Emag_Reporting","KEEP",$C56="Nutrition_Data_Archived_Tables","KEEP",$C56="EU_Data","KEEP",TRUE,"REVIEW"),OR($A56="thg-influencer",$A56="thg-ingenuity",$A56="thg-central-marketing",$A56="thg-seoclarity"),"HOLD",TRUE,"")} | R56: {=_xlfn.IFS(AND($A56="thg-beauty",ISNUMBER(SEARCH("liveramp",$C56))),"thg-beauty Liveramp dataset — confirmed safe to delete",$A56="agile-bonbon-662",_xlfn.IFS(LEFT($G56,9)="Tranche 1","Tranche 1: cleared",$C56="Sessions_Level_1_All_Sites","Downstream aggregation of UA raw logs — keep if raw tables go",ISNUMBER(--$C56),"UA raw site logs (account ID) — keep pending audit-retention check",$C56="Emag_Reporting","Legacy but likely needed",$C56="Nutrition_Data_Archived_Tables","Worth keeping",$C56="EU_Data","Static lookup tables — scripts still reference (smoke-test risk)",TRUE,"Review"),OR($A56="thg-influencer",$A56="thg-ingenuity",$A56="thg-central-marketing",$A56="thg-seoclarity"),"HOLD — Charlie Stringer to review before deletion",TRUE,"")} | S56: CONFIRMED: NO MODS > 1YR
A57: thg-influencer | B57: eu | C57: Ditto_Society_staging | D57: No Description | E57: 0 | F57: 0 | G57: Active | H57: Low | I57: 63 | K57: 46133.552 | L57: 46133.552 | M57: 2026-04-21 13:15 (dittwo@thg-influencer.iam.gserviceaccount.com) 2026-04-21 13:15 (dittwo@thg-influencer.iam.gserviceaccount.com) 2026-04-21 13:15 (dittwo@thg-influencer.iam.gserviceaccount.com) 2026-04-21 12:15 (dittwo@thg-influencer.iam.gserviceaccount.com) 2026-04-21 12:15 (dittwo@thg-influencer.iam.gserviceaccount.com) | N57: 2026-04-21 13:15 (dittwo@thg-influencer.iam.gserviceaccount.com) 2026-04-21 13:15 (dittwo@thg-influencer.iam.gserviceaccount.com) 2026-04-21 13:15 (dittwo@thg-influencer.iam.gserviceaccount.com) 2026-04-21 12:15 (dittwo@thg-influencer.iam.gserviceaccount.com) 2026-04-21 12:15 (dittwo@thg-influencer.iam.gserviceaccount.com) | P57: =IF($Q57="DELETE",IF($S57="CONFIRMED: NO MODS > 1YR","CONFIRMED: NO MODS > 1YR","DO NOT DELETE — not defensibly confirmed"),IF($Q57="HOLD","DO NOT DELETE — HOLD (Charlie review)",IF($Q57="KEEP","DO NOT DELETE — KEEP",IF(ISNUMBER(SEARCH("REVIEW",$Q57)),"DO NOT DELETE — REVIEW pending",$S57)))) -> DO NOT DELETE — HOLD (Charlie review) | Q57: {=_xlfn.IFS(AND($A57="thg-beauty",ISNUMBER(SEARCH("liveramp",$C57))),"DELETE",$A57="agile-bonbon-662",_xlfn.IFS(LEFT($G57,9)="Tranche 1","DELETE",$C57="Sessions_Level_1_All_Sites","KEEP",ISNUMBER(--$C57),"REVIEW — UA raw logs",$C57="Emag_Reporting","KEEP",$C57="Nutrition_Data_Archived_Tables","KEEP",$C57="EU_Data","KEEP",TRUE,"REVIEW"),OR($A57="thg-influencer",$A57="thg-ingenuity",$A57="thg-central-marketing",$A57="thg-seoclarity"),"HOLD",TRUE,"")} -> HOLD | R57: {=_xlfn.IFS(AND($A57="thg-beauty",ISNUMBER(SEARCH("liveramp",$C57))),"thg-beauty Liveramp dataset — confirmed safe to delete",$A57="agile-bonbon-662",_xlfn.IFS(LEFT($G57,9)="Tranche 1","Tranche 1: cleared",$C57="Sessions_Level_1_All_Sites","Downstream aggregation of UA raw logs — keep if raw tables go",ISNUMBER(--$C57),"UA raw site logs (account ID) — keep pending audit-retention check",$C57="Emag_Reporting","Legacy but likely needed",$C57="Nutrition_Data_Archived_Tables","Worth keeping",$C57="EU_Data","Static lookup tables — scripts still reference (smoke-test risk)",TRUE,"Review"),OR($A57="thg-influencer",$A57="thg-ingenuity",$A57="thg-central-marketing",$A57="thg-seoclarity"),"HOLD — Charlie Stringer to review before deletion",TRUE,"")} -> HOLD — Charlie Stringer to review before deletion | S57: CONFIRMED: NO MODS > 1YR
A58: thg-ml-dev | B58: eu | C58: demand_forecasting_gb5_dump | D58: No Description | E58: 0.62 | F58: 0.01 | G58: Active | H58: Low | I58: 62 | J58: 96 | K58: 46134.466 | L58: 46101.449 | M58: 2026-04-22 11:11 (atharva.lipare32@thgingenuity.com) 2026-04-22 11:10 (atharva.lipare32@thgingenuity.com) 2026-04-19 02:33 (vm-service@thg-demand-forecast-dev.iam.gserviceaccount.com) 2026-04-19 02:33 (vm-service@thg-demand-forecast-dev.iam.gserviceaccount.com) 2026-04-19 02:33 (vm-service@thg-demand-forecast-dev.iam.gserviceaccount.com) | N58: 2026-03-20 10:45 (atharva.lipare32@thgingenuity.com) 2026-03-09 09:56 (atharva.lipare32@thgingenuity.com) 2026-03-06 10:13 (priestleyg@thehutgroup.com) 2026-03-06 10:13 (priestleyg@thehutgroup.com) 2026-03-06 10:12 (priestleyg@thehutgroup.com) | O58: 46101.449 | P58: =IF($Q58="DELETE",IF($S58="CONFIRMED: NO MODS > 1YR","CONFIRMED: NO MODS > 1YR","DO NOT DELETE — not defensibly confirmed"),IF($Q58="HOLD","DO NOT DELETE — HOLD (Charlie review)",IF($Q58="KEEP","DO NOT DELETE — KEEP",IF(ISNUMBER(SEARCH("REVIEW",$Q58)),"DO NOT DELETE — REVIEW pending",$S58)))) -> CONFIRMED: NO MODS > 1YR | Q58: {=_xlfn.IFS(AND($A58="thg-beauty",ISNUMBER(SEARCH("liveramp",$C58))),"DELETE",$A58="agile-bonbon-662",_xlfn.IFS(LEFT($G58,9)="Tranche 1","DELETE",$C58="Sessions_Level_1_All_Sites","KEEP",ISNUMBER(--$C58),"REVIEW — UA raw logs",$C58="Emag_Reporting","KEEP",$C58="Nutrition_Data_Archived_Tables","KEEP",$C58="EU_Data","KEEP",TRUE,"REVIEW"),OR($A58="thg-influencer",$A58="thg-ingenuity",$A58="thg-central-marketing",$A58="thg-seoclarity"),"HOLD",TRUE,"")} | R58: {=_xlfn.IFS(AND($A58="thg-beauty",ISNUMBER(SEARCH("liveramp",$C58))),"thg-beauty Liveramp dataset — confirmed safe to delete",$A58="agile-bonbon-662",_xlfn.IFS(LEFT($G58,9)="Tranche 1","Tranche 1: cleared",$C58="Sessions_Level_1_All_Sites","Downstream aggregation of UA raw logs — keep if raw tables go",ISNUMBER(--$C58),"UA raw site logs (account ID) — keep pending audit-retention check",$C58="Emag_Reporting","Legacy but likely needed",$C58="Nutrition_Data_Archived_Tables","Worth keeping",$C58="EU_Data","Static lookup tables — scripts still reference (smoke-test risk)",TRUE,"Review"),OR($A58="thg-influencer",$A58="thg-ingenuity",$A58="thg-central-marketing",$A58="thg-seoclarity"),"HOLD — Charlie Stringer to review before deletion",TRUE,"")} | S58: CONFIRMED: NO MODS > 1YR
A59: thg-ml-live | B59: europe-west2 | C59: ml_spaces_v2 | D59: No Description | E59: 0.02 | F59: 0 | G59: Active | H59: Low | I59: 62 | J59: 62 | K59: 46135.447 | L59: 46135.447 | M59: 2026-04-23 10:43 (ml-spaces@thg-ml-live.iam.gserviceaccount.com) 2026-04-23 10:41 (ml-spaces@thg-ml-live.iam.gserviceaccount.com) 2026-04-21 13:24 (ml-spaces@thg-ml-live.iam.gserviceaccount.com) 2026-04-21 13:23 (ml-spaces@thg-ml-live.iam.gserviceaccount.com) 2026-04-21 13:22 (ml-spaces@thg-ml-live.iam.gserviceaccount.com) | N59: 2026-04-23 10:43 (ml-spaces@thg-ml-live.iam.gserviceaccount.com) 2026-04-23 10:41 (ml-spaces@thg-ml-live.iam.gserviceaccount.com) 2026-04-21 13:24 (ml-spaces@thg-ml-live.iam.gserviceaccount.com) 2026-04-21 13:23 (ml-spaces@thg-ml-live.iam.gserviceaccount.com) 2026-04-21 13:22 (ml-spaces@thg-ml-live.iam.gserviceaccount.com) | O59: 46135.447 | P59: =IF($Q59="DELETE",IF($S59="CONFIRMED: NO MODS > 1YR","CONFIRMED: NO MODS > 1YR","DO NOT DELETE — not defensibly confirmed"),IF($Q59="HOLD","DO NOT DELETE — HOLD (Charlie review)",IF($Q59="KEEP","DO NOT DELETE — KEEP",IF(ISNUMBER(SEARCH("REVIEW",$Q59)),"DO NOT DELETE — REVIEW pending",$S59)))) -> CONFIRMED: NO MODS > 1YR | Q59: {=_xlfn.IFS(AND($A59="thg-beauty",ISNUMBER(SEARCH("liveramp",$C59))),"DELETE",$A59="agile-bonbon-662",_xlfn.IFS(LEFT($G59,9)="Tranche 1","DELETE",$C59="Sessions_Level_1_All_Sites","KEEP",ISNUMBER(--$C59),"REVIEW — UA raw logs",$C59="Emag_Reporting","KEEP",$C59="Nutrition_Data_Archived_Tables","KEEP",$C59="EU_Data","KEEP",TRUE,"REVIEW"),OR($A59="thg-influencer",$A59="thg-ingenuity",$A59="thg-central-marketing",$A59="thg-seoclarity"),"HOLD",TRUE,"")} | R59: {=_xlfn.IFS(AND($A59="thg-beauty",ISNUMBER(SEARCH("liveramp",$C59))),"thg-beauty Liveramp dataset — confirmed safe to delete",$A59="agile-bonbon-662",_xlfn.IFS(LEFT($G59,9)="Tranche 1","Tranche 1: cleared",$C59="Sessions_Level_1_All_Sites","Downstream aggregation of UA raw logs — keep if raw tables go",ISNUMBER(--$C59),"UA raw site logs (account ID) — keep pending audit-retention check",$C59="Emag_Reporting","Legacy but likely needed",$C59="Nutrition_Data_Archived_Tables","Worth keeping",$C59="EU_Data","Static lookup tables — scripts still reference (smoke-test risk)",TRUE,"Review"),OR($A59="thg-influencer",$A59="thg-ingenuity",$A59="thg-central-marketing",$A59="thg-seoclarity"),"HOLD — Charlie Stringer to review before deletion",TRUE,"")} | S59: CONFIRMED: NO MODS > 1YR
A60: thg-beauty | B60: eu | C60: Summer_Report | D60: No Description | E60: 59.01 | F60: 1.18 | G60: Active | H60: Low | I60: 0 | J60: 0 | K60: 46197.421 | L60: 46197.11 | M60: 2026-06-24 10:06 (beauty-data@agile-bonbon-662.iam.gserviceaccount.com) 2026-06-24 10:06 (beauty-data@agile-bonbon-662.iam.gserviceaccount.com) 2026-06-24 10:03 (beauty-data@agile-bonbon-662.iam.gserviceaccount.com) 2026-06-24 10:03 (beauty-data@agile-bonbon-662.iam.gserviceaccount.com) 2026-06-24 10:00 (beauty-data@agile-bonbon-662.iam.gserviceaccount.com) | N60: 2026-06-24 02:39 (sa-bpswcbdsql01@thg-beauty.iam.gserviceaccount.com) 2026-06-24 02:38 (sa-bpswcbdsql01@thg-beauty.iam.gserviceaccount.com) 2026-06-24 02:38 (sa-bpswcbdsql01@thg-beauty.iam.gserviceaccount.com) 2026-06-24 02:38 (sa-bpswcbdsql01@thg-beauty.iam.gserviceaccount.com) 2026-06-24 02:38 (sa-bpswcbdsql01@thg-beauty.iam.gserviceaccount.com) | O60: 46197.11 | P60: =IF($Q60="DELETE",IF($S60="CONFIRMED: NO MODS > 1YR","CONFIRMED: NO MODS > 1YR","DO NOT DELETE — not defensibly confirmed"),IF($Q60="HOLD","DO NOT DELETE — HOLD (Charlie review)",IF($Q60="KEEP","DO NOT DELETE — KEEP",IF(ISNUMBER(SEARCH("REVIEW",$Q60)),"DO NOT DELETE — REVIEW pending",$S60)))) -> CONFIRMED: NO MODS > 1YR | Q60: {=_xlfn.IFS(AND($A60="thg-beauty",ISNUMBER(SEARCH("liveramp",$C60))),"DELETE",$A60="agile-bonbon-662",_xlfn.IFS(LEFT($G60,9)="Tranche 1","DELETE",$C60="Sessions_Level_1_All_Sites","KEEP",ISNUMBER(--$C60),"REVIEW — UA raw logs",$C60="Emag_Reporting","KEEP",$C60="Nutrition_Data_Archived_Tables","KEEP",$C60="EU_Data","KEEP",TRUE,"REVIEW"),OR($A60="thg-influencer",$A60="thg-ingenuity",$A60="thg-central-marketing",$A60="thg-seoclarity"),"HOLD",TRUE,"")} | R60: {=_xlfn.IFS(AND($A60="thg-beauty",ISNUMBER(SEARCH("liveramp",$C60))),"thg-beauty Liveramp dataset — confirmed safe to delete",$A60="agile-bonbon-662",_xlfn.IFS(LEFT($G60,9)="Tranche 1","Tranche 1: cleared",$C60="Sessions_Level_1_All_Sites","Downstream aggregation of UA raw logs — keep if raw tables go",ISNUMBER(--$C60),"UA raw site logs (account ID) — keep pending audit-retention check",$C60="Emag_Reporting","Legacy but likely needed",$C60="Nutrition_Data_Archived_Tables","Worth keeping",$C60="EU_Data","Static lookup tables — scripts still reference (smoke-test risk)",TRUE,"Review"),OR($A60="thg-influencer",$A60="thg-ingenuity",$A60="thg-central-marketing",$A60="thg-seoclarity"),"HOLD — Charlie Stringer to review before deletion",TRUE,"")} | S60: CONFIRMED: NO MODS > 1YR
A61: thg-beauty | B61: eu | C61: Liveramp_Segments | D61: No Description | E61: 55.23 | F61: 1.1 | G61: Active | H61: Low | I61: 0 | J61: 0 | K61: 46197.233 | L61: 46197.232 | M61: 2026-06-24 05:36 (ravi.subramaniam04@thehutgroup.com) 2026-06-24 05:34 (ravi.subramaniam04@thehutgroup.com) 2026-06-24 05:34 (ravi.subramaniam04@thehutgroup.com) 2026-06-24 05:33 (ravi.subramaniam04@thehutgroup.com) 2026-06-24 05:33 (ravi.subramaniam04@thehutgroup.com) | N61: 2026-06-24 05:33 (ravi.subramaniam04@thehutgroup.com) 2026-06-24 05:33 (ravi.subramaniam04@thehutgroup.com) 2026-06-24 02:45 (ravi.subramaniam04@thehutgroup.com) 2026-06-24 02:45 (ravi.subramaniam04@thehutgroup.com) 2026-06-24 02:45 (ravi.subramaniam04@thehutgroup.com) | O61: 46197.232 | P61: =IF($Q61="DELETE",IF($S61="CONFIRMED: NO MODS > 1YR","CONFIRMED: NO MODS > 1YR","DO NOT DELETE — not defensibly confirmed"),IF($Q61="HOLD","DO NOT DELETE — HOLD (Charlie review)",IF($Q61="KEEP","DO NOT DELETE — KEEP",IF(ISNUMBER(SEARCH("REVIEW",$Q61)),"DO NOT DELETE — REVIEW pending",$S61)))) -> CONFIRMED: NO MODS > 1YR | Q61: {=_xlfn.IFS(AND($A61="thg-beauty",ISNUMBER(SEARCH("liveramp",$C61))),"DELETE",$A61="agile-bonbon-662",_xlfn.IFS(LEFT($G61,9)="Tranche 1","DELETE",$C61="Sessions_Level_1_All_Sites","KEEP",ISNUMBER(--$C61),"REVIEW — UA raw logs",$C61="Emag_Reporting","KEEP",$C61="Nutrition_Data_Archived_Tables","KEEP",$C61="EU_Data","KEEP",TRUE,"REVIEW"),OR($A61="thg-influencer",$A61="thg-ingenuity",$A61="thg-central-marketing",$A61="thg-seoclarity"),"HOLD",TRUE,"")} -> DELETE | R61: {=_xlfn.IFS(AND($A61="thg-beauty",ISNUMBER(SEARCH("liveramp",$C61))),"thg-beauty Liveramp dataset — confirmed safe to delete",$A61="agile-bonbon-662",_xlfn.IFS(LEFT($G61,9)="Tranche 1","Tranche 1: cleared",$C61="Sessions_Level_1_All_Sites","Downstream aggregation of UA raw logs — keep if raw tables go",ISNUMBER(--$C61),"UA raw site logs (account ID) — keep pending audit-retention check",$C61="Emag_Reporting","Legacy but likely needed",$C61="Nutrition_Data_Archived_Tables","Worth keeping",$C61="EU_Data","Static lookup tables — scripts still reference (smoke-test risk)",TRUE,"Review"),OR($A61="thg-influencer",$A61="thg-ingenuity",$A61="thg-central-marketing",$A61="thg-seoclarity"),"HOLD — Charlie Stringer to review before deletion",TRUE,"")} -> thg-beauty Liveramp dataset — confirmed safe to delete | S61: CONFIRMED: NO MODS > 1YR
A62: the-hut-group | B62: eu | C62: experimentation_sessions_exp_value_fix | D62: No Description | E62: 34495.04 | F62: 689.9 | G62: Active | H62: Low | I62: 56 | J62: 160 | K62: 46141.388 | L62: 46070.167 | M62: 2026-04-29 09:18 (ingersolla@thehutgroup.com) 2026-01-15 04:02 (exp-saviour@the-hut-group.iam.gserviceaccount.com) 2026-01-15 04:02 (exp-saviour@the-hut-group.iam.gserviceaccount.com) 2026-01-15 04:02 (exp-saviour@the-hut-group.iam.gserviceaccount.com) 2026-01-15 04:02 (exp-saviour@the-hut-group.iam.gserviceaccount.com) | N62: 2026-02-17 04:00 (exp-saviour@the-hut-group.iam.gserviceaccount.com) 2026-02-16 04:00 (exp-saviour@the-hut-group.iam.gserviceaccount.com) 2026-02-15 04:00 (exp-saviour@the-hut-group.iam.gserviceaccount.com) 2026-02-14 04:00 (exp-saviour@the-hut-group.iam.gserviceaccount.com) 2026-02-13 04:00 (exp-saviour@the-hut-group.iam.gserviceaccount.com) | O62: 46037.169 | P62: =IF($Q62="DELETE",IF($S62="CONFIRMED: NO MODS > 1YR","CONFIRMED: NO MODS > 1YR","DO NOT DELETE — not defensibly confirmed"),IF($Q62="HOLD","DO NOT DELETE — HOLD (Charlie review)",IF($Q62="KEEP","DO NOT DELETE — KEEP",IF(ISNUMBER(SEARCH("REVIEW",$Q62)),"DO NOT DELETE — REVIEW pending",$S62)))) -> CONFIRMED: NO MODS > 1YR | Q62: {=_xlfn.IFS(AND($A62="thg-beauty",ISNUMBER(SEARCH("liveramp",$C62))),"DELETE",$A62="agile-bonbon-662",_xlfn.IFS(LEFT($G62,9)="Tranche 1","DELETE",$C62="Sessions_Level_1_All_Sites","KEEP",ISNUMBER(--$C62),"REVIEW — UA raw logs",$C62="Emag_Reporting","KEEP",$C62="Nutrition_Data_Archived_Tables","KEEP",$C62="EU_Data","KEEP",TRUE,"REVIEW"),OR($A62="thg-influencer",$A62="thg-ingenuity",$A62="thg-central-marketing",$A62="thg-seoclarity"),"HOLD",TRUE,"")} | R62: {=_xlfn.IFS(AND($A62="thg-beauty",ISNUMBER(SEARCH("liveramp",$C62))),"thg-beauty Liveramp dataset — confirmed safe to delete",$A62="agile-bonbon-662",_xlfn.IFS(LEFT($G62,9)="Tranche 1","Tranche 1: cleared",$C62="Sessions_Level_1_All_Sites","Downstream aggregation of UA raw logs — keep if raw tables go",ISNUMBER(--$C62),"UA raw site logs (account ID) — keep pending audit-retention check",$C62="Emag_Reporting","Legacy but likely needed",$C62="Nutrition_Data_Archived_Tables","Worth keeping",$C62="EU_Data","Static lookup tables — scripts still reference (smoke-test risk)",TRUE,"Review"),OR($A62="thg-influencer",$A62="thg-ingenuity",$A62="thg-central-marketing",$A62="thg-seoclarity"),"HOLD — Charlie Stringer to review before deletion",TRUE,"")} | S62: CONFIRMED: NO MODS > 1YR
A63: the-hut-group | B63: eu | C63: experiments_value_fix | D63: No Description | E63: 22142.42 | F63: 442.85 | G63: Active | H63: Low | I63: 56 | J63: 161 | K63: 46141.388 | L63: 46036.126 | M63: 2026-04-29 09:18 (ingersolla@thehutgroup.com) 2026-01-15 04:02 (exp-saviour@the-hut-group.iam.gserviceaccount.com) 2026-01-15 04:00 (exp-saviour@the-hut-group.iam.gserviceaccount.com) 2026-01-15 04:00 (exp-saviour@the-hut-group.iam.gserviceaccount.com) 2026-01-14 04:09 (exp-saviour@the-hut-group.iam.gserviceaccount.com) | N63: 2026-01-14 03:01 (meirosur@thehutgroup.com) 2026-01-14 03:01 (meirosur@thehutgroup.com) 2026-01-14 03:01 (meirosur@thehutgroup.com) 2026-01-14 03:00 (meirosur@thehutgroup.com) 2026-01-14 03:00 (meirosur@thehutgroup.com) | O63: 46036.126 | P63: =IF($Q63="DELETE",IF($S63="CONFIRMED: NO MODS > 1YR","CONFIRMED: NO MODS > 1YR","DO NOT DELETE — not defensibly confirmed"),IF($Q63="HOLD","DO NOT DELETE — HOLD (Charlie review)",IF($Q63="KEEP","DO NOT DELETE — KEEP",IF(ISNUMBER(SEARCH("REVIEW",$Q63)),"DO NOT DELETE — REVIEW pending",$S63)))) -> CONFIRMED: NO MODS > 1YR | Q63: {=_xlfn.IFS(AND($A63="thg-beauty",ISNUMBER(SEARCH("liveramp",$C63))),"DELETE",$A63="agile-bonbon-662",_xlfn.IFS(LEFT($G63,9)="Tranche 1","DELETE",$C63="Sessions_Level_1_All_Sites","KEEP",ISNUMBER(--$C63),"REVIEW — UA raw logs",$C63="Emag_Reporting","KEEP",$C63="Nutrition_Data_Archived_Tables","KEEP",$C63="EU_Data","KEEP",TRUE,"REVIEW"),OR($A63="thg-influencer",$A63="thg-ingenuity",$A63="thg-central-marketing",$A63="thg-seoclarity"),"HOLD",TRUE,"")} | R63: {=_xlfn.IFS(AND($A63="thg-beauty",ISNUMBER(SEARCH("liveramp",$C63))),"thg-beauty Liveramp dataset — confirmed safe to delete",$A63="agile-bonbon-662",_xlfn.IFS(LEFT($G63,9)="Tranche 1","Tranche 1: cleared",$C63="Sessions_Level_1_All_Sites","Downstream aggregation of UA raw logs — keep if raw tables go",ISNUMBER(--$C63),"UA raw site logs (account ID) — keep pending audit-retention check",$C63="Emag_Reporting","Legacy but likely needed",$C63="Nutrition_Data_Archived_Tables","Worth keeping",$C63="EU_Data","Static lookup tables — scripts still reference (smoke-test risk)",TRUE,"Review"),OR($A63="thg-influencer",$A63="thg-ingenuity",$A63="thg-central-marketing",$A63="thg-seoclarity"),"HOLD — Charlie Stringer to review before deletion",TRUE,"")} | S63: CONFIRMED: NO MODS > 1YR
A64: the-hut-group | B64: eu | C64: real_user_monitoring | D64: No Description | E64: 12778.71 | F64: 255.57 | G64: Active | H64: Low | I64: 56 | J64: 357 | K64: 46141.388 | M64: 2026-04-29 09:18 (ingersolla@thehutgroup.com) | N64: No Write Access (180d) | O64: 45839.469 | P64: =IF($Q64="DELETE",IF($S64="CONFIRMED: NO MODS > 1YR","CONFIRMED: NO MODS > 1YR","DO NOT DELETE — not defensibly confirmed"),IF($Q64="HOLD","DO NOT DELETE — HOLD (Charlie review)",IF($Q64="KEEP","DO NOT DELETE — KEEP",IF(ISNUMBER(SEARCH("REVIEW",$Q64)),"DO NOT DELETE — REVIEW pending",$S64)))) -> CONFIRMED: NO MODS > 1YR | Q64: {=_xlfn.IFS(AND($A64="thg-beauty",ISNUMBER(SEARCH("liveramp",$C64))),"DELETE",$A64="agile-bonbon-662",_xlfn.IFS(LEFT($G64,9)="Tranche 1","DELETE",$C64="Sessions_Level_1_All_Sites","KEEP",ISNUMBER(--$C64),"REVIEW — UA raw logs",$C64="Emag_Reporting","KEEP",$C64="Nutrition_Data_Archived_Tables","KEEP",$C64="EU_Data","KEEP",TRUE,"REVIEW"),OR($A64="thg-influencer",$A64="thg-ingenuity",$A64="thg-central-marketing",$A64="thg-seoclarity"),"HOLD",TRUE,"")} | R64: {=_xlfn.IFS(AND($A64="thg-beauty",ISNUMBER(SEARCH("liveramp",$C64))),"thg-beauty Liveramp dataset — confirmed safe to delete",$A64="agile-bonbon-662",_xlfn.IFS(LEFT($G64,9)="Tranche 1","Tranche 1: cleared",$C64="Sessions_Level_1_All_Sites","Downstream aggregation of UA raw logs — keep if raw tables go",ISNUMBER(--$C64),"UA raw site logs (account ID) — keep pending audit-retention check",$C64="Emag_Reporting","Legacy but likely needed",$C64="Nutrition_Data_Archived_Tables","Worth keeping",$C64="EU_Data","Static lookup tables — scripts still reference (smoke-test risk)",TRUE,"Review"),OR($A64="thg-influencer",$A64="thg-ingenuity",$A64="thg-central-marketing",$A64="thg-seoclarity"),"HOLD — Charlie Stringer to review before deletion",TRUE,"")} | S64: CONFIRMED: NO MODS > 1YR
A65: vibrant-map-107910 | B65: eu | C65: email_segmentation | D65: No Description | E65: 264.34 | F65: 5.29 | G65: Active | H65: Low | I65: 56 | J65: 291 | K65: 46141.415 | M65: 2026-04-29 09:57 (ingersolla@thehutgroup.com) | N65: No Write Access (180d) | O65: 45905.58 | P65: =IF($Q65="DELETE",IF($S65="CONFIRMED: NO MODS > 1YR","CONFIRMED: NO MODS > 1YR","DO NOT DELETE — not defensibly confirmed"),IF($Q65="HOLD","DO NOT DELETE — HOLD (Charlie review)",IF($Q65="KEEP","DO NOT DELETE — KEEP",IF(ISNUMBER(SEARCH("REVIEW",$Q65)),"DO NOT DELETE — REVIEW pending",$S65)))) -> CONFIRMED: NO MODS > 1YR | Q65: {=_xlfn.IFS(AND($A65="thg-beauty",ISNUMBER(SEARCH("liveramp",$C65))),"DELETE",$A65="agile-bonbon-662",_xlfn.IFS(LEFT($G65,9)="Tranche 1","DELETE",$C65="Sessions_Level_1_All_Sites","KEEP",ISNUMBER(--$C65),"REVIEW — UA raw logs",$C65="Emag_Reporting","KEEP",$C65="Nutrition_Data_Archived_Tables","KEEP",$C65="EU_Data","KEEP",TRUE,"REVIEW"),OR($A65="thg-influencer",$A65="thg-ingenuity",$A65="thg-central-marketing",$A65="thg-seoclarity"),"HOLD",TRUE,"")} | R65: {=_xlfn.IFS(AND($A65="thg-beauty",ISNUMBER(SEARCH("liveramp",$C65))),"thg-beauty Liveramp dataset — confirmed safe to delete",$A65="agile-bonbon-662",_xlfn.IFS(LEFT($G65,9)="Tranche 1","Tranche 1: cleared",$C65="Sessions_Level_1_All_Sites","Downstream aggregation of UA raw logs — keep if raw tables go",ISNUMBER(--$C65),"UA raw site logs (account ID) — keep pending audit-retention check",$C65="Emag_Reporting","Legacy but likely needed",$C65="Nutrition_Data_Archived_Tables","Worth keeping",$C65="EU_Data","Static lookup tables — scripts still reference (smoke-test risk)",TRUE,"Review"),OR($A65="thg-influencer",$A65="thg-ingenuity",$A65="thg-central-marketing",$A65="thg-seoclarity"),"HOLD — Charlie Stringer to review before deletion",TRUE,"")} | S65: CONFIRMED: NO MODS > 1YR
A66: vibrant-map-107910 | B66: eu | C66: data_engineering | D66: No Description | E66: 13.3 | F66: 0.27 | G66: Active | H66: Low | I66: 56 | J66: 112 | K66: 46141.415 | L66: 46084.57 | M66: 2026-04-29 09:56 (ingersolla@thehutgroup.com) 2026-03-05 16:25 (hassaina@thehutgroup.com) 2026-03-05 16:25 (hassaina@thehutgroup.com) 2026-03-03 13:58 (hassaina@thehutgroup.com) 2026-03-03 13:40 (hassaina@thehutgroup.com) | N66: 2026-03-03 13:40 (hassaina@thehutgroup.com) 2026-03-03 13:40 (hassaina@thehutgroup.com) 2026-03-03 13:13 (hassaina@thehutgroup.com) 2026-03-03 13:13 (hassaina@thehutgroup.com) 2026-03-03 12:28 (hassaina@thehutgroup.com) | O66: 46084.582 | P66: =IF($Q66="DELETE",IF($S66="CONFIRMED: NO MODS > 1YR","CONFIRMED: NO MODS > 1YR","DO NOT DELETE — not defensibly confirmed"),IF($Q66="HOLD","DO NOT DELETE — HOLD (Charlie review)",IF($Q66="KEEP","DO NOT DELETE — KEEP",IF(ISNUMBER(SEARCH("REVIEW",$Q66)),"DO NOT DELETE — REVIEW pending",$S66)))) -> CONFIRMED: NO MODS > 1YR | Q66: {=_xlfn.IFS(AND($A66="thg-beauty",ISNUMBER(SEARCH("liveramp",$C66))),"DELETE",$A66="agile-bonbon-662",_xlfn.IFS(LEFT($G66,9)="Tranche 1","DELETE",$C66="Sessions_Level_1_All_Sites","KEEP",ISNUMBER(--$C66),"REVIEW — UA raw logs",$C66="Emag_Reporting","KEEP",$C66="Nutrition_Data_Archived_Tables","KEEP",$C66="EU_Data","KEEP",TRUE,"REVIEW"),OR($A66="thg-influencer",$A66="thg-ingenuity",$A66="thg-central-marketing",$A66="thg-seoclarity"),"HOLD",TRUE,"")} | R66: {=_xlfn.IFS(AND($A66="thg-beauty",ISNUMBER(SEARCH("liveramp",$C66))),"thg-beauty Liveramp dataset — confirmed safe to delete",$A66="agile-bonbon-662",_xlfn.IFS(LEFT($G66,9)="Tranche 1","Tranche 1: cleared",$C66="Sessions_Level_1_All_Sites","Downstream aggregation of UA raw logs — keep if raw tables go",ISNUMBER(--$C66),"UA raw site logs (account ID) — keep pending audit-retention check",$C66="Emag_Reporting","Legacy but likely needed",$C66="Nutrition_Data_Archived_Tables","Worth keeping",$C66="EU_Data","Static lookup tables — scripts still reference (smoke-test risk)",TRUE,"Review"),OR($A66="thg-influencer",$A66="thg-ingenuity",$A66="thg-central-marketing",$A66="thg-seoclarity"),"HOLD — Charlie Stringer to review before deletion",TRUE,"")} | S66: CONFIRMED: NO MODS > 1YR
A67: the-hut-group | B67: eu | C67: 01_Aaks | D67: No Description | E67: 10.04 | F67: 0.2 | G67: Active | H67: Low | I67: 56 | J67: 323 | K67: 46141.387 | M67: 2026-04-29 09:17 (ingersolla@thehutgroup.com) | N67: No Write Access (180d) | O67: 45873.525 | P67: =IF($Q67="DELETE",IF($S67="CONFIRMED: NO MODS > 1YR","CONFIRMED: NO MODS > 1YR","DO NOT DELETE — not defensibly confirmed"),IF($Q67="HOLD","DO NOT DELETE — HOLD (Charlie review)",IF($Q67="KEEP","DO NOT DELETE — KEEP",IF(ISNUMBER(SEARCH("REVIEW",$Q67)),"DO NOT DELETE — REVIEW pending",$S67)))) -> CONFIRMED: NO MODS > 1YR | Q67: {=_xlfn.IFS(AND($A67="thg-beauty",ISNUMBER(SEARCH("liveramp",$C67))),"DELETE",$A67="agile-bonbon-662",_xlfn.IFS(LEFT($G67,9)="Tranche 1","DELETE",$C67="Sessions_Level_1_All_Sites","KEEP",ISNUMBER(--$C67),"REVIEW — UA raw logs",$C67="Emag_Reporting","KEEP",$C67="Nutrition_Data_Archived_Tables","KEEP",$C67="EU_Data","KEEP",TRUE,"REVIEW"),OR($A67="thg-influencer",$A67="thg-ingenuity",$A67="thg-central-marketing",$A67="thg-seoclarity"),"HOLD",TRUE,"")} | R67: {=_xlfn.IFS(AND($A67="thg-beauty",ISNUMBER(SEARCH("liveramp",$C67))),"thg-beauty Liveramp dataset — confirmed safe to delete",$A67="agile-bonbon-662",_xlfn.IFS(LEFT($G67,9)="Tranche 1","Tranche 1: cleared",$C67="Sessions_Level_1_All_Sites","Downstream aggregation of UA raw logs — keep if raw tables go",ISNUMBER(--$C67),"UA raw site logs (account ID) — keep pending audit-retention check",$C67="Emag_Reporting","Legacy but likely needed",$C67="Nutrition_Data_Archived_Tables","Worth keeping",$C67="EU_Data","Static lookup tables — scripts still reference (smoke-test risk)",TRUE,"Review"),OR($A67="thg-influencer",$A67="thg-ingenuity",$A67="thg-central-marketing",$A67="thg-seoclarity"),"HOLD — Charlie Stringer to review before deletion",TRUE,"")} | S67: CONFIRMED: NO MODS > 1YR
A68: the-hut-group | B68: eu | C68: search | D68: No Description | E68: 9.69 | F68: 0.19 | G68: Active | H68: Low | I68: 56 | J68: 358 | K68: 46141.388 | M68: 2026-04-29 09:19 (ingersolla@thehutgroup.com) 2026-03-19 09:00 (search-trending-searches@the-hut-group.iam.gserviceaccount.com) | N68: No Write Access (180d) | O68: 45839.01 | P68: =IF($Q68="DELETE",IF($S68="CONFIRMED: NO MODS > 1YR","CONFIRMED: NO MODS > 1YR","DO NOT DELETE — not defensibly confirmed"),IF($Q68="HOLD","DO NOT DELETE — HOLD (Charlie review)",IF($Q68="KEEP","DO NOT DELETE — KEEP",IF(ISNUMBER(SEARCH("REVIEW",$Q68)),"DO NOT DELETE — REVIEW pending",$S68)))) -> CONFIRMED: NO MODS > 1YR | Q68: {=_xlfn.IFS(AND($A68="thg-beauty",ISNUMBER(SEARCH("liveramp",$C68))),"DELETE",$A68="agile-bonbon-662",_xlfn.IFS(LEFT($G68,9)="Tranche 1","DELETE",$C68="Sessions_Level_1_All_Sites","KEEP",ISNUMBER(--$C68),"REVIEW — UA raw logs",$C68="Emag_Reporting","KEEP",$C68="Nutrition_Data_Archived_Tables","KEEP",$C68="EU_Data","KEEP",TRUE,"REVIEW"),OR($A68="thg-influencer",$A68="thg-ingenuity",$A68="thg-central-marketing",$A68="thg-seoclarity"),"HOLD",TRUE,"")} | R68: {=_xlfn.IFS(AND($A68="thg-beauty",ISNUMBER(SEARCH("liveramp",$C68))),"thg-beauty Liveramp dataset — confirmed safe to delete",$A68="agile-bonbon-662",_xlfn.IFS(LEFT($G68,9)="Tranche 1","Tranche 1: cleared",$C68="Sessions_Level_1_All_Sites","Downstream aggregation of UA raw logs — keep if raw tables go",ISNUMBER(--$C68),"UA raw site logs (account ID) — keep pending audit-retention check",$C68="Emag_Reporting","Legacy but likely needed",$C68="Nutrition_Data_Archived_Tables","Worth keeping",$C68="EU_Data","Static lookup tables — scripts still reference (smoke-test risk)",TRUE,"Review"),OR($A68="thg-influencer",$A68="thg-ingenuity",$A68="thg-central-marketing",$A68="thg-seoclarity"),"HOLD — Charlie Stringer to review before deletion",TRUE,"")} | S68: CONFIRMED: NO MODS > 1YR
A69: vibrant-map-107910 | B69: eu | C69: kafka | D69: No Description | E69: 5.88 | F69: 0.12 | G69: Active | H69: Low | I69: 56 | J69: 256 | K69: 46141.415 | M69: 2026-04-29 09:57 (ingersolla@thehutgroup.com) | N69: No Write Access (180d) | O69: 45940.568 | P69: =IF($Q69="DELETE",IF($S69="CONFIRMED: NO MODS > 1YR","CONFIRMED: NO MODS > 1YR","DO NOT DELETE — not defensibly confirmed"),IF($Q69="HOLD","DO NOT DELETE — HOLD (Charlie review)",IF($Q69="KEEP","DO NOT DELETE — KEEP",IF(ISNUMBER(SEARCH("REVIEW",$Q69)),"DO NOT DELETE — REVIEW pending",$S69)))) -> CONFIRMED: NO MODS > 1YR | Q69: {=_xlfn.IFS(AND($A69="thg-beauty",ISNUMBER(SEARCH("liveramp",$C69))),"DELETE",$A69="agile-bonbon-662",_xlfn.IFS(LEFT($G69,9)="Tranche 1","DELETE",$C69="Sessions_Level_1_All_Sites","KEEP",ISNUMBER(--$C69),"REVIEW — UA raw logs",$C69="Emag_Reporting","KEEP",$C69="Nutrition_Data_Archived_Tables","KEEP",$C69="EU_Data","KEEP",TRUE,"REVIEW"),OR($A69="thg-influencer",$A69="thg-ingenuity",$A69="thg-central-marketing",$A69="thg-seoclarity"),"HOLD",TRUE,"")} | R69: {=_xlfn.IFS(AND($A69="thg-beauty",ISNUMBER(SEARCH("liveramp",$C69))),"thg-beauty Liveramp dataset — confirmed safe to delete",$A69="agile-bonbon-662",_xlfn.IFS(LEFT($G69,9)="Tranche 1","Tranche 1: cleared",$C69="Sessions_Level_1_All_Sites","Downstream aggregation of UA raw logs — keep if raw tables go",ISNUMBER(--$C69),"UA raw site logs (account ID) — keep pending audit-retention check",$C69="Emag_Reporting","Legacy but likely needed",$C69="Nutrition_Data_Archived_Tables","Worth keeping",$C69="EU_Data","Static lookup tables — scripts still reference (smoke-test risk)",TRUE,"Review"),OR($A69="thg-influencer",$A69="thg-ingenuity",$A69="thg-central-marketing",$A69="thg-seoclarity"),"HOLD — Charlie Stringer to review before deletion",TRUE,"")} | S69: CONFIRMED: NO MODS > 1YR
A70: vibrant-map-107910 | B70: eu | C70: Elysium | D70: No Description | E70: 2.44 | F70: 0.05 | G70: Active | H70: Low | I70: 56 | J70: 298 | K70: 46141.414 | M70: 2026-04-29 09:56 (ingersolla@thehutgroup.com) 2026-03-23 17:38 (ingersolla@thehutgroup.com) | N70: No Write Access (180d) | O70: 45898.56 | P70: =IF($Q70="DELETE",IF($S70="CONFIRMED: NO MODS > 1YR","CONFIRMED: NO MODS > 1YR","DO NOT DELETE — not defensibly confirmed"),IF($Q70="HOLD","DO NOT DELETE — HOLD (Charlie review)",IF($Q70="KEEP","DO NOT DELETE — KEEP",IF(ISNUMBER(SEARCH("REVIEW",$Q70)),"DO NOT DELETE — REVIEW pending",$S70)))) -> CONFIRMED: NO MODS > 1YR | Q70: {=_xlfn.IFS(AND($A70="thg-beauty",ISNUMBER(SEARCH("liveramp",$C70))),"DELETE",$A70="agile-bonbon-662",_xlfn.IFS(LEFT($G70,9)="Tranche 1","DELETE",$C70="Sessions_Level_1_All_Sites","KEEP",ISNUMBER(--$C70),"REVIEW — UA raw logs",$C70="Emag_Reporting","KEEP",$C70="Nutrition_Data_Archived_Tables","KEEP",$C70="EU_Data","KEEP",TRUE,"REVIEW"),OR($A70="thg-influencer",$A70="thg-ingenuity",$A70="thg-central-marketing",$A70="thg-seoclarity"),"HOLD",TRUE,"")} | R70: {=_xlfn.IFS(AND($A70="thg-beauty",ISNUMBER(SEARCH("liveramp",$C70))),"thg-beauty Liveramp dataset — confirmed safe to delete",$A70="agile-bonbon-662",_xlfn.IFS(LEFT($G70,9)="Tranche 1","Tranche 1: cleared",$C70="Sessions_Level_1_All_Sites","Downstream aggregation of UA raw logs — keep if raw tables go",ISNUMBER(--$C70),"UA raw site logs (account ID) — keep pending audit-retention check",$C70="Emag_Reporting","Legacy but likely needed",$C70="Nutrition_Data_Archived_Tables","Worth keeping",$C70="EU_Data","Static lookup tables — scripts still reference (smoke-test risk)",TRUE,"Review"),OR($A70="thg-influencer",$A70="thg-ingenuity",$A70="thg-central-marketing",$A70="thg-seoclarity"),"HOLD — Charlie Stringer to review before deletion",TRUE,"")} | S70: CONFIRMED: NO MODS > 1YR
A71: the-hut-group | B71: eu | C71: Personify_Segmentation_Data | D71: No Description | E71: 1.2 | F71: 0.02 | G71: Active | H71: Low | I71: 56 | J71: 301 | K71: 46141.387 | M71: 2026-04-29 09:17 (ingersolla@thehutgroup.com) | N71: No Write Access (180d) | O71: 45896.125 | P71: =IF($Q71="DELETE",IF($S71="CONFIRMED: NO MODS > 1YR","CONFIRMED: NO MODS > 1YR","DO NOT DELETE — not defensibly confirmed"),IF($Q71="HOLD","DO NOT DELETE — HOLD (Charlie review)",IF($Q71="KEEP","DO NOT DELETE — KEEP",IF(ISNUMBER(SEARCH("REVIEW",$Q71)),"DO NOT DELETE — REVIEW pending",$S71)))) -> CONFIRMED: NO MODS > 1YR | Q71: {=_xlfn.IFS(AND($A71="thg-beauty",ISNUMBER(SEARCH("liveramp",$C71))),"DELETE",$A71="agile-bonbon-662",_xlfn.IFS(LEFT($G71,9)="Tranche 1","DELETE",$C71="Sessions_Level_1_All_Sites","KEEP",ISNUMBER(--$C71),"REVIEW — UA raw logs",$C71="Emag_Reporting","KEEP",$C71="Nutrition_Data_Archived_Tables","KEEP",$C71="EU_Data","KEEP",TRUE,"REVIEW"),OR($A71="thg-influencer",$A71="thg-ingenuity",$A71="thg-central-marketing",$A71="thg-seoclarity"),"HOLD",TRUE,"")} | R71: {=_xlfn.IFS(AND($A71="thg-beauty",ISNUMBER(SEARCH("liveramp",$C71))),"thg-beauty Liveramp dataset — confirmed safe to delete",$A71="agile-bonbon-662",_xlfn.IFS(LEFT($G71,9)="Tranche 1","Tranche 1: cleared",$C71="Sessions_Level_1_All_Sites","Downstream aggregation of UA raw logs — keep if raw tables go",ISNUMBER(--$C71),"UA raw site logs (account ID) — keep pending audit-retention check",$C71="Emag_Reporting","Legacy but likely needed",$C71="Nutrition_Data_Archived_Tables","Worth keeping",$C71="EU_Data","Static lookup tables — scripts still reference (smoke-test risk)",TRUE,"Review"),OR($A71="thg-influencer",$A71="thg-ingenuity",$A71="thg-central-marketing",$A71="thg-seoclarity"),"HOLD — Charlie Stringer to review before deletion",TRUE,"")} | S71: CONFIRMED: NO MODS > 1YR
A72: vibrant-map-107910 | B72: eu | C72: PnG_Data | D72: No Description | E72: 0.52 | F72: 0.01 | G72: Active | H72: Low | I72: 56 | J72: 201 | K72: 46141.414 | M72: 2026-04-29 09:56 (ingersolla@thehutgroup.com) | N72: No Write Access (180d) | O72: 45995.479 | P72: =IF($Q72="DELETE",IF($S72="CONFIRMED: NO MODS > 1YR","CONFIRMED: NO MODS > 1YR","DO NOT DELETE — not defensibly confirmed"),IF($Q72="HOLD","DO NOT DELETE — HOLD (Charlie review)",IF($Q72="KEEP","DO NOT DELETE — KEEP",IF(ISNUMBER(SEARCH("REVIEW",$Q72)),"DO NOT DELETE — REVIEW pending",$S72)))) -> CONFIRMED: NO MODS > 1YR | Q72: {=_xlfn.IFS(AND($A72="thg-beauty",ISNUMBER(SEARCH("liveramp",$C72))),"DELETE",$A72="agile-bonbon-662",_xlfn.IFS(LEFT($G72,9)="Tranche 1","DELETE",$C72="Sessions_Level_1_All_Sites","KEEP",ISNUMBER(--$C72),"REVIEW — UA raw logs",$C72="Emag_Reporting","KEEP",$C72="Nutrition_Data_Archived_Tables","KEEP",$C72="EU_Data","KEEP",TRUE,"REVIEW"),OR($A72="thg-influencer",$A72="thg-ingenuity",$A72="thg-central-marketing",$A72="thg-seoclarity"),"HOLD",TRUE,"")} | R72: {=_xlfn.IFS(AND($A72="thg-beauty",ISNUMBER(SEARCH("liveramp",$C72))),"thg-beauty Liveramp dataset — confirmed safe to delete",$A72="agile-bonbon-662",_xlfn.IFS(LEFT($G72,9)="Tranche 1","Tranche 1: cleared",$C72="Sessions_Level_1_All_Sites","Downstream aggregation of UA raw logs — keep if raw tables go",ISNUMBER(--$C72),"UA raw site logs (account ID) — keep pending audit-retention check",$C72="Emag_Reporting","Legacy but likely needed",$C72="Nutrition_Data_Archived_Tables","Worth keeping",$C72="EU_Data","Static lookup tables — scripts still reference (smoke-test risk)",TRUE,"Review"),OR($A72="thg-influencer",$A72="thg-ingenuity",$A72="thg-central-marketing",$A72="thg-seoclarity"),"HOLD — Charlie Stringer to review before deletion",TRUE,"")} | S72: CONFIRMED: NO MODS > 1YR
A73: vibrant-map-107910 | B73: eu | C73: dead_letters | D73: No Description | E73: 0.05 | F73: 0 | G73: Active | H73: Low | I73: 56 | J73: 58 | K73: 46141.415 | M73: 2026-04-29 09:57 (ingersolla@thehutgroup.com) | N73: No Write Access (180d) | O73: 46139.289 | P73: =IF($Q73="DELETE",IF($S73="CONFIRMED: NO MODS > 1YR","CONFIRMED: NO MODS > 1YR","DO NOT DELETE — not defensibly confirmed"),IF($Q73="HOLD","DO NOT DELETE — HOLD (Charlie review)",IF($Q73="KEEP","DO NOT DELETE — KEEP",IF(ISNUMBER(SEARCH("REVIEW",$Q73)),"DO NOT DELETE — REVIEW pending",$S73)))) -> CONFIRMED: NO MODS > 1YR | Q73: {=_xlfn.IFS(AND($A73="thg-beauty",ISNUMBER(SEARCH("liveramp",$C73))),"DELETE",$A73="agile-bonbon-662",_xlfn.IFS(LEFT($G73,9)="Tranche 1","DELETE",$C73="Sessions_Level_1_All_Sites","KEEP",ISNUMBER(--$C73),"REVIEW — UA raw logs",$C73="Emag_Reporting","KEEP",$C73="Nutrition_Data_Archived_Tables","KEEP",$C73="EU_Data","KEEP",TRUE,"REVIEW"),OR($A73="thg-influencer",$A73="thg-ingenuity",$A73="thg-central-marketing",$A73="thg-seoclarity"),"HOLD",TRUE,"")} | R73: {=_xlfn.IFS(AND($A73="thg-beauty",ISNUMBER(SEARCH("liveramp",$C73))),"thg-beauty Liveramp dataset — confirmed safe to delete",$A73="agile-bonbon-662",_xlfn.IFS(LEFT($G73,9)="Tranche 1","Tranche 1: cleared",$C73="Sessions_Level_1_All_Sites","Downstream aggregation of UA raw logs — keep if raw tables go",ISNUMBER(--$C73),"UA raw site logs (account ID) — keep pending audit-retention check",$C73="Emag_Reporting","Legacy but likely needed",$C73="Nutrition_Data_Archived_Tables","Worth keeping",$C73="EU_Data","Static lookup tables — scripts still reference (smoke-test risk)",TRUE,"Review"),OR($A73="thg-influencer",$A73="thg-ingenuity",$A73="thg-central-marketing",$A73="thg-seoclarity"),"HOLD — Charlie Stringer to review before deletion",TRUE,"")} | S73: CONFIRMED: NO MODS > 1YR
A74: vibrant-map-107910 | B74: eu | C74: airflow_xcom | D74: No Description | E74: 0.01 | F74: 0 | G74: Active | H74: Low | I74: 56 | J74: 259 | K74: 46141.414 | M74: 2026-04-29 09:56 (ingersolla@thehutgroup.com) | N74: No Write Access (180d) | O74: 45938.387 | P74: =IF($Q74="DELETE",IF($S74="CONFIRMED: NO MODS > 1YR","CONFIRMED: NO MODS > 1YR","DO NOT DELETE — not defensibly confirmed"),IF($Q74="HOLD","DO NOT DELETE — HOLD (Charlie review)",IF($Q74="KEEP","DO NOT DELETE — KEEP",IF(ISNUMBER(SEARCH("REVIEW",$Q74)),"DO NOT DELETE — REVIEW pending",$S74)))) -> CONFIRMED: NO MODS > 1YR | Q74: {=_xlfn.IFS(AND($A74="thg-beauty",ISNUMBER(SEARCH("liveramp",$C74))),"DELETE",$A74="agile-bonbon-662",_xlfn.IFS(LEFT($G74,9)="Tranche 1","DELETE",$C74="Sessions_Level_1_All_Sites","KEEP",ISNUMBER(--$C74),"REVIEW — UA raw logs",$C74="Emag_Reporting","KEEP",$C74="Nutrition_Data_Archived_Tables","KEEP",$C74="EU_Data","KEEP",TRUE,"REVIEW"),OR($A74="thg-influencer",$A74="thg-ingenuity",$A74="thg-central-marketing",$A74="thg-seoclarity"),"HOLD",TRUE,"")} | R74: {=_xlfn.IFS(AND($A74="thg-beauty",ISNUMBER(SEARCH("liveramp",$C74))),"thg-beauty Liveramp dataset — confirmed safe to delete",$A74="agile-bonbon-662",_xlfn.IFS(LEFT($G74,9)="Tranche 1","Tranche 1: cleared",$C74="Sessions_Level_1_All_Sites","Downstream aggregation of UA raw logs — keep if raw tables go",ISNUMBER(--$C74),"UA raw site logs (account ID) — keep pending audit-retention check",$C74="Emag_Reporting","Legacy but likely needed",$C74="Nutrition_Data_Archived_Tables","Worth keeping",$C74="EU_Data","Static lookup tables — scripts still reference (smoke-test risk)",TRUE,"Review"),OR($A74="thg-influencer",$A74="thg-ingenuity",$A74="thg-central-marketing",$A74="thg-seoclarity"),"HOLD — Charlie Stringer to review before deletion",TRUE,"")} | S74: CONFIRMED: NO MODS > 1YR
A75: the-hut-group | B75: europe-west2 | C75: billing | D75: No Description | E75: 0 | F75: 0 | G75: Active | H75: Low | I75: 56 | J75: 187 | K75: 46141.388 | M75: 2026-04-29 09:18 (ingersolla@thehutgroup.com) | N75: No Write Access (180d) | O75: 46009.489 | P75: =IF($Q75="DELETE",IF($S75="CONFIRMED: NO MODS > 1YR","CONFIRMED: NO MODS > 1YR","DO NOT DELETE — not defensibly confirmed"),IF($Q75="HOLD","DO NOT DELETE — HOLD (Charlie review)",IF($Q75="KEEP","DO NOT DELETE — KEEP",IF(ISNUMBER(SEARCH("REVIEW",$Q75)),"DO NOT DELETE — REVIEW pending",$S75)))) -> CONFIRMED: NO MODS > 1YR | Q75: {=_xlfn.IFS(AND($A75="thg-beauty",ISNUMBER(SEARCH("liveramp",$C75))),"DELETE",$A75="agile-bonbon-662",_xlfn.IFS(LEFT($G75,9)="Tranche 1","DELETE",$C75="Sessions_Level_1_All_Sites","KEEP",ISNUMBER(--$C75),"REVIEW — UA raw logs",$C75="Emag_Reporting","KEEP",$C75="Nutrition_Data_Archived_Tables","KEEP",$C75="EU_Data","KEEP",TRUE,"REVIEW"),OR($A75="thg-influencer",$A75="thg-ingenuity",$A75="thg-central-marketing",$A75="thg-seoclarity"),"HOLD",TRUE,"")} | R75: {=_xlfn.IFS(AND($A75="thg-beauty",ISNUMBER(SEARCH("liveramp",$C75))),"thg-beauty Liveramp dataset — confirmed safe to delete",$A75="agile-bonbon-662",_xlfn.IFS(LEFT($G75,9)="Tranche 1","Tranche 1: cleared",$C75="Sessions_Level_1_All_Sites","Downstream aggregation of UA raw logs — keep if raw tables go",ISNUMBER(--$C75),"UA raw site logs (account ID) — keep pending audit-retention check",$C75="Emag_Reporting","Legacy but likely needed",$C75="Nutrition_Data_Archived_Tables","Worth keeping",$C75="EU_Data","Static lookup tables — scripts still reference (smoke-test risk)",TRUE,"Review"),OR($A75="thg-influencer",$A75="thg-ingenuity",$A75="thg-central-marketing",$A75="thg-seoclarity"),"HOLD — Charlie Stringer to review before deletion",TRUE,"")} | S75: CONFIRMED: NO MODS > 1YR
A76: the-hut-group | B76: eu | C76: app_routines | D76: No Description | E76: 0 | F76: 0 | G76: Active | H76: Low | I76: 56 | K76: 46141.387 | M76: 2026-04-29 09:17 (ingersolla@thehutgroup.com) | N76: No Write Access (180d) | P76: =IF($Q76="DELETE",IF($S76="CONFIRMED: NO MODS > 1YR","CONFIRMED: NO MODS > 1YR","DO NOT DELETE — not defensibly confirmed"),IF($Q76="HOLD","DO NOT DELETE — HOLD (Charlie review)",IF($Q76="KEEP","DO NOT DELETE — KEEP",IF(ISNUMBER(SEARCH("REVIEW",$Q76)),"DO NOT DELETE — REVIEW pending",$S76)))) -> REVIEW | Q76: {=_xlfn.IFS(AND($A76="thg-beauty",ISNUMBER(SEARCH("liveramp",$C76))),"DELETE",$A76="agile-bonbon-662",_xlfn.IFS(LEFT($G76,9)="Tranche 1","DELETE",$C76="Sessions_Level_1_All_Sites","KEEP",ISNUMBER(--$C76),"REVIEW — UA raw logs",$C76="Emag_Reporting","KEEP",$C76="Nutrition_Data_Archived_Tables","KEEP",$C76="EU_Data","KEEP",TRUE,"REVIEW"),OR($A76="thg-influencer",$A76="thg-ingenuity",$A76="thg-central-marketing",$A76="thg-seoclarity"),"HOLD",TRUE,"")} | R76: {=_xlfn.IFS(AND($A76="thg-beauty",ISNUMBER(SEARCH("liveramp",$C76))),"thg-beauty Liveramp dataset — confirmed safe to delete",$A76="agile-bonbon-662",_xlfn.IFS(LEFT($G76,9)="Tranche 1","Tranche 1: cleared",$C76="Sessions_Level_1_All_Sites","Downstream aggregation of UA raw logs — keep if raw tables go",ISNUMBER(--$C76),"UA raw site logs (account ID) — keep pending audit-retention check",$C76="Emag_Reporting","Legacy but likely needed",$C76="Nutrition_Data_Archived_Tables","Worth keeping",$C76="EU_Data","Static lookup tables — scripts still reference (smoke-test risk)",TRUE,"Review"),OR($A76="thg-influencer",$A76="thg-ingenuity",$A76="thg-central-marketing",$A76="thg-seoclarity"),"HOLD — Charlie Stringer to review before deletion",TRUE,"")} | S76: REVIEW
A77: the-hut-group | B77: eu | C77: orders_staging | D77: No Description | E77: 0 | F77: 0 | G77: Active | H77: Low | I77: 56 | K77: 46141.388 | M77: 2026-04-29 09:18 (ingersolla@thehutgroup.com) | N77: No Write Access (180d) | P77: =IF($Q77="DELETE",IF($S77="CONFIRMED: NO MODS > 1YR","CONFIRMED: NO MODS > 1YR","DO NOT DELETE — not defensibly confirmed"),IF($Q77="HOLD","DO NOT DELETE — HOLD (Charlie review)",IF($Q77="KEEP","DO NOT DELETE — KEEP",IF(ISNUMBER(SEARCH("REVIEW",$Q77)),"DO NOT DELETE — REVIEW pending",$S77)))) -> CONFIRMED: NO MODS > 1YR | Q77: {=_xlfn.IFS(AND($A77="thg-beauty",ISNUMBER(SEARCH("liveramp",$C77))),"DELETE",$A77="agile-bonbon-662",_xlfn.IFS(LEFT($G77,9)="Tranche 1","DELETE",$C77="Sessions_Level_1_All_Sites","KEEP",ISNUMBER(--$C77),"REVIEW — UA raw logs",$C77="Emag_Reporting","KEEP",$C77="Nutrition_Data_Archived_Tables","KEEP",$C77="EU_Data","KEEP",TRUE,"REVIEW"),OR($A77="thg-influencer",$A77="thg-ingenuity",$A77="thg-central-marketing",$A77="thg-seoclarity"),"HOLD",TRUE,"")} | R77: {=_xlfn.IFS(AND($A77="thg-beauty",ISNUMBER(SEARCH("liveramp",$C77))),"thg-beauty Liveramp dataset — confirmed safe to delete",$A77="agile-bonbon-662",_xlfn.IFS(LEFT($G77,9)="Tranche 1","Tranche 1: cleared",$C77="Sessions_Level_1_All_Sites","Downstream aggregation of UA raw logs — keep if raw tables go",ISNUMBER(--$C77),"UA raw site logs (account ID) — keep pending audit-retention check",$C77="Emag_Reporting","Legacy but likely needed",$C77="Nutrition_Data_Archived_Tables","Worth keeping",$C77="EU_Data","Static lookup tables — scripts still reference (smoke-test risk)",TRUE,"Review"),OR($A77="thg-influencer",$A77="thg-ingenuity",$A77="thg-central-marketing",$A77="thg-seoclarity"),"HOLD — Charlie Stringer to review before deletion",TRUE,"")} | S77: CONFIRMED: NO MODS > 1YR
A78: the-hut-group | B78: eu | C78: mobileapp | D78: No Description | E78: 0 | F78: 0 | G78: Active | H78: Low | I78: 56 | J78: 315 | K78: 46141.388 | M78: 2026-04-29 09:18 (ingersolla@thehutgroup.com) 2026-01-14 03:00 (meirosur@thehutgroup.com) 2026-01-13 03:00 (meirosur@thehutgroup.com) 2026-01-12 03:00 (meirosur@thehutgroup.com) 2026-01-11 03:00 (meirosur@thehutgroup.com) | N78: No Write Access (180d) | O78: 45882.432 | P78: =IF($Q78="DELETE",IF($S78="CONFIRMED: NO MODS > 1YR","CONFIRMED: NO MODS > 1YR","DO NOT DELETE — not defensibly confirmed"),IF($Q78="HOLD","DO NOT DELETE — HOLD (Charlie review)",IF($Q78="KEEP","DO NOT DELETE — KEEP",IF(ISNUMBER(SEARCH("REVIEW",$Q78)),"DO NOT DELETE — REVIEW pending",$S78)))) -> CONFIRMED: NO MODS > 1YR | Q78: {=_xlfn.IFS(AND($A78="thg-beauty",ISNUMBER(SEARCH("liveramp",$C78))),"DELETE",$A78="agile-bonbon-662",_xlfn.IFS(LEFT($G78,9)="Tranche 1","DELETE",$C78="Sessions_Level_1_All_Sites","KEEP",ISNUMBER(--$C78),"REVIEW — UA raw logs",$C78="Emag_Reporting","KEEP",$C78="Nutrition_Data_Archived_Tables","KEEP",$C78="EU_Data","KEEP",TRUE,"REVIEW"),OR($A78="thg-influencer",$A78="thg-ingenuity",$A78="thg-central-marketing",$A78="thg-seoclarity"),"HOLD",TRUE,"")} | R78: {=_xlfn.IFS(AND($A78="thg-beauty",ISNUMBER(SEARCH("liveramp",$C78))),"thg-beauty Liveramp dataset — confirmed safe to delete",$A78="agile-bonbon-662",_xlfn.IFS(LEFT($G78,9)="Tranche 1","Tranche 1: cleared",$C78="Sessions_Level_1_All_Sites","Downstream aggregation of UA raw logs — keep if raw tables go",ISNUMBER(--$C78),"UA raw site logs (account ID) — keep pending audit-retention check",$C78="Emag_Reporting","Legacy but likely needed",$C78="Nutrition_Data_Archived_Tables","Worth keeping",$C78="EU_Data","Static lookup tables — scripts still reference (smoke-test risk)",TRUE,"Review"),OR($A78="thg-influencer",$A78="thg-ingenuity",$A78="thg-central-marketing",$A78="thg-seoclarity"),"HOLD — Charlie Stringer to review before deletion",TRUE,"")} | S78: CONFIRMED: NO MODS > 1YR
A79: the-hut-group | B79: eu | C79: archived_unity_lookup | D79: No Description | E79: 0 | F79: 0 | G79: Active | H79: Low | I79: 56 | K79: 46141.388 | M79: 2026-04-29 09:18 (ingersolla@thehutgroup.com) | N79: No Write Access (180d) | P79: =IF($Q79="DELETE",IF($S79="CONFIRMED: NO MODS > 1YR","CONFIRMED: NO MODS > 1YR","DO NOT DELETE — not defensibly confirmed"),IF($Q79="HOLD","DO NOT DELETE — HOLD (Charlie review)",IF($Q79="KEEP","DO NOT DELETE — KEEP",IF(ISNUMBER(SEARCH("REVIEW",$Q79)),"DO NOT DELETE — REVIEW pending",$S79)))) -> CONFIRMED: NO MODS > 1YR | Q79: {=_xlfn.IFS(AND($A79="thg-beauty",ISNUMBER(SEARCH("liveramp",$C79))),"DELETE",$A79="agile-bonbon-662",_xlfn.IFS(LEFT($G79,9)="Tranche 1","DELETE",$C79="Sessions_Level_1_All_Sites","KEEP",ISNUMBER(--$C79),"REVIEW — UA raw logs",$C79="Emag_Reporting","KEEP",$C79="Nutrition_Data_Archived_Tables","KEEP",$C79="EU_Data","KEEP",TRUE,"REVIEW"),OR($A79="thg-influencer",$A79="thg-ingenuity",$A79="thg-central-marketing",$A79="thg-seoclarity"),"HOLD",TRUE,"")} | R79: {=_xlfn.IFS(AND($A79="thg-beauty",ISNUMBER(SEARCH("liveramp",$C79))),"thg-beauty Liveramp dataset — confirmed safe to delete",$A79="agile-bonbon-662",_xlfn.IFS(LEFT($G79,9)="Tranche 1","Tranche 1: cleared",$C79="Sessions_Level_1_All_Sites","Downstream aggregation of UA raw logs — keep if raw tables go",ISNUMBER(--$C79),"UA raw site logs (account ID) — keep pending audit-retention check",$C79="Emag_Reporting","Legacy but likely needed",$C79="Nutrition_Data_Archived_Tables","Worth keeping",$C79="EU_Data","Static lookup tables — scripts still reference (smoke-test risk)",TRUE,"Review"),OR($A79="thg-influencer",$A79="thg-ingenuity",$A79="thg-central-marketing",$A79="thg-seoclarity"),"HOLD — Charlie Stringer to review before deletion",TRUE,"")} | S79: CONFIRMED: NO MODS > 1YR
A80: the-hut-group | B80: eu | C80: ditto_staging | D80: No Description | E80: 0 | F80: 0 | G80: Active | H80: Low | I80: 56 | K80: 46141.388 | M80: 2026-04-29 09:18 (ingersolla@thehutgroup.com) | N80: No Write Access (180d) | P80: =IF($Q80="DELETE",IF($S80="CONFIRMED: NO MODS > 1YR","CONFIRMED: NO MODS > 1YR","DO NOT DELETE — not defensibly confirmed"),IF($Q80="HOLD","DO NOT DELETE — HOLD (Charlie review)",IF($Q80="KEEP","DO NOT DELETE — KEEP",IF(ISNUMBER(SEARCH("REVIEW",$Q80)),"DO NOT DELETE — REVIEW pending",$S80)))) -> CONFIRMED: NO MODS > 1YR | Q80: {=_xlfn.IFS(AND($A80="thg-beauty",ISNUMBER(SEARCH("liveramp",$C80))),"DELETE",$A80="agile-bonbon-662",_xlfn.IFS(LEFT($G80,9)="Tranche 1","DELETE",$C80="Sessions_Level_1_All_Sites","KEEP",ISNUMBER(--$C80),"REVIEW — UA raw logs",$C80="Emag_Reporting","KEEP",$C80="Nutrition_Data_Archived_Tables","KEEP",$C80="EU_Data","KEEP",TRUE,"REVIEW"),OR($A80="thg-influencer",$A80="thg-ingenuity",$A80="thg-central-marketing",$A80="thg-seoclarity"),"HOLD",TRUE,"")} | R80: {=_xlfn.IFS(AND($A80="thg-beauty",ISNUMBER(SEARCH("liveramp",$C80))),"thg-beauty Liveramp dataset — confirmed safe to delete",$A80="agile-bonbon-662",_xlfn.IFS(LEFT($G80,9)="Tranche 1","Tranche 1: cleared",$C80="Sessions_Level_1_All_Sites","Downstream aggregation of UA raw logs — keep if raw tables go",ISNUMBER(--$C80),"UA raw site logs (account ID) — keep pending audit-retention check",$C80="Emag_Reporting","Legacy but likely needed",$C80="Nutrition_Data_Archived_Tables","Worth keeping",$C80="EU_Data","Static lookup tables — scripts still reference (smoke-test risk)",TRUE,"Review"),OR($A80="thg-influencer",$A80="thg-ingenuity",$A80="thg-central-marketing",$A80="thg-seoclarity"),"HOLD — Charlie Stringer to review before deletion",TRUE,"")} | S80: CONFIRMED: NO MODS > 1YR
A81: the-hut-group | B81: eu | C81: archived_61241944 | D81: No Description | E81: 0 | F81: 0 | G81: Active | H81: Low | I81: 56 | K81: 46141.388 | M81: 2026-04-29 09:18 (ingersolla@thehutgroup.com) | N81: No Write Access (180d) | P81: =IF($Q81="DELETE",IF($S81="CONFIRMED: NO MODS > 1YR","CONFIRMED: NO MODS > 1YR","DO NOT DELETE — not defensibly confirmed"),IF($Q81="HOLD","DO NOT DELETE — HOLD (Charlie review)",IF($Q81="KEEP","DO NOT DELETE — KEEP",IF(ISNUMBER(SEARCH("REVIEW",$Q81)),"DO NOT DELETE — REVIEW pending",$S81)))) -> CONFIRMED: NO MODS > 1YR | Q81: {=_xlfn.IFS(AND($A81="thg-beauty",ISNUMBER(SEARCH("liveramp",$C81))),"DELETE",$A81="agile-bonbon-662",_xlfn.IFS(LEFT($G81,9)="Tranche 1","DELETE",$C81="Sessions_Level_1_All_Sites","KEEP",ISNUMBER(--$C81),"REVIEW — UA raw logs",$C81="Emag_Reporting","KEEP",$C81="Nutrition_Data_Archived_Tables","KEEP",$C81="EU_Data","KEEP",TRUE,"REVIEW"),OR($A81="thg-influencer",$A81="thg-ingenuity",$A81="thg-central-marketing",$A81="thg-seoclarity"),"HOLD",TRUE,"")} | R81: {=_xlfn.IFS(AND($A81="thg-beauty",ISNUMBER(SEARCH("liveramp",$C81))),"thg-beauty Liveramp dataset — confirmed safe to delete",$A81="agile-bonbon-662",_xlfn.IFS(LEFT($G81,9)="Tranche 1","Tranche 1: cleared",$C81="Sessions_Level_1_All_Sites","Downstream aggregation of UA raw logs — keep if raw tables go",ISNUMBER(--$C81),"UA raw site logs (account ID) — keep pending audit-retention check",$C81="Emag_Reporting","Legacy but likely needed",$C81="Nutrition_Data_Archived_Tables","Worth keeping",$C81="EU_Data","Static lookup tables — scripts still reference (smoke-test risk)",TRUE,"Review"),OR($A81="thg-influencer",$A81="thg-ingenuity",$A81="thg-central-marketing",$A81="thg-seoclarity"),"HOLD — Charlie Stringer to review before deletion",TRUE,"")} | S81: CONFIRMED: NO MODS > 1YR
A82: the-hut-group | B82: eu | C82: lfcom_search_accesslogs_0827_0901 | D82: No Description | E82: 0 | F82: 0 | G82: Active | H82: Low | I82: 56 | K82: 46141.388 | M82: 2026-04-29 09:18 (ingersolla@thehutgroup.com) | N82: No Write Access (180d) | P82: =IF($Q82="DELETE",IF($S82="CONFIRMED: NO MODS > 1YR","CONFIRMED: NO MODS > 1YR","DO NOT DELETE — not defensibly confirmed"),IF($Q82="HOLD","DO NOT DELETE — HOLD (Charlie review)",IF($Q82="KEEP","DO NOT DELETE — KEEP",IF(ISNUMBER(SEARCH("REVIEW",$Q82)),"DO NOT DELETE — REVIEW pending",$S82)))) -> CONFIRMED: NO MODS > 1YR | Q82: {=_xlfn.IFS(AND($A82="thg-beauty",ISNUMBER(SEARCH("liveramp",$C82))),"DELETE",$A82="agile-bonbon-662",_xlfn.IFS(LEFT($G82,9)="Tranche 1","DELETE",$C82="Sessions_Level_1_All_Sites","KEEP",ISNUMBER(--$C82),"REVIEW — UA raw logs",$C82="Emag_Reporting","KEEP",$C82="Nutrition_Data_Archived_Tables","KEEP",$C82="EU_Data","KEEP",TRUE,"REVIEW"),OR($A82="thg-influencer",$A82="thg-ingenuity",$A82="thg-central-marketing",$A82="thg-seoclarity"),"HOLD",TRUE,"")} | R82: {=_xlfn.IFS(AND($A82="thg-beauty",ISNUMBER(SEARCH("liveramp",$C82))),"thg-beauty Liveramp dataset — confirmed safe to delete",$A82="agile-bonbon-662",_xlfn.IFS(LEFT($G82,9)="Tranche 1","Tranche 1: cleared",$C82="Sessions_Level_1_All_Sites","Downstream aggregation of UA raw logs — keep if raw tables go",ISNUMBER(--$C82),"UA raw site logs (account ID) — keep pending audit-retention check",$C82="Emag_Reporting","Legacy but likely needed",$C82="Nutrition_Data_Archived_Tables","Worth keeping",$C82="EU_Data","Static lookup tables — scripts still reference (smoke-test risk)",TRUE,"Review"),OR($A82="thg-influencer",$A82="thg-ingenuity",$A82="thg-central-marketing",$A82="thg-seoclarity"),"HOLD — Charlie Stringer to review before deletion",TRUE,"")} | S82: CONFIRMED: NO MODS > 1YR
A83: the-hut-group | B83: eu | C83: archived_gdpr_pipeline | D83: No Description | E83: 0 | F83: 0 | G83: Active | H83: Low | I83: 56 | K83: 46141.388 | M83: 2026-04-29 09:18 (ingersolla@thehutgroup.com) | N83: No Write Access (180d) | P83: =IF($Q83="DELETE",IF($S83="CONFIRMED: NO MODS > 1YR","CONFIRMED: NO MODS > 1YR","DO NOT DELETE — not defensibly confirmed"),IF($Q83="HOLD","DO NOT DELETE — HOLD (Charlie review)",IF($Q83="KEEP","DO NOT DELETE — KEEP",IF(ISNUMBER(SEARCH("REVIEW",$Q83)),"DO NOT DELETE — REVIEW pending",$S83)))) -> CONFIRMED: NO MODS > 1YR | Q83: {=_xlfn.IFS(AND($A83="thg-beauty",ISNUMBER(SEARCH("liveramp",$C83))),"DELETE",$A83="agile-bonbon-662",_xlfn.IFS(LEFT($G83,9)="Tranche 1","DELETE",$C83="Sessions_Level_1_All_Sites","KEEP",ISNUMBER(--$C83),"REVIEW — UA raw logs",$C83="Emag_Reporting","KEEP",$C83="Nutrition_Data_Archived_Tables","KEEP",$C83="EU_Data","KEEP",TRUE,"REVIEW"),OR($A83="thg-influencer",$A83="thg-ingenuity",$A83="thg-central-marketing",$A83="thg-seoclarity"),"HOLD",TRUE,"")} | R83: {=_xlfn.IFS(AND($A83="thg-beauty",ISNUMBER(SEARCH("liveramp",$C83))),"thg-beauty Liveramp dataset — confirmed safe to delete",$A83="agile-bonbon-662",_xlfn.IFS(LEFT($G83,9)="Tranche 1","Tranche 1: cleared",$C83="Sessions_Level_1_All_Sites","Downstream aggregation of UA raw logs — keep if raw tables go",ISNUMBER(--$C83),"UA raw site logs (account ID) — keep pending audit-retention check",$C83="Emag_Reporting","Legacy but likely needed",$C83="Nutrition_Data_Archived_Tables","Worth keeping",$C83="EU_Data","Static lookup tables — scripts still reference (smoke-test risk)",TRUE,"Review"),OR($A83="thg-influencer",$A83="thg-ingenuity",$A83="thg-central-marketing",$A83="thg-seoclarity"),"HOLD — Charlie Stringer to review before deletion",TRUE,"")} | S83: CONFIRMED: NO MODS > 1YR
A84: the-hut-group | B84: eu | C84: Pentland_Data_Send | D84: No Description | E84: 0 | F84: 0 | G84: Active | H84: Low | I84: 56 | K84: 46141.387 | M84: 2026-04-29 09:17 (ingersolla@thehutgroup.com) | N84: No Write Access (180d) | P84: =IF($Q84="DELETE",IF($S84="CONFIRMED: NO MODS > 1YR","CONFIRMED: NO MODS > 1YR","DO NOT DELETE — not defensibly confirmed"),IF($Q84="HOLD","DO NOT DELETE — HOLD (Charlie review)",IF($Q84="KEEP","DO NOT DELETE — KEEP",IF(ISNUMBER(SEARCH("REVIEW",$Q84)),"DO NOT DELETE — REVIEW pending",$S84)))) -> CONFIRMED: NO MODS > 1YR | Q84: {=_xlfn.IFS(AND($A84="thg-beauty",ISNUMBER(SEARCH("liveramp",$C84))),"DELETE",$A84="agile-bonbon-662",_xlfn.IFS(LEFT($G84,9)="Tranche 1","DELETE",$C84="Sessions_Level_1_All_Sites","KEEP",ISNUMBER(--$C84),"REVIEW — UA raw logs",$C84="Emag_Reporting","KEEP",$C84="Nutrition_Data_Archived_Tables","KEEP",$C84="EU_Data","KEEP",TRUE,"REVIEW"),OR($A84="thg-influencer",$A84="thg-ingenuity",$A84="thg-central-marketing",$A84="thg-seoclarity"),"HOLD",TRUE,"")} | R84: {=_xlfn.IFS(AND($A84="thg-beauty",ISNUMBER(SEARCH("liveramp",$C84))),"thg-beauty Liveramp dataset — confirmed safe to delete",$A84="agile-bonbon-662",_xlfn.IFS(LEFT($G84,9)="Tranche 1","Tranche 1: cleared",$C84="Sessions_Level_1_All_Sites","Downstream aggregation of UA raw logs — keep if raw tables go",ISNUMBER(--$C84),"UA raw site logs (account ID) — keep pending audit-retention check",$C84="Emag_Reporting","Legacy but likely needed",$C84="Nutrition_Data_Archived_Tables","Worth keeping",$C84="EU_Data","Static lookup tables — scripts still reference (smoke-test risk)",TRUE,"Review"),OR($A84="thg-influencer",$A84="thg-ingenuity",$A84="thg-central-marketing",$A84="thg-seoclarity"),"HOLD — Charlie Stringer to review before deletion",TRUE,"")} | S84: CONFIRMED: NO MODS > 1YR
A85: the-hut-group | B85: eu | C85: product_visit_events | D85: No Description | E85: 0 | F85: 0 | G85: Active | H85: Low | I85: 56 | K85: 46141.388 | M85: 2026-04-29 09:18 (ingersolla@thehutgroup.com) | N85: No Write Access (180d) | P85: =IF($Q85="DELETE",IF($S85="CONFIRMED: NO MODS > 1YR","CONFIRMED: NO MODS > 1YR","DO NOT DELETE — not defensibly confirmed"),IF($Q85="HOLD","DO NOT DELETE — HOLD (Charlie review)",IF($Q85="KEEP","DO NOT DELETE — KEEP",IF(ISNUMBER(SEARCH("REVIEW",$Q85)),"DO NOT DELETE — REVIEW pending",$S85)))) -> CONFIRMED: NO MODS > 1YR | Q85: {=_xlfn.IFS(AND($A85="thg-beauty",ISNUMBER(SEARCH("liveramp",$C85))),"DELETE",$A85="agile-bonbon-662",_xlfn.IFS(LEFT($G85,9)="Tranche 1","DELETE",$C85="Sessions_Level_1_All_Sites","KEEP",ISNUMBER(--$C85),"REVIEW — UA raw logs",$C85="Emag_Reporting","KEEP",$C85="Nutrition_Data_Archived_Tables","KEEP",$C85="EU_Data","KEEP",TRUE,"REVIEW"),OR($A85="thg-influencer",$A85="thg-ingenuity",$A85="thg-central-marketing",$A85="thg-seoclarity"),"HOLD",TRUE,"")} | R85: {=_xlfn.IFS(AND($A85="thg-beauty",ISNUMBER(SEARCH("liveramp",$C85))),"thg-beauty Liveramp dataset — confirmed safe to delete",$A85="agile-bonbon-662",_xlfn.IFS(LEFT($G85,9)="Tranche 1","Tranche 1: cleared",$C85="Sessions_Level_1_All_Sites","Downstream aggregation of UA raw logs — keep if raw tables go",ISNUMBER(--$C85),"UA raw site logs (account ID) — keep pending audit-retention check",$C85="Emag_Reporting","Legacy but likely needed",$C85="Nutrition_Data_Archived_Tables","Worth keeping",$C85="EU_Data","Static lookup tables — scripts still reference (smoke-test risk)",TRUE,"Review"),OR($A85="thg-influencer",$A85="thg-ingenuity",$A85="thg-central-marketing",$A85="thg-seoclarity"),"HOLD — Charlie Stringer to review before deletion",TRUE,"")} | S85: CONFIRMED: NO MODS > 1YR
A86: the-hut-group | B86: eu | C86: Pricing | D86: No Description | E86: 0 | F86: 0 | G86: Active | H86: Low | I86: 56 | K86: 46141.387 | M86: 2026-04-29 09:17 (ingersolla@thehutgroup.com) | N86: No Write Access (180d) | P86: =IF($Q86="DELETE",IF($S86="CONFIRMED: NO MODS > 1YR","CONFIRMED: NO MODS > 1YR","DO NOT DELETE — not defensibly confirmed"),IF($Q86="HOLD","DO NOT DELETE — HOLD (Charlie review)",IF($Q86="KEEP","DO NOT DELETE — KEEP",IF(ISNUMBER(SEARCH("REVIEW",$Q86)),"DO NOT DELETE — REVIEW pending",$S86)))) -> CONFIRMED: NO MODS > 1YR | Q86: {=_xlfn.IFS(AND($A86="thg-beauty",ISNUMBER(SEARCH("liveramp",$C86))),"DELETE",$A86="agile-bonbon-662",_xlfn.IFS(LEFT($G86,9)="Tranche 1","DELETE",$C86="Sessions_Level_1_All_Sites","KEEP",ISNUMBER(--$C86),"REVIEW — UA raw logs",$C86="Emag_Reporting","KEEP",$C86="Nutrition_Data_Archived_Tables","KEEP",$C86="EU_Data","KEEP",TRUE,"REVIEW"),OR($A86="thg-influencer",$A86="thg-ingenuity",$A86="thg-central-marketing",$A86="thg-seoclarity"),"HOLD",TRUE,"")} | R86: {=_xlfn.IFS(AND($A86="thg-beauty",ISNUMBER(SEARCH("liveramp",$C86))),"thg-beauty Liveramp dataset — confirmed safe to delete",$A86="agile-bonbon-662",_xlfn.IFS(LEFT($G86,9)="Tranche 1","Tranche 1: cleared",$C86="Sessions_Level_1_All_Sites","Downstream aggregation of UA raw logs — keep if raw tables go",ISNUMBER(--$C86),"UA raw site logs (account ID) — keep pending audit-retention check",$C86="Emag_Reporting","Legacy but likely needed",$C86="Nutrition_Data_Archived_Tables","Worth keeping",$C86="EU_Data","Static lookup tables — scripts still reference (smoke-test risk)",TRUE,"Review"),OR($A86="thg-influencer",$A86="thg-ingenuity",$A86="thg-central-marketing",$A86="thg-seoclarity"),"HOLD — Charlie Stringer to review before deletion",TRUE,"")} | S86: CONFIRMED: NO MODS > 1YR
A87: the-hut-group | B87: eu | C87: search_team_analysis | D87: No Description | E87: 0 | F87: 0 | G87: Active | H87: Low | I87: 56 | K87: 46141.388 | M87: 2026-04-29 09:19 (ingersolla@thehutgroup.com) | N87: No Write Access (180d) | P87: =IF($Q87="DELETE",IF($S87="CONFIRMED: NO MODS > 1YR","CONFIRMED: NO MODS > 1YR","DO NOT DELETE — not defensibly confirmed"),IF($Q87="HOLD","DO NOT DELETE — HOLD (Charlie review)",IF($Q87="KEEP","DO NOT DELETE — KEEP",IF(ISNUMBER(SEARCH("REVIEW",$Q87)),"DO NOT DELETE — REVIEW pending",$S87)))) -> CONFIRMED: NO MODS > 1YR | Q87: {=_xlfn.IFS(AND($A87="thg-beauty",ISNUMBER(SEARCH("liveramp",$C87))),"DELETE",$A87="agile-bonbon-662",_xlfn.IFS(LEFT($G87,9)="Tranche 1","DELETE",$C87="Sessions_Level_1_All_Sites","KEEP",ISNUMBER(--$C87),"REVIEW — UA raw logs",$C87="Emag_Reporting","KEEP",$C87="Nutrition_Data_Archived_Tables","KEEP",$C87="EU_Data","KEEP",TRUE,"REVIEW"),OR($A87="thg-influencer",$A87="thg-ingenuity",$A87="thg-central-marketing",$A87="thg-seoclarity"),"HOLD",TRUE,"")} | R87: {=_xlfn.IFS(AND($A87="thg-beauty",ISNUMBER(SEARCH("liveramp",$C87))),"thg-beauty Liveramp dataset — confirmed safe to delete",$A87="agile-bonbon-662",_xlfn.IFS(LEFT($G87,9)="Tranche 1","Tranche 1: cleared",$C87="Sessions_Level_1_All_Sites","Downstream aggregation of UA raw logs — keep if raw tables go",ISNUMBER(--$C87),"UA raw site logs (account ID) — keep pending audit-retention check",$C87="Emag_Reporting","Legacy but likely needed",$C87="Nutrition_Data_Archived_Tables","Worth keeping",$C87="EU_Data","Static lookup tables — scripts still reference (smoke-test risk)",TRUE,"Review"),OR($A87="thg-influencer",$A87="thg-ingenuity",$A87="thg-central-marketing",$A87="thg-seoclarity"),"HOLD — Charlie Stringer to review before deletion",TRUE,"")} | S87: CONFIRMED: NO MODS > 1YR
